Workbook

Sheet How to use
A1: Turo Fleet Tracker — path to $300k/yr net
A2: Educational tool only. Not financial, tax or legal advice. Verify insurance, tax and permits locally.
A4: Step 1 | B4: Assumptions tab: set your goal, start month and targets (yellow cells).
A5: Step 2 | B5: Fleet tab: one row per car. Fixed monthly costs (loan, insurance, registration, tracker, parking) go here — NOT in Expenses.
A6: Step 3 | B6: Trips tab: log every trip from your Turo earnings export. Days, host share, earnings and month fill in automatically.
A7: Step 4 | B7: Expenses tab: log variable costs (maintenance, tires, repairs, supplies, software). Use Car ID 'FLEET' for overhead.
A8: Step 5 | B8: Each month: move the Report month on Assumptions forward, then check Car Scorecard and see each car's net, utilization and payback. Cut any car flagged '3 losing months'.
A9: Step 6 | B9: Dashboard: 12-month P&L, run-rate and how many cars you need at today's net per car.
A10: Step 7 | B10: Buy Box: test a car before you buy it. Only buy 'BUY' verdicts.
A12: Colour legend
A13: Blue text, pale yellow fill | B13: Inputs you type in.
A14: Bright yellow fill | B14: Key assumptions that drive the whole workbook.
A15: Black text | B15: Formulas — do not overwrite.
A16: Green text | B16: Pulled from another tab.
A18: Example rows | B18: Rows whose Notes say 'EXAMPLE – delete' show the expected format. Clear them before you start.
A19: Trip timing | B19: Trips are counted in the month they START. A trip spanning month-end counts fully in the start month.
A20: Host share | B20: Trips use the car's earnings-plan share from Fleet; if blank, the default on Assumptions. US plans pay 70/80/90% of trip price (Turo help centre, Jan 2026) — re-check, Turo changes terms.
A21: Not modelled | B21: Depreciation / resale value, income tax, owner's time. Track resale value separately when you sell a car.

Sheet Dashboard
A1: Dashboard — 12-month P&L
A2: All figures are formulas. Trips count in the month they start.
A4: Annual goal | C4: Net profit (12 mo) | E4: % of goal | G4: Report-month run-rate | I4: Cars owned (that month) | K4: Cars needed at that net/car | M4: Cash reserve to hold
A5: =Assumptions!$B$4 -> 300000 | C5: =K22 -> -293.2 | E5: =IF(Assumptions!$B$4=0,0,K22/Assumptions!$B$4) -> -0.00097733333 | G5: =IFERROR(INDEX(M10:M21,MATCH(Assumptions!$B$6,A10:A21,0)),0) -> -3518.4 | I5: =IFERROR(INDEX(B10:B21,MATCH(Assumptions!$B$6,A10:A21,0)),0) -> 2 | K5: =IFERROR(INDEX(N10:N21,MATCH(Assumptions!$B$6,A10:A21,0)),"n/a") -> n/a | M5: =IFERROR(INDEX(B10:B21,MATCH(Assumptions!$B$6,A10:A21,0))*Assumptions!$B$11*(INDEX(I10:I21,MATCH(Assumptions!$B$6,A10:A21,0))+INDEX(J10:J21,MATCH(Assumptions!$B$6,A10:A21,0)))/MAX(1,INDEX(B10:B21,MATCH(Assumptions!$B$6,A10:A21,0))),0) -> 2576
A7: Rows show months up to the Report month (Assumptions tab). Tiles use the Report month. Cars bought mid-month carry a full month of fixed cost.
A9: Month | B9: Cars owned | C9: Available car-days | D9: Booked days | E9: Utilization | F9: Trips | G9: Gross trip price ($) | H9: Earnings + extras ($) | I9: Variable costs ($) | J9: Fixed costs ($) | K9: Net profit ($) | L9: Net per car ($) | M9: Annualized run-rate ($) | N9: Cars needed for goal (at this net/car)
A10: =Assumptions!$B$5 -> 46327 | B10: =IF($A10>Assumptions!$B$6,"",SUMPRODUCT(((Fleet!$A$5:$A$79<>"")*(Fleet!$E$5:$E$79<=EOMONTH($A10,0))*(((Fleet!$F$5:$F$79="")+(Fleet!$F$5:$F$79>=$A10))>0)))) -> 2 | C10: =IF($A10>Assumptions!$B$6,"",B10*DAY(EOMONTH($A10,0))) -> 60 | D10: =IF($A10>Assumptions!$B$6,"",SUMIFS(Trips!$E$5:$E$1004,Trips!$L$5:$L$1004,$A10)) -> 19 | E10: =IF($A10>Assumptions!$B$6,"",IF(C10=0,0,D10/C10)) -> 0.31666667 | F10: =IF($A10>Assumptions!$B$6,"",COUNTIFS(Trips!$L$5:$L$1004,$A10)) -> 4 | G10: =IF($A10>Assumptions!$B$6,"",SUMIFS(Trips!$F$5:$F$1004,Trips!$L$5:$L$1004,$A10)) -> 1206 | H10: =IF($A10>Assumptions!$B$6,"",SUMIFS(Trips!$H$5:$H$1004,Trips!$L$5:$L$1004,$A10)+SUMIFS(Trips!$I$5:$I$1004,Trips!$L$5:$L$1004,$A10)) -> 994.8 | I10: =IF($A10>Assumptions!$B$6,"",SUMIFS(Trips!$J$5:$J$1004,Trips!$L$5:$L$1004,$A10)+SUMIFS(Expenses!$E$5:$E$1004,Expenses!$G$5:$G$1004,$A10)) -> 323 | J10: =IF($A10>Assumptions!$B$6,"",SUMPRODUCT(((Fleet!$A$5:$A$79<>"")*(Fleet!$E$5:$E$79<=EOMONTH($A10,0))*(((Fleet!$F$5:$F$79="")+(Fleet!$F$5:$F$79>=$A10))>0))*Fleet!$O$5:$O$79)) -> 965 | K10: =IF($A10>Assumptions!$B$6,"",H10-I10-J10) -> -293.2 | L10: =IF($A10>Assumptions!$B$6,"",IF(B10=0,0,K10/B10)) -> -146.6 | M10: =IF($A10>Assumptions!$B$6,"",K10*12) -> -3518.4 | N10: =IF($A10>Assumptions!$B$6,"",IF(L10<=0,"n/a",Assumptions!$B$4/12/L10)) -> n/a
A11: =EDATE(A10,1) -> 46357 | B11: =IF($A11>Assumptions!$B$6,"",SUMPRODUCT(((Fleet!$A$5:$A$79<>"")*(Fleet!$E$5:$E$79<=EOMONTH($A11,0))*(((Fleet!$F$5:$F$79="")+(Fleet!$F$5:$F$79>=$A11))>0)))) | C11: =IF($A11>Assumptions!$B$6,"",B11*DAY(EOMONTH($A11,0))) | D11: =IF($A11>Assumptions!$B$6,"",SUMIFS(Trips!$E$5:$E$1004,Trips!$L$5:$L$1004,$A11)) | E11: =IF($A11>Assumptions!$B$6,"",IF(C11=0,0,D11/C11)) | F11: =IF($A11>Assumptions!$B$6,"",COUNTIFS(Trips!$L$5:$L$1004,$A11)) | G11: =IF($A11>Assumptions!$B$6,"",SUMIFS(Trips!$F$5:$F$1004,Trips!$L$5:$L$1004,$A11)) | H11: =IF($A11>Assumptions!$B$6,"",SUMIFS(Trips!$H$5:$H$1004,Trips!$L$5:$L$1004,$A11)+SUMIFS(Trips!$I$5:$I$1004,Trips!$L$5:$L$1004,$A11)) | I11: =IF($A11>Assumptions!$B$6,"",SUMIFS(Trips!$J$5:$J$1004,Trips!$L$5:$L$1004,$A11)+SUMIFS(Expenses!$E$5:$E$1004,Expenses!$G$5:$G$1004,$A11)) | J11: =IF($A11>Assumptions!$B$6,"",SUMPRODUCT(((Fleet!$A$5:$A$79<>"")*(Fleet!$E$5:$E$79<=EOMONTH($A11,0))*(((Fleet!$F$5:$F$79="")+(Fleet!$F$5:$F$79>=$A11))>0))*Fleet!$O$5:$O$79)) | K11: =IF($A11>Assumptions!$B$6,"",H11-I11-J11) | L11: =IF($A11>Assumptions!$B$6,"",IF(B11=0,0,K11/B11)) | M11: =IF($A11>Assumptions!$B$6,"",K11*12) | N11: =IF($A11>Assumptions!$B$6,"",IF(L11<=0,"n/a",Assumptions!$B$4/12/L11))
A12: =EDATE(A11,1) -> 46388 | B12: =IF($A12>Assumptions!$B$6,"",SUMPRODUCT(((Fleet!$A$5:$A$79<>"")*(Fleet!$E$5:$E$79<=EOMONTH($A12,0))*(((Fleet!$F$5:$F$79="")+(Fleet!$F$5:$F$79>=$A12))>0)))) | C12: =IF($A12>Assumptions!$B$6,"",B12*DAY(EOMONTH($A12,0))) | D12: =IF($A12>Assumptions!$B$6,"",SUMIFS(Trips!$E$5:$E$1004,Trips!$L$5:$L$1004,$A12)) | E12: =IF($A12>Assumptions!$B$6,"",IF(C12=0,0,D12/C12)) | F12: =IF($A12>Assumptions!$B$6,"",COUNTIFS(Trips!$L$5:$L$1004,$A12)) | G12: =IF($A12>Assumptions!$B$6,"",SUMIFS(Trips!$F$5:$F$1004,Trips!$L$5:$L$1004,$A12)) | H12: =IF($A12>Assumptions!$B$6,"",SUMIFS(Trips!$H$5:$H$1004,Trips!$L$5:$L$1004,$A12)+SUMIFS(Trips!$I$5:$I$1004,Trips!$L$5:$L$1004,$A12)) | I12: =IF($A12>Assumptions!$B$6,"",SUMIFS(Trips!$J$5:$J$1004,Trips!$L$5:$L$1004,$A12)+SUMIFS(Expenses!$E$5:$E$1004,Expenses!$G$5:$G$1004,$A12)) | J12: =IF($A12>Assumptions!$B$6,"",SUMPRODUCT(((Fleet!$A$5:$A$79<>"")*(Fleet!$E$5:$E$79<=EOMONTH($A12,0))*(((Fleet!$F$5:$F$79="")+(Fleet!$F$5:$F$79>=$A12))>0))*Fleet!$O$5:$O$79)) | K12: =IF($A12>Assumptions!$B$6,"",H12-I12-J12) | L12: =IF($A12>Assumptions!$B$6,"",IF(B12=0,0,K12/B12)) | M12: =IF($A12>Assumptions!$B$6,"",K12*12) | N12: =IF($A12>Assumptions!$B$6,"",IF(L12<=0,"n/a",Assumptions!$B$4/12/L12))
A13: =EDATE(A12,1) -> 46419 | B13: =IF($A13>Assumptions!$B$6,"",SUMPRODUCT(((Fleet!$A$5:$A$79<>"")*(Fleet!$E$5:$E$79<=EOMONTH($A13,0))*(((Fleet!$F$5:$F$79="")+(Fleet!$F$5:$F$79>=$A13))>0)))) | C13: =IF($A13>Assumptions!$B$6,"",B13*DAY(EOMONTH($A13,0))) | D13: =IF($A13>Assumptions!$B$6,"",SUMIFS(Trips!$E$5:$E$1004,Trips!$L$5:$L$1004,$A13)) | E13: =IF($A13>Assumptions!$B$6,"",IF(C13=0,0,D13/C13)) | F13: =IF($A13>Assumptions!$B$6,"",COUNTIFS(Trips!$L$5:$L$1004,$A13)) | G13: =IF($A13>Assumptions!$B$6,"",SUMIFS(Trips!$F$5:$F$1004,Trips!$L$5:$L$1004,$A13)) | H13: =IF($A13>Assumptions!$B$6,"",SUMIFS(Trips!$H$5:$H$1004,Trips!$L$5:$L$1004,$A13)+SUMIFS(Trips!$I$5:$I$1004,Trips!$L$5:$L$1004,$A13)) | I13: =IF($A13>Assumptions!$B$6,"",SUMIFS(Trips!$J$5:$J$1004,Trips!$L$5:$L$1004,$A13)+SUMIFS(Expenses!$E$5:$E$1004,Expenses!$G$5:$G$1004,$A13)) | J13: =IF($A13>Assumptions!$B$6,"",SUMPRODUCT(((Fleet!$A$5:$A$79<>"")*(Fleet!$E$5:$E$79<=EOMONTH($A13,0))*(((Fleet!$F$5:$F$79="")+(Fleet!$F$5:$F$79>=$A13))>0))*Fleet!$O$5:$O$79)) | K13: =IF($A13>Assumptions!$B$6,"",H13-I13-J13) | L13: =IF($A13>Assumptions!$B$6,"",IF(B13=0,0,K13/B13)) | M13: =IF($A13>Assumptions!$B$6,"",K13*12) | N13: =IF($A13>Assumptions!$B$6,"",IF(L13<=0,"n/a",Assumptions!$B$4/12/L13))
A14: =EDATE(A13,1) -> 46447 | B14: =IF($A14>Assumptions!$B$6,"",SUMPRODUCT(((Fleet!$A$5:$A$79<>"")*(Fleet!$E$5:$E$79<=EOMONTH($A14,0))*(((Fleet!$F$5:$F$79="")+(Fleet!$F$5:$F$79>=$A14))>0)))) | C14: =IF($A14>Assumptions!$B$6,"",B14*DAY(EOMONTH($A14,0))) | D14: =IF($A14>Assumptions!$B$6,"",SUMIFS(Trips!$E$5:$E$1004,Trips!$L$5:$L$1004,$A14)) | E14: =IF($A14>Assumptions!$B$6,"",IF(C14=0,0,D14/C14)) | F14: =IF($A14>Assumptions!$B$6,"",COUNTIFS(Trips!$L$5:$L$1004,$A14)) | G14: =IF($A14>Assumptions!$B$6,"",SUMIFS(Trips!$F$5:$F$1004,Trips!$L$5:$L$1004,$A14)) | H14: =IF($A14>Assumptions!$B$6,"",SUMIFS(Trips!$H$5:$H$1004,Trips!$L$5:$L$1004,$A14)+SUMIFS(Trips!$I$5:$I$1004,Trips!$L$5:$L$1004,$A14)) | I14: =IF($A14>Assumptions!$B$6,"",SUMIFS(Trips!$J$5:$J$1004,Trips!$L$5:$L$1004,$A14)+SUMIFS(Expenses!$E$5:$E$1004,Expenses!$G$5:$G$1004,$A14)) | J14: =IF($A14>Assumptions!$B$6,"",SUMPRODUCT(((Fleet!$A$5:$A$79<>"")*(Fleet!$E$5:$E$79<=EOMONTH($A14,0))*(((Fleet!$F$5:$F$79="")+(Fleet!$F$5:$F$79>=$A14))>0))*Fleet!$O$5:$O$79)) | K14: =IF($A14>Assumptions!$B$6,"",H14-I14-J14) | L14: =IF($A14>Assumptions!$B$6,"",IF(B14=0,0,K14/B14)) | M14: =IF($A14>Assumptions!$B$6,"",K14*12) | N14: =IF($A14>Assumptions!$B$6,"",IF(L14<=0,"n/a",Assumptions!$B$4/12/L14))
A15: =EDATE(A14,1) -> 46478 | B15: =IF($A15>Assumptions!$B$6,"",SUMPRODUCT(((Fleet!$A$5:$A$79<>"")*(Fleet!$E$5:$E$79<=EOMONTH($A15,0))*(((Fleet!$F$5:$F$79="")+(Fleet!$F$5:$F$79>=$A15))>0)))) | C15: =IF($A15>Assumptions!$B$6,"",B15*DAY(EOMONTH($A15,0))) | D15: =IF($A15>Assumptions!$B$6,"",SUMIFS(Trips!$E$5:$E$1004,Trips!$L$5:$L$1004,$A15)) | E15: =IF($A15>Assumptions!$B$6,"",IF(C15=0,0,D15/C15)) | F15: =IF($A15>Assumptions!$B$6,"",COUNTIFS(Trips!$L$5:$L$1004,$A15)) | G15: =IF($A15>Assumptions!$B$6,"",SUMIFS(Trips!$F$5:$F$1004,Trips!$L$5:$L$1004,$A15)) | H15: =IF($A15>Assumptions!$B$6,"",SUMIFS(Trips!$H$5:$H$1004,Trips!$L$5:$L$1004,$A15)+SUMIFS(Trips!$I$5:$I$1004,Trips!$L$5:$L$1004,$A15)) | I15: =IF($A15>Assumptions!$B$6,"",SUMIFS(Trips!$J$5:$J$1004,Trips!$L$5:$L$1004,$A15)+SUMIFS(Expenses!$E$5:$E$1004,Expenses!$G$5:$G$1004,$A15)) | J15: =IF($A15>Assumptions!$B$6,"",SUMPRODUCT(((Fleet!$A$5:$A$79<>"")*(Fleet!$E$5:$E$79<=EOMONTH($A15,0))*(((Fleet!$F$5:$F$79="")+(Fleet!$F$5:$F$79>=$A15))>0))*Fleet!$O$5:$O$79)) | K15: =IF($A15>Assumptions!$B$6,"",H15-I15-J15) | L15: =IF($A15>Assumptions!$B$6,"",IF(B15=0,0,K15/B15)) | M15: =IF($A15>Assumptions!$B$6,"",K15*12) | N15: =IF($A15>Assumptions!$B$6,"",IF(L15<=0,"n/a",Assumptions!$B$4/12/L15))
A16: =EDATE(A15,1) -> 46508 | B16: =IF($A16>Assumptions!$B$6,"",SUMPRODUCT(((Fleet!$A$5:$A$79<>"")*(Fleet!$E$5:$E$79<=EOMONTH($A16,0))*(((Fleet!$F$5:$F$79="")+(Fleet!$F$5:$F$79>=$A16))>0)))) | C16: =IF($A16>Assumptions!$B$6,"",B16*DAY(EOMONTH($A16,0))) | D16: =IF($A16>Assumptions!$B$6,"",SUMIFS(Trips!$E$5:$E$1004,Trips!$L$5:$L$1004,$A16)) | E16: =IF($A16>Assumptions!$B$6,"",IF(C16=0,0,D16/C16)) | F16: =IF($A16>Assumptions!$B$6,"",COUNTIFS(Trips!$L$5:$L$1004,$A16)) | G16: =IF($A16>Assumptions!$B$6,"",SUMIFS(Trips!$F$5:$F$1004,Trips!$L$5:$L$1004,$A16)) | H16: =IF($A16>Assumptions!$B$6,"",SUMIFS(Trips!$H$5:$H$1004,Trips!$L$5:$L$1004,$A16)+SUMIFS(Trips!$I$5:$I$1004,Trips!$L$5:$L$1004,$A16)) | I16: =IF($A16>Assumptions!$B$6,"",SUMIFS(Trips!$J$5:$J$1004,Trips!$L$5:$L$1004,$A16)+SUMIFS(Expenses!$E$5:$E$1004,Expenses!$G$5:$G$1004,$A16)) | J16: =IF($A16>Assumptions!$B$6,"",SUMPRODUCT(((Fleet!$A$5:$A$79<>"")*(Fleet!$E$5:$E$79<=EOMONTH($A16,0))*(((Fleet!$F$5:$F$79="")+(Fleet!$F$5:$F$79>=$A16))>0))*Fleet!$O$5:$O$79)) | K16: =IF($A16>Assumptions!$B$6,"",H16-I16-J16) | L16: =IF($A16>Assumptions!$B$6,"",IF(B16=0,0,K16/B16)) | M16: =IF($A16>Assumptions!$B$6,"",K16*12) | N16: =IF($A16>Assumptions!$B$6,"",IF(L16<=0,"n/a",Assumptions!$B$4/12/L16))
A17: =EDATE(A16,1) -> 46539 | B17: =IF($A17>Assumptions!$B$6,"",SUMPRODUCT(((Fleet!$A$5:$A$79<>"")*(Fleet!$E$5:$E$79<=EOMONTH($A17,0))*(((Fleet!$F$5:$F$79="")+(Fleet!$F$5:$F$79>=$A17))>0)))) | C17: =IF($A17>Assumptions!$B$6,"",B17*DAY(EOMONTH($A17,0))) | D17: =IF($A17>Assumptions!$B$6,"",SUMIFS(Trips!$E$5:$E$1004,Trips!$L$5:$L$1004,$A17)) | E17: =IF($A17>Assumptions!$B$6,"",IF(C17=0,0,D17/C17)) | F17: =IF($A17>Assumptions!$B$6,"",COUNTIFS(Trips!$L$5:$L$1004,$A17)) | G17: =IF($A17>Assumptions!$B$6,"",SUMIFS(Trips!$F$5:$F$1004,Trips!$L$5:$L$1004,$A17)) | H17: =IF($A17>Assumptions!$B$6,"",SUMIFS(Trips!$H$5:$H$1004,Trips!$L$5:$L$1004,$A17)+SUMIFS(Trips!$I$5:$I$1004,Trips!$L$5:$L$1004,$A17)) | I17: =IF($A17>Assumptions!$B$6,"",SUMIFS(Trips!$J$5:$J$1004,Trips!$L$5:$L$1004,$A17)+SUMIFS(Expenses!$E$5:$E$1004,Expenses!$G$5:$G$1004,$A17)) | J17: =IF($A17>Assumptions!$B$6,"",SUMPRODUCT(((Fleet!$A$5:$A$79<>"")*(Fleet!$E$5:$E$79<=EOMONTH($A17,0))*(((Fleet!$F$5:$F$79="")+(Fleet!$F$5:$F$79>=$A17))>0))*Fleet!$O$5:$O$79)) | K17: =IF($A17>Assumptions!$B$6,"",H17-I17-J17) | L17: =IF($A17>Assumptions!$B$6,"",IF(B17=0,0,K17/B17)) | M17: =IF($A17>Assumptions!$B$6,"",K17*12) | N17: =IF($A17>Assumptions!$B$6,"",IF(L17<=0,"n/a",Assumptions!$B$4/12/L17))
A18: =EDATE(A17,1) -> 46569 | B18: =IF($A18>Assumptions!$B$6,"",SUMPRODUCT(((Fleet!$A$5:$A$79<>"")*(Fleet!$E$5:$E$79<=EOMONTH($A18,0))*(((Fleet!$F$5:$F$79="")+(Fleet!$F$5:$F$79>=$A18))>0)))) | C18: =IF($A18>Assumptions!$B$6,"",B18*DAY(EOMONTH($A18,0))) | D18: =IF($A18>Assumptions!$B$6,"",SUMIFS(Trips!$E$5:$E$1004,Trips!$L$5:$L$1004,$A18)) | E18: =IF($A18>Assumptions!$B$6,"",IF(C18=0,0,D18/C18)) | F18: =IF($A18>Assumptions!$B$6,"",COUNTIFS(Trips!$L$5:$L$1004,$A18)) | G18: =IF($A18>Assumptions!$B$6,"",SUMIFS(Trips!$F$5:$F$1004,Trips!$L$5:$L$1004,$A18)) | H18: =IF($A18>Assumptions!$B$6,"",SUMIFS(Trips!$H$5:$H$1004,Trips!$L$5:$L$1004,$A18)+SUMIFS(Trips!$I$5:$I$1004,Trips!$L$5:$L$1004,$A18)) | I18: =IF($A18>Assumptions!$B$6,"",SUMIFS(Trips!$J$5:$J$1004,Trips!$L$5:$L$1004,$A18)+SUMIFS(Expenses!$E$5:$E$1004,Expenses!$G$5:$G$1004,$A18)) | J18: =IF($A18>Assumptions!$B$6,"",SUMPRODUCT(((Fleet!$A$5:$A$79<>"")*(Fleet!$E$5:$E$79<=EOMONTH($A18,0))*(((Fleet!$F$5:$F$79="")+(Fleet!$F$5:$F$79>=$A18))>0))*Fleet!$O$5:$O$79)) | K18: =IF($A18>Assumptions!$B$6,"",H18-I18-J18) | L18: =IF($A18>Assumptions!$B$6,"",IF(B18=0,0,K18/B18)) | M18: =IF($A18>Assumptions!$B$6,"",K18*12) | N18: =IF($A18>Assumptions!$B$6,"",IF(L18<=0,"n/a",Assumptions!$B$4/12/L18))
A19: =EDATE(A18,1) -> 46600 | B19: =IF($A19>Assumptions!$B$6,"",SUMPRODUCT(((Fleet!$A$5:$A$79<>"")*(Fleet!$E$5:$E$79<=EOMONTH($A19,0))*(((Fleet!$F$5:$F$79="")+(Fleet!$F$5:$F$79>=$A19))>0)))) | C19: =IF($A19>Assumptions!$B$6,"",B19*DAY(EOMONTH($A19,0))) | D19: =IF($A19>Assumptions!$B$6,"",SUMIFS(Trips!$E$5:$E$1004,Trips!$L$5:$L$1004,$A19)) | E19: =IF($A19>Assumptions!$B$6,"",IF(C19=0,0,D19/C19)) | F19: =IF($A19>Assumptions!$B$6,"",COUNTIFS(Trips!$L$5:$L$1004,$A19)) | G19: =IF($A19>Assumptions!$B$6,"",SUMIFS(Trips!$F$5:$F$1004,Trips!$L$5:$L$1004,$A19)) | H19: =IF($A19>Assumptions!$B$6,"",SUMIFS(Trips!$H$5:$H$1004,Trips!$L$5:$L$1004,$A19)+SUMIFS(Trips!$I$5:$I$1004,Trips!$L$5:$L$1004,$A19)) | I19: =IF($A19>Assumptions!$B$6,"",SUMIFS(Trips!$J$5:$J$1004,Trips!$L$5:$L$1004,$A19)+SUMIFS(Expenses!$E$5:$E$1004,Expenses!$G$5:$G$1004,$A19)) | J19: =IF($A19>Assumptions!$B$6,"",SUMPRODUCT(((Fleet!$A$5:$A$79<>"")*(Fleet!$E$5:$E$79<=EOMONTH($A19,0))*(((Fleet!$F$5:$F$79="")+(Fleet!$F$5:$F$79>=$A19))>0))*Fleet!$O$5:$O$79)) | K19: =IF($A19>Assumptions!$B$6,"",H19-I19-J19) | L19: =IF($A19>Assumptions!$B$6,"",IF(B19=0,0,K19/B19)) | M19: =IF($A19>Assumptions!$B$6,"",K19*12) | N19: =IF($A19>Assumptions!$B$6,"",IF(L19<=0,"n/a",Assumptions!$B$4/12/L19))
A20: =EDATE(A19,1) -> 46631 | B20: =IF($A20>Assumptions!$B$6,"",SUMPRODUCT(((Fleet!$A$5:$A$79<>"")*(Fleet!$E$5:$E$79<=EOMONTH($A20,0))*(((Fleet!$F$5:$F$79="")+(Fleet!$F$5:$F$79>=$A20))>0)))) | C20: =IF($A20>Assumptions!$B$6,"",B20*DAY(EOMONTH($A20,0))) | D20: =IF($A20>Assumptions!$B$6,"",SUMIFS(Trips!$E$5:$E$1004,Trips!$L$5:$L$1004,$A20)) | E20: =IF($A20>Assumptions!$B$6,"",IF(C20=0,0,D20/C20)) | F20: =IF($A20>Assumptions!$B$6,"",COUNTIFS(Trips!$L$5:$L$1004,$A20)) | G20: =IF($A20>Assumptions!$B$6,"",SUMIFS(Trips!$F$5:$F$1004,Trips!$L$5:$L$1004,$A20)) | H20: =IF($A20>Assumptions!$B$6,"",SUMIFS(Trips!$H$5:$H$1004,Trips!$L$5:$L$1004,$A20)+SUMIFS(Trips!$I$5:$I$1004,Trips!$L$5:$L$1004,$A20)) | I20: =IF($A20>Assumptions!$B$6,"",SUMIFS(Trips!$J$5:$J$1004,Trips!$L$5:$L$1004,$A20)+SUMIFS(Expenses!$E$5:$E$1004,Expenses!$G$5:$G$1004,$A20)) | J20: =IF($A20>Assumptions!$B$6,"",SUMPRODUCT(((Fleet!$A$5:$A$79<>"")*(Fleet!$E$5:$E$79<=EOMONTH($A20,0))*(((Fleet!$F$5:$F$79="")+(Fleet!$F$5:$F$79>=$A20))>0))*Fleet!$O$5:$O$79)) | K20: =IF($A20>Assumptions!$B$6,"",H20-I20-J20) | L20: =IF($A20>Assumptions!$B$6,"",IF(B20=0,0,K20/B20)) | M20: =IF($A20>Assumptions!$B$6,"",K20*12) | N20: =IF($A20>Assumptions!$B$6,"",IF(L20<=0,"n/a",Assumptions!$B$4/12/L20))
A21: =EDATE(A20,1) -> 46661 | B21: =IF($A21>Assumptions!$B$6,"",SUMPRODUCT(((Fleet!$A$5:$A$79<>"")*(Fleet!$E$5:$E$79<=EOMONTH($A21,0))*(((Fleet!$F$5:$F$79="")+(Fleet!$F$5:$F$79>=$A21))>0)))) | C21: =IF($A21>Assumptions!$B$6,"",B21*DAY(EOMONTH($A21,0))) | D21: =IF($A21>Assumptions!$B$6,"",SUMIFS(Trips!$E$5:$E$1004,Trips!$L$5:$L$1004,$A21)) | E21: =IF($A21>Assumptions!$B$6,"",IF(C21=0,0,D21/C21)) | F21: =IF($A21>Assumptions!$B$6,"",COUNTIFS(Trips!$L$5:$L$1004,$A21)) | G21: =IF($A21>Assumptions!$B$6,"",SUMIFS(Trips!$F$5:$F$1004,Trips!$L$5:$L$1004,$A21)) | H21: =IF($A21>Assumptions!$B$6,"",SUMIFS(Trips!$H$5:$H$1004,Trips!$L$5:$L$1004,$A21)+SUMIFS(Trips!$I$5:$I$1004,Trips!$L$5:$L$1004,$A21)) | I21: =IF($A21>Assumptions!$B$6,"",SUMIFS(Trips!$J$5:$J$1004,Trips!$L$5:$L$1004,$A21)+SUMIFS(Expenses!$E$5:$E$1004,Expenses!$G$5:$G$1004,$A21)) | J21: =IF($A21>Assumptions!$B$6,"",SUMPRODUCT(((Fleet!$A$5:$A$79<>"")*(Fleet!$E$5:$E$79<=EOMONTH($A21,0))*(((Fleet!$F$5:$F$79="")+(Fleet!$F$5:$F$79>=$A21))>0))*Fleet!$O$5:$O$79)) | K21: =IF($A21>Assumptions!$B$6,"",H21-I21-J21) | L21: =IF($A21>Assumptions!$B$6,"",IF(B21=0,0,K21/B21)) | M21: =IF($A21>Assumptions!$B$6,"",K21*12) | N21: =IF($A21>Assumptions!$B$6,"",IF(L21<=0,"n/a",Assumptions!$B$4/12/L21))
A22: 12-mo total | C22: =SUM(C10:C21) -> 60 | D22: =SUM(D10:D21) -> 19 | E22: =IF(C22=0,0,D22/C22) -> 0.31666667 | F22: =SUM(F10:F21) -> 4 | G22: =SUM(G10:G21) -> 1206 | H22: =SUM(H10:H21) -> 994.8 | I22: =SUM(I10:I21) -> 323 | J22: =SUM(J10:J21) -> 965 | K22: =SUM(K10:K21) -> -293.2

Sheet Assumptions
A1: Assumptions & targets
A2: Change the yellow cells. Everything else recalculates.
A4: Annual net profit goal ($) | B4: 300000 | C4: Your target (from the plan).
A5: Tracker start month | B5: 46327 | C5: First month on the Dashboard. Use the 1st of a month.
A6: Report month (latest closed month) | B6: 46327 | C6: Car Scorecard reports on this month; Dashboard shows months up to it. Move it forward each month. Use the 1st of a month.
A7: Default host share | B7: 0.8 | C7: Used when a car's plan is blank. US plans: 70% / 80% / 90% (Turo help centre, earnings plans, Jan 2026).
A8: Target utilization | B8: 0.6 | C8: ≈18 booked days a month. Turo's published US average is ~15 days/month (turo.com/list-your-car).
A9: Target net per car per month ($) | B9: 350 | C9: Stage-1 gate from the plan. ~$500 is the well-run-fleet benchmark needed for $300k at ~50 cars.
A10: Max payback (months) | B10: 30 | C10: Buy Box rule: car must repay its price from operating cash flow within this many months.
A11: Cash reserve per car (months of costs) | B11: 2 | C11: Keep this many months of each car's fixed + variable cost in the bank.

Sheet Lists
A1: Expense categories | B1: Car IDs + FLEET
A2: Maintenance | B2: FLEET
A3: Tires | B3: =IF(Fleet!A5="","",Fleet!A5) -> CAR-01
A4: Repairs / damage | B4: =IF(Fleet!A6="","",Fleet!A6) -> CAR-02
A5: Cleaning supplies | B5: =IF(Fleet!A7="","",Fleet!A7)
A6: Detailing | B6: =IF(Fleet!A8="","",Fleet!A8)
A7: Tolls / parking | B7: =IF(Fleet!A9="","",Fleet!A9)
A8: Fuel / charging | B8: =IF(Fleet!A10="","",Fleet!A10)
A9: Software / subscriptions | B9: =IF(Fleet!A11="","",Fleet!A11)
A10: Marketing | B10: =IF(Fleet!A12="","",Fleet!A12)
A11: Labor / contractor | B11: =IF(Fleet!A13="","",Fleet!A13)
A12: Delivery | B12: =IF(Fleet!A14="","",Fleet!A14)
A13: Other | B13: =IF(Fleet!A15="","",Fleet!A15)
B14: =IF(Fleet!A16="","",Fleet!A16)
B15: =IF(Fleet!A17="","",Fleet!A17)
B16: =IF(Fleet!A18="","",Fleet!A18)
B17: =IF(Fleet!A19="","",Fleet!A19)
B18: =IF(Fleet!A20="","",Fleet!A20)
B19: =IF(Fleet!A21="","",Fleet!A21)
B20: =IF(Fleet!A22="","",Fleet!A22)
B21: =IF(Fleet!A23="","",Fleet!A23)
B22: =IF(Fleet!A24="","",Fleet!A24)
B23: =IF(Fleet!A25="","",Fleet!A25)
B24: =IF(Fleet!A26="","",Fleet!A26)
B25: =IF(Fleet!A27="","",Fleet!A27)
... B77: =IF(Fleet!A79="","",Fleet!A79)

Sheet Fleet
A1: Fleet register
A2: One row per car. Fixed monthly costs live here. Leave Sold date blank while you own the car.
A4: Car ID | B4: Year | C4: Make / model | D4: Status | E4: Purchase date | F4: Sold date | G4: Purchase price ($) | H4: Cash invested ($) (down pmt, or full price if cash) | I4: Loan payment ($/mo) | J4: Insurance ($/mo) | K4: Registration ($/yr) | L4: Tracker & software ($/mo) | M4: Parking ($/mo) | N4: Earnings plan host share | O4: Fixed cost ($/mo) | P4: Notes
A5: CAR-01 | B5: 2022 | C5: Toyota Corolla LE | D5: Active | E5: 46327 | G5: 18500 | H5: 3700 | I5: 295 | J5: 110 | K5: 240 | L5: 25 | M5: 0 | N5: 0.8 | O5: =IF(A5="",0,N(I5)+N(J5)+N(K5)/12+N(L5)+N(M5)) -> 450 | P5: EXAMPLE – delete
A6: CAR-02 | B6: 2021 | C6: Toyota RAV4 Hybrid | D6: Active | E6: 46341 | G6: 24000 | H6: 6000 | I6: 335 | J6: 130 | K6: 300 | L6: 25 | M6: 0 | N6: 0.8 | O6: =IF(A6="",0,N(I6)+N(J6)+N(K6)/12+N(L6)+N(M6)) -> 515 | P6: EXAMPLE – delete
O7: =IF(A7="",0,N(I7)+N(J7)+N(K7)/12+N(L7)+N(M7)) -> 0
O8: =IF(A8="",0,N(I8)+N(J8)+N(K8)/12+N(L8)+N(M8)) -> 0
O9: =IF(A9="",0,N(I9)+N(J9)+N(K9)/12+N(L9)+N(M9)) -> 0
O10: =IF(A10="",0,N(I10)+N(J10)+N(K10)/12+N(L10)+N(M10)) -> 0
O11: =IF(A11="",0,N(I11)+N(J11)+N(K11)/12+N(L11)+N(M11)) -> 0
O12: =IF(A12="",0,N(I12)+N(J12)+N(K12)/12+N(L12)+N(M12)) -> 0
O13: =IF(A13="",0,N(I13)+N(J13)+N(K13)/12+N(L13)+N(M13)) -> 0
O14: =IF(A14="",0,N(I14)+N(J14)+N(K14)/12+N(L14)+N(M14)) -> 0
O15: =IF(A15="",0,N(I15)+N(J15)+N(K15)/12+N(L15)+N(M15)) -> 0
O16: =IF(A16="",0,N(I16)+N(J16)+N(K16)/12+N(L16)+N(M16)) -> 0
O17: =IF(A17="",0,N(I17)+N(J17)+N(K17)/12+N(L17)+N(M17)) -> 0
O18: =IF(A18="",0,N(I18)+N(J18)+N(K18)/12+N(L18)+N(M18)) -> 0
... O79: =IF(A79="",0,N(I79)+N(J79)+N(K79)/12+N(L79)+N(M79)) -> 0

Sheet Trips
A1: Trip log
A2: Copy from your Turo earnings export. Trip price = price before Turo's cut. Grey columns are formulas.
A4: Trip ID | B4: Car ID | C4: Start date | D4: End date | E4: Days | F4: Trip price ($) | G4: Host share | H4: Host earnings ($) | I4: Reimbursements & extras ($) (tolls, fuel, delivery) | J4: Turnover cost ($) (clean, fuel, labor) | K4: Guest rating (1–5) | L4: Month | M4: Net trip ($) | N4: Notes
A5: T-1001 | B5: CAR-01 | C5: 46329 | D5: 46333 | E5: =IF(OR(C5="",D5=""),"",MAX(1,D5-C5)) -> 4 | F5: 248 | G5: =IF(B5="","",IFERROR(IF(N(INDEX(Fleet!$N$5:$N$79,MATCH(B5,Fleet!$A$5:$A$79,0)))>0,INDEX(Fleet!$N$5:$N$79,MATCH(B5,Fleet!$A$5:$A$79,0)),Assumptions!$B$7),Assumptions!$B$7)) -> 0.8 | H5: =IF(OR(F5="",G5=""),"",F5*G5) -> 198.4 | I5: 0 | J5: 35 | K5: 5 | L5: =IF(C5="","",DATE(YEAR(C5),MONTH(C5),1)) -> 46327 | M5: =IF(F5="","",N(H5)+N(I5)-N(J5)) -> 163.4 | N5: EXAMPLE – delete
A6: T-1002 | B6: CAR-01 | C6: 46335 | D6: 46342 | E6: =IF(OR(C6="",D6=""),"",MAX(1,D6-C6)) -> 7 | F6: 410 | G6: =IF(B6="","",IFERROR(IF(N(INDEX(Fleet!$N$5:$N$79,MATCH(B6,Fleet!$A$5:$A$79,0)))>0,INDEX(Fleet!$N$5:$N$79,MATCH(B6,Fleet!$A$5:$A$79,0)),Assumptions!$B$7),Assumptions!$B$7)) -> 0.8 | H6: =IF(OR(F6="",G6=""),"",F6*G6) -> 328 | I6: 18 | J6: 35 | K6: 5 | L6: =IF(C6="","",DATE(YEAR(C6),MONTH(C6),1)) -> 46327 | M6: =IF(F6="","",N(H6)+N(I6)-N(J6)) -> 311 | N6: EXAMPLE – delete
A7: T-1003 | B7: CAR-02 | C7: 46344 | D7: 46348 | E7: =IF(OR(C7="",D7=""),"",MAX(1,D7-C7)) -> 4 | F7: 312 | G7: =IF(B7="","",IFERROR(IF(N(INDEX(Fleet!$N$5:$N$79,MATCH(B7,Fleet!$A$5:$A$79,0)))>0,INDEX(Fleet!$N$5:$N$79,MATCH(B7,Fleet!$A$5:$A$79,0)),Assumptions!$B$7),Assumptions!$B$7)) -> 0.8 | H7: =IF(OR(F7="",G7=""),"",F7*G7) -> 249.6 | I7: 0 | J7: 35 | K7: 5 | L7: =IF(C7="","",DATE(YEAR(C7),MONTH(C7),1)) -> 46327 | M7: =IF(F7="","",N(H7)+N(I7)-N(J7)) -> 214.6 | N7: EXAMPLE – delete
A8: T-1004 | B8: CAR-01 | C8: 46346 | D8: 46350 | E8: =IF(OR(C8="",D8=""),"",MAX(1,D8-C8)) -> 4 | F8: 236 | G8: =IF(B8="","",IFERROR(IF(N(INDEX(Fleet!$N$5:$N$79,MATCH(B8,Fleet!$A$5:$A$79,0)))>0,INDEX(Fleet!$N$5:$N$79,MATCH(B8,Fleet!$A$5:$A$79,0)),Assumptions!$B$7),Assumptions!$B$7)) -> 0.8 | H8: =IF(OR(F8="",G8=""),"",F8*G8) -> 188.8 | I8: 12 | J8: 35 | K8: 4 | L8: =IF(C8="","",DATE(YEAR(C8),MONTH(C8),1)) -> 46327 | M8: =IF(F8="","",N(H8)+N(I8)-N(J8)) -> 165.8 | N8: EXAMPLE – delete
E9: =IF(OR(C9="",D9=""),"",MAX(1,D9-C9)) | G9: =IF(B9="","",IFERROR(IF(N(INDEX(Fleet!$N$5:$N$79,MATCH(B9,Fleet!$A$5:$A$79,0)))>0,INDEX(Fleet!$N$5:$N$79,MATCH(B9,Fleet!$A$5:$A$79,0)),Assumptions!$B$7),Assumptions!$B$7)) | H9: =IF(OR(F9="",G9=""),"",F9*G9) | L9: =IF(C9="","",DATE(YEAR(C9),MONTH(C9),1)) | M9: =IF(F9="","",N(H9)+N(I9)-N(J9))
E10: =IF(OR(C10="",D10=""),"",MAX(1,D10-C10)) | G10: =IF(B10="","",IFERROR(IF(N(INDEX(Fleet!$N$5:$N$79,MATCH(B10,Fleet!$A$5:$A$79,0)))>0,INDEX(Fleet!$N$5:$N$79,MATCH(B10,Fleet!$A$5:$A$79,0)),Assumptions!$B$7),Assumptions!$B$7)) | H10: =IF(OR(F10="",G10=""),"",F10*G10) | L10: =IF(C10="","",DATE(YEAR(C10),MONTH(C10),1)) | M10: =IF(F10="","",N(H10)+N(I10)-N(J10))
E11: =IF(OR(C11="",D11=""),"",MAX(1,D11-C11)) | G11: =IF(B11="","",IFERROR(IF(N(INDEX(Fleet!$N$5:$N$79,MATCH(B11,Fleet!$A$5:$A$79,0)))>0,INDEX(Fleet!$N$5:$N$79,MATCH(B11,Fleet!$A$5:$A$79,0)),Assumptions!$B$7),Assumptions!$B$7)) | H11: =IF(OR(F11="",G11=""),"",F11*G11) | L11: =IF(C11="","",DATE(YEAR(C11),MONTH(C11),1)) | M11: =IF(F11="","",N(H11)+N(I11)-N(J11))
E12: =IF(OR(C12="",D12=""),"",MAX(1,D12-C12)) | G12: =IF(B12="","",IFERROR(IF(N(INDEX(Fleet!$N$5:$N$79,MATCH(B12,Fleet!$A$5:$A$79,0)))>0,INDEX(Fleet!$N$5:$N$79,MATCH(B12,Fleet!$A$5:$A$79,0)),Assumptions!$B$7),Assumptions!$B$7)) | H12: =IF(OR(F12="",G12=""),"",F12*G12) | L12: =IF(C12="","",DATE(YEAR(C12),MONTH(C12),1)) | M12: =IF(F12="","",N(H12)+N(I12)-N(J12))
E13: =IF(OR(C13="",D13=""),"",MAX(1,D13-C13)) | G13: =IF(B13="","",IFERROR(IF(N(INDEX(Fleet!$N$5:$N$79,MATCH(B13,Fleet!$A$5:$A$79,0)))>0,INDEX(Fleet!$N$5:$N$79,MATCH(B13,Fleet!$A$5:$A$79,0)),Assumptions!$B$7),Assumptions!$B$7)) | H13: =IF(OR(F13="",G13=""),"",F13*G13) | L13: =IF(C13="","",DATE(YEAR(C13),MONTH(C13),1)) | M13: =IF(F13="","",N(H13)+N(I13)-N(J13))
E14: =IF(OR(C14="",D14=""),"",MAX(1,D14-C14)) | G14: =IF(B14="","",IFERROR(IF(N(INDEX(Fleet!$N$5:$N$79,MATCH(B14,Fleet!$A$5:$A$79,0)))>0,INDEX(Fleet!$N$5:$N$79,MATCH(B14,Fleet!$A$5:$A$79,0)),Assumptions!$B$7),Assumptions!$B$7)) | H14: =IF(OR(F14="",G14=""),"",F14*G14) | L14: =IF(C14="","",DATE(YEAR(C14),MONTH(C14),1)) | M14: =IF(F14="","",N(H14)+N(I14)-N(J14))
E15: =IF(OR(C15="",D15=""),"",MAX(1,D15-C15)) | G15: =IF(B15="","",IFERROR(IF(N(INDEX(Fleet!$N$5:$N$79,MATCH(B15,Fleet!$A$5:$A$79,0)))>0,INDEX(Fleet!$N$5:$N$79,MATCH(B15,Fleet!$A$5:$A$79,0)),Assumptions!$B$7),Assumptions!$B$7)) | H15: =IF(OR(F15="",G15=""),"",F15*G15) | L15: =IF(C15="","",DATE(YEAR(C15),MONTH(C15),1)) | M15: =IF(F15="","",N(H15)+N(I15)-N(J15))
E16: =IF(OR(C16="",D16=""),"",MAX(1,D16-C16)) | G16: =IF(B16="","",IFERROR(IF(N(INDEX(Fleet!$N$5:$N$79,MATCH(B16,Fleet!$A$5:$A$79,0)))>0,INDEX(Fleet!$N$5:$N$79,MATCH(B16,Fleet!$A$5:$A$79,0)),Assumptions!$B$7),Assumptions!$B$7)) | H16: =IF(OR(F16="",G16=""),"",F16*G16) | L16: =IF(C16="","",DATE(YEAR(C16),MONTH(C16),1)) | M16: =IF(F16="","",N(H16)+N(I16)-N(J16))
E17: =IF(OR(C17="",D17=""),"",MAX(1,D17-C17)) | G17: =IF(B17="","",IFERROR(IF(N(INDEX(Fleet!$N$5:$N$79,MATCH(B17,Fleet!$A$5:$A$79,0)))>0,INDEX(Fleet!$N$5:$N$79,MATCH(B17,Fleet!$A$5:$A$79,0)),Assumptions!$B$7),Assumptions!$B$7)) | H17: =IF(OR(F17="",G17=""),"",F17*G17) | L17: =IF(C17="","",DATE(YEAR(C17),MONTH(C17),1)) | M17: =IF(F17="","",N(H17)+N(I17)-N(J17))
E18: =IF(OR(C18="",D18=""),"",MAX(1,D18-C18)) | G18: =IF(B18="","",IFERROR(IF(N(INDEX(Fleet!$N$5:$N$79,MATCH(B18,Fleet!$A$5:$A$79,0)))>0,INDEX(Fleet!$N$5:$N$79,MATCH(B18,Fleet!$A$5:$A$79,0)),Assumptions!$B$7),Assumptions!$B$7)) | H18: =IF(OR(F18="",G18=""),"",F18*G18) | L18: =IF(C18="","",DATE(YEAR(C18),MONTH(C18),1)) | M18: =IF(F18="","",N(H18)+N(I18)-N(J18))
E19: =IF(OR(C19="",D19=""),"",MAX(1,D19-C19)) | G19: =IF(B19="","",IFERROR(IF(N(INDEX(Fleet!$N$5:$N$79,MATCH(B19,Fleet!$A$5:$A$79,0)))>0,INDEX(Fleet!$N$5:$N$79,MATCH(B19,Fleet!$A$5:$A$79,0)),Assumptions!$B$7),Assumptions!$B$7)) | H19: =IF(OR(F19="",G19=""),"",F19*G19) | L19: =IF(C19="","",DATE(YEAR(C19),MONTH(C19),1)) | M19: =IF(F19="","",N(H19)+N(I19)-N(J19))
E20: =IF(OR(C20="",D20=""),"",MAX(1,D20-C20)) | G20: =IF(B20="","",IFERROR(IF(N(INDEX(Fleet!$N$5:$N$79,MATCH(B20,Fleet!$A$5:$A$79,0)))>0,INDEX(Fleet!$N$5:$N$79,MATCH(B20,Fleet!$A$5:$A$79,0)),Assumptions!$B$7),Assumptions!$B$7)) | H20: =IF(OR(F20="",G20=""),"",F20*G20) | L20: =IF(C20="","",DATE(YEAR(C20),MONTH(C20),1)) | M20: =IF(F20="","",N(H20)+N(I20)-N(J20))
... E1004: =IF(OR(C1004="",D1004=""),"",MAX(1,D1004-C1004)) | G1004: =IF(B1004="","",IFERROR(IF(N(INDEX(Fleet!$N$5:$N$79,MATCH(B1004,Fleet!$A$5:$A$79,0)))>0,INDEX(Fleet!$N$5:$N$79,MATCH(B1004,Fleet!$A$5:$A$79,0)),Assumptions!$B$7),Assumptions!$B$7)) | H1004: =IF(OR(F1004="",G1004=""),"",F1004*G1004) | L1004: =IF(C1004="","",DATE(YEAR(C1004),MONTH(C1004),1)) | M1004: =IF(F1004="","",N(H1004)+N(I1004)-N(J1004))

Sheet Expenses
A1: Variable expenses
A2: Do NOT log loan, insurance, registration, tracker or parking here — those are fixed costs on the Fleet tab.
A4: Date | B4: Car ID (or FLEET) | C4: Category | D4: Vendor | E4: Amount ($) | F4: Notes | G4: Month
A5: 46328 | B5: FLEET | C5: Cleaning supplies | D5: Costco | E5: 64 | F5: EXAMPLE – delete | G5: =IF(A5="","",DATE(YEAR(A5),MONTH(A5),1)) -> 46327
A6: 46343 | B6: CAR-01 | C6: Maintenance | D6: Quick Lube | E6: 79 | F6: EXAMPLE – delete | G6: =IF(A6="","",DATE(YEAR(A6),MONTH(A6),1)) -> 46327
A7: 46351 | B7: FLEET | C7: Software / subscriptions | D7: Pricing tool | E7: 40 | F7: EXAMPLE – delete | G7: =IF(A7="","",DATE(YEAR(A7),MONTH(A7),1)) -> 46327
G8: =IF(A8="","",DATE(YEAR(A8),MONTH(A8),1))
G9: =IF(A9="","",DATE(YEAR(A9),MONTH(A9),1))
G10: =IF(A10="","",DATE(YEAR(A10),MONTH(A10),1))
G11: =IF(A11="","",DATE(YEAR(A11),MONTH(A11),1))
G12: =IF(A12="","",DATE(YEAR(A12),MONTH(A12),1))
G13: =IF(A13="","",DATE(YEAR(A13),MONTH(A13),1))
G14: =IF(A14="","",DATE(YEAR(A14),MONTH(A14),1))
G15: =IF(A15="","",DATE(YEAR(A15),MONTH(A15),1))
G16: =IF(A16="","",DATE(YEAR(A16),MONTH(A16),1))
G17: =IF(A17="","",DATE(YEAR(A17),MONTH(A17),1))
G18: =IF(A18="","",DATE(YEAR(A18),MONTH(A18),1))
G19: =IF(A19="","",DATE(YEAR(A19),MONTH(A19),1))
... G1004: =IF(A1004="","",DATE(YEAR(A1004),MONTH(A1004),1))

Sheet Car Scorecard
A1: Car scorecard
A2: Reports on the Report month set on the Assumptions tab.
A3: Month: | B3: =Assumptions!$B$6 -> 46327
A5: Car ID | B5: Make / model | C5: Owned this month | D5: Booked days | E5: Utilization | F5: Earnings + extras ($) | G5: Variable costs ($) | H5: Fixed cost ($) | I5: Net this month ($) | J5: Net last month ($) | K5: Net 2 months ago ($) | L5: Lifetime net ($) | M5: Cash invested ($) | N5: Payback progress | O5: Flag
A6: =IF(Fleet!A5="","",Fleet!A5) -> CAR-01 | B6: =IF(Fleet!A5="","",Fleet!B5&" "&Fleet!C5) -> 2022 Toyota Corolla LE | C6: =IF($A6="","",IF(AND(Fleet!$A$5<>"",N(Fleet!$E$5)<=EOMONTH($B$3,0),OR(Fleet!$F$5="",N(Fleet!$F$5)>=$B$3)),1,0)) -> 1 | D6: =IF($A6="","",SUMIFS(Trips!$E$5:$E$1004,Trips!$B$5:$B$1004,$A6,Trips!$L$5:$L$1004,$B$3)) -> 15 | E6: =IF(OR($A6="",N(C6)=0),"",D6/DAY(EOMONTH($B$3,0))) -> 0.5 | F6: =IF($A6="","",SUMIFS(Trips!$H$5:$H$1004,Trips!$B$5:$B$1004,$A6,Trips!$L$5:$L$1004,$B$3)+SUMIFS(Trips!$I$5:$I$1004,Trips!$B$5:$B$1004,$A6,Trips!$L$5:$L$1004,$B$3)) -> 745.2 | G6: =IF($A6="","",SUMIFS(Trips!$J$5:$J$1004,Trips!$B$5:$B$1004,$A6,Trips!$L$5:$L$1004,$B$3)+SUMIFS(Expenses!$E$5:$E$1004,Expenses!$B$5:$B$1004,$A6,Expenses!$G$5:$G$1004,$B$3)) -> 184 | H6: =IF($A6="","",Fleet!$O$5*C6) -> 450 | I6: =IF($A6="","",F6-G6-H6) -> 111.2 | J6: =IF($A6="","",(SUMIFS(Trips!$H$5:$H$1004,Trips!$B$5:$B$1004,$A6,Trips!$L$5:$L$1004,EDATE($B$3,-1))+SUMIFS(Trips!$I$5:$I$1004,Trips!$B$5:$B$1004,$A6,Trips!$L$5:$L$1004,EDATE($B$3,-1))-SUMIFS(Trips!$J$5:$J$1004,Trips!$B$5:$B$1004,$A6,Trips!$L$5:$L$1004,EDATE($B$3,-1))-SUMIFS(Expenses!$E$5:$E$1004,Expenses!$B$5:$B$1004,$A6,Expenses!$G$5:$G$1004,EDATE($B$3,-1))-Fleet!$O$5*IF(AND(Fleet!$A$5<>"",N(Fleet!$E$5)<=EOMONTH(EDATE($B$3,-1),0),OR(Fleet!$F$5="",N(Fleet!$F$5)>=EDATE($B$3,-1))),1,0))) -> 0 | K6: =IF($A6="","",(SUMIFS(Trips!$H$5:$H$1004,Trips!$B$5:$B$1004,$A6,Trips!$L$5:$L$1004,EDATE($B$3,-2))+SUMIFS(Trips!$I$5:$I$1004,Trips!$B$5:$B$1004,$A6,Trips!$L$5:$L$1004,EDATE($B$3,-2))-SUMIFS(Trips!$J$5:$J$1004,Trips!$B$5:$B$1004,$A6,Trips!$L$5:$L$1004,EDATE($B$3,-2))-SUMIFS(Expenses!$E$5:$E$1004,Expenses!$B$5:$B$1004,$A6,Expenses!$G$5:$G$1004,EDATE($B$3,-2))-Fleet!$O$5*IF(AND(Fleet!$A$5<>"",N(Fleet!$E$5)<=EOMONTH(EDATE($B$3,-2),0),OR(Fleet!$F$5="",N(Fleet!$F$5)>=EDATE($B$3,-2))),1,0))) -> 0 | L6: =IF($A6="","",SUMIFS(Trips!$M$5:$M$1004,Trips!$B$5:$B$1004,$A6,Trips!$L$5:$L$1004,"<="&$B$3)-SUMIFS(Expenses!$E$5:$E$1004,Expenses!$B$5:$B$1004,$A6,Expenses!$G$5:$G$1004,"<="&$B$3)-Fleet!$O$5*IF(N(Fleet!$E$5)=0,0,MAX(0,(YEAR(IF(Fleet!$F$5="",EOMONTH($B$3,0),MIN(Fleet!$F$5,EOMONTH($B$3,0))))-YEAR(Fleet!$E$5))*12+MONTH(IF(Fleet!$F$5="",EOMONTH($B$3,0),MIN(Fleet!$F$5,EOMONTH($B$3,0))))-MONTH(Fleet!$E$5)+1))) -> 111.2 | M6: =IF($A6="","",Fleet!$H$5) -> 3700 | N6: =IF(OR($A6="",N(M6)=0),"",L6/M6) -> 0.030054054 | O6: =IF(OR($A6="",N(C6)=0),"",IF(AND(I6<0,J6<0,K6<0),"REVIEW: 3 losing months",IF(I6<Assumptions!$B$9,"Below net target",IF(E6<Assumptions!$B$8,"Low utilization","On track")))) -> Below net target
A7: =IF(Fleet!A6="","",Fleet!A6) -> CAR-02 | B7: =IF(Fleet!A6="","",Fleet!B6&" "&Fleet!C6) -> 2021 Toyota RAV4 Hybrid | C7: =IF($A7="","",IF(AND(Fleet!$A$6<>"",N(Fleet!$E$6)<=EOMONTH($B$3,0),OR(Fleet!$F$6="",N(Fleet!$F$6)>=$B$3)),1,0)) -> 1 | D7: =IF($A7="","",SUMIFS(Trips!$E$5:$E$1004,Trips!$B$5:$B$1004,$A7,Trips!$L$5:$L$1004,$B$3)) -> 4 | E7: =IF(OR($A7="",N(C7)=0),"",D7/DAY(EOMONTH($B$3,0))) -> 0.13333333 | F7: =IF($A7="","",SUMIFS(Trips!$H$5:$H$1004,Trips!$B$5:$B$1004,$A7,Trips!$L$5:$L$1004,$B$3)+SUMIFS(Trips!$I$5:$I$1004,Trips!$B$5:$B$1004,$A7,Trips!$L$5:$L$1004,$B$3)) -> 249.6 | G7: =IF($A7="","",SUMIFS(Trips!$J$5:$J$1004,Trips!$B$5:$B$1004,$A7,Trips!$L$5:$L$1004,$B$3)+SUMIFS(Expenses!$E$5:$E$1004,Expenses!$B$5:$B$1004,$A7,Expenses!$G$5:$G$1004,$B$3)) -> 35 | H7: =IF($A7="","",Fleet!$O$6*C7) -> 515 | I7: =IF($A7="","",F7-G7-H7) -> -300.4 | J7: =IF($A7="","",(SUMIFS(Trips!$H$5:$H$1004,Trips!$B$5:$B$1004,$A7,Trips!$L$5:$L$1004,EDATE($B$3,-1))+SUMIFS(Trips!$I$5:$I$1004,Trips!$B$5:$B$1004,$A7,Trips!$L$5:$L$1004,EDATE($B$3,-1))-SUMIFS(Trips!$J$5:$J$1004,Trips!$B$5:$B$1004,$A7,Trips!$L$5:$L$1004,EDATE($B$3,-1))-SUMIFS(Expenses!$E$5:$E$1004,Expenses!$B$5:$B$1004,$A7,Expenses!$G$5:$G$1004,EDATE($B$3,-1))-Fleet!$O$6*IF(AND(Fleet!$A$6<>"",N(Fleet!$E$6)<=EOMONTH(EDATE($B$3,-1),0),OR(Fleet!$F$6="",N(Fleet!$F$6)>=EDATE($B$3,-1))),1,0))) -> 0 | K7: =IF($A7="","",(SUMIFS(Trips!$H$5:$H$1004,Trips!$B$5:$B$1004,$A7,Trips!$L$5:$L$1004,EDATE($B$3,-2))+SUMIFS(Trips!$I$5:$I$1004,Trips!$B$5:$B$1004,$A7,Trips!$L$5:$L$1004,EDATE($B$3,-2))-SUMIFS(Trips!$J$5:$J$1004,Trips!$B$5:$B$1004,$A7,Trips!$L$5:$L$1004,EDATE($B$3,-2))-SUMIFS(Expenses!$E$5:$E$1004,Expenses!$B$5:$B$1004,$A7,Expenses!$G$5:$G$1004,EDATE($B$3,-2))-Fleet!$O$6*IF(AND(Fleet!$A$6<>"",N(Fleet!$E$6)<=EOMONTH(EDATE($B$3,-2),0),OR(Fleet!$F$6="",N(Fleet!$F$6)>=EDATE($B$3,-2))),1,0))) -> 0 | L7: =IF($A7="","",SUMIFS(Trips!$M$5:$M$1004,Trips!$B$5:$B$1004,$A7,Trips!$L$5:$L$1004,"<="&$B$3)-SUMIFS(Expenses!$E$5:$E$1004,Expenses!$B$5:$B$1004,$A7,Expenses!$G$5:$G$1004,"<="&$B$3)-Fleet!$O$6*IF(N(Fleet!$E$6)=0,0,MAX(0,(YEAR(IF(Fleet!$F$6="",EOMONTH($B$3,0),MIN(Fleet!$F$6,EOMONTH($B$3,0))))-YEAR(Fleet!$E$6))*12+MONTH(IF(Fleet!$F$6="",EOMONTH($B$3,0),MIN(Fleet!$F$6,EOMONTH($B$3,0))))-MONTH(Fleet!$E$6)+1))) -> -300.4 | M7: =IF($A7="","",Fleet!$H$6) -> 6000 | N7: =IF(OR($A7="",N(M7)=0),"",L7/M7) -> -0.050066667 | O7: =IF(OR($A7="",N(C7)=0),"",IF(AND(I7<0,J7<0,K7<0),"REVIEW: 3 losing months",IF(I7<Assumptions!$B$9,"Below net target",IF(E7<Assumptions!$B$8,"Low utilization","On track")))) -> Below net target
A8: =IF(Fleet!A7="","",Fleet!A7) | B8: =IF(Fleet!A7="","",Fleet!B7&" "&Fleet!C7) | C8: =IF($A8="","",IF(AND(Fleet!$A$7<>"",N(Fleet!$E$7)<=EOMONTH($B$3,0),OR(Fleet!$F$7="",N(Fleet!$F$7)>=$B$3)),1,0)) | D8: =IF($A8="","",SUMIFS(Trips!$E$5:$E$1004,Trips!$B$5:$B$1004,$A8,Trips!$L$5:$L$1004,$B$3)) | E8: =IF(OR($A8="",N(C8)=0),"",D8/DAY(EOMONTH($B$3,0))) | F8: =IF($A8="","",SUMIFS(Trips!$H$5:$H$1004,Trips!$B$5:$B$1004,$A8,Trips!$L$5:$L$1004,$B$3)+SUMIFS(Trips!$I$5:$I$1004,Trips!$B$5:$B$1004,$A8,Trips!$L$5:$L$1004,$B$3)) | G8: =IF($A8="","",SUMIFS(Trips!$J$5:$J$1004,Trips!$B$5:$B$1004,$A8,Trips!$L$5:$L$1004,$B$3)+SUMIFS(Expenses!$E$5:$E$1004,Expenses!$B$5:$B$1004,$A8,Expenses!$G$5:$G$1004,$B$3)) | H8: =IF($A8="","",Fleet!$O$7*C8) | I8: =IF($A8="","",F8-G8-H8) | J8: =IF($A8="","",(SUMIFS(Trips!$H$5:$H$1004,Trips!$B$5:$B$1004,$A8,Trips!$L$5:$L$1004,EDATE($B$3,-1))+SUMIFS(Trips!$I$5:$I$1004,Trips!$B$5:$B$1004,$A8,Trips!$L$5:$L$1004,EDATE($B$3,-1))-SUMIFS(Trips!$J$5:$J$1004,Trips!$B$5:$B$1004,$A8,Trips!$L$5:$L$1004,EDATE($B$3,-1))-SUMIFS(Expenses!$E$5:$E$1004,Expenses!$B$5:$B$1004,$A8,Expenses!$G$5:$G$1004,EDATE($B$3,-1))-Fleet!$O$7*IF(AND(Fleet!$A$7<>"",N(Fleet!$E$7)<=EOMONTH(EDATE($B$3,-1),0),OR(Fleet!$F$7="",N(Fleet!$F$7)>=EDATE($B$3,-1))),1,0))) | K8: =IF($A8="","",(SUMIFS(Trips!$H$5:$H$1004,Trips!$B$5:$B$1004,$A8,Trips!$L$5:$L$1004,EDATE($B$3,-2))+SUMIFS(Trips!$I$5:$I$1004,Trips!$B$5:$B$1004,$A8,Trips!$L$5:$L$1004,EDATE($B$3,-2))-SUMIFS(Trips!$J$5:$J$1004,Trips!$B$5:$B$1004,$A8,Trips!$L$5:$L$1004,EDATE($B$3,-2))-SUMIFS(Expenses!$E$5:$E$1004,Expenses!$B$5:$B$1004,$A8,Expenses!$G$5:$G$1004,EDATE($B$3,-2))-Fleet!$O$7*IF(AND(Fleet!$A$7<>"",N(Fleet!$E$7)<=EOMONTH(EDATE($B$3,-2),0),OR(Fleet!$F$7="",N(Fleet!$F$7)>=EDATE($B$3,-2))),1,0))) | L8: =IF($A8="","",SUMIFS(Trips!$M$5:$M$1004,Trips!$B$5:$B$1004,$A8,Trips!$L$5:$L$1004,"<="&$B$3)-SUMIFS(Expenses!$E$5:$E$1004,Expenses!$B$5:$B$1004,$A8,Expenses!$G$5:$G$1004,"<="&$B$3)-Fleet!$O$7*IF(N(Fleet!$E$7)=0,0,MAX(0,(YEAR(IF(Fleet!$F$7="",EOMONTH($B$3,0),MIN(Fleet!$F$7,EOMONTH($B$3,0))))-YEAR(Fleet!$E$7))*12+MONTH(IF(Fleet!$F$7="",EOMONTH($B$3,0),MIN(Fleet!$F$7,EOMONTH($B$3,0))))-MONTH(Fleet!$E$7)+1))) | M8: =IF($A8="","",Fleet!$H$7) | N8: =IF(OR($A8="",N(M8)=0),"",L8/M8) | O8: =IF(OR($A8="",N(C8)=0),"",IF(AND(I8<0,J8<0,K8<0),"REVIEW: 3 losing months",IF(I8<Assumptions!$B$9,"Below net target",IF(E8<Assumptions!$B$8,"Low utilization","On track"))))
A9: =IF(Fleet!A8="","",Fleet!A8) | B9: =IF(Fleet!A8="","",Fleet!B8&" "&Fleet!C8) | C9: =IF($A9="","",IF(AND(Fleet!$A$8<>"",N(Fleet!$E$8)<=EOMONTH($B$3,0),OR(Fleet!$F$8="",N(Fleet!$F$8)>=$B$3)),1,0)) | D9: =IF($A9="","",SUMIFS(Trips!$E$5:$E$1004,Trips!$B$5:$B$1004,$A9,Trips!$L$5:$L$1004,$B$3)) | E9: =IF(OR($A9="",N(C9)=0),"",D9/DAY(EOMONTH($B$3,0))) | F9: =IF($A9="","",SUMIFS(Trips!$H$5:$H$1004,Trips!$B$5:$B$1004,$A9,Trips!$L$5:$L$1004,$B$3)+SUMIFS(Trips!$I$5:$I$1004,Trips!$B$5:$B$1004,$A9,Trips!$L$5:$L$1004,$B$3)) | G9: =IF($A9="","",SUMIFS(Trips!$J$5:$J$1004,Trips!$B$5:$B$1004,$A9,Trips!$L$5:$L$1004,$B$3)+SUMIFS(Expenses!$E$5:$E$1004,Expenses!$B$5:$B$1004,$A9,Expenses!$G$5:$G$1004,$B$3)) | H9: =IF($A9="","",Fleet!$O$8*C9) | I9: =IF($A9="","",F9-G9-H9) | J9: =IF($A9="","",(SUMIFS(Trips!$H$5:$H$1004,Trips!$B$5:$B$1004,$A9,Trips!$L$5:$L$1004,EDATE($B$3,-1))+SUMIFS(Trips!$I$5:$I$1004,Trips!$B$5:$B$1004,$A9,Trips!$L$5:$L$1004,EDATE($B$3,-1))-SUMIFS(Trips!$J$5:$J$1004,Trips!$B$5:$B$1004,$A9,Trips!$L$5:$L$1004,EDATE($B$3,-1))-SUMIFS(Expenses!$E$5:$E$1004,Expenses!$B$5:$B$1004,$A9,Expenses!$G$5:$G$1004,EDATE($B$3,-1))-Fleet!$O$8*IF(AND(Fleet!$A$8<>"",N(Fleet!$E$8)<=EOMONTH(EDATE($B$3,-1),0),OR(Fleet!$F$8="",N(Fleet!$F$8)>=EDATE($B$3,-1))),1,0))) | K9: =IF($A9="","",(SUMIFS(Trips!$H$5:$H$1004,Trips!$B$5:$B$1004,$A9,Trips!$L$5:$L$1004,EDATE($B$3,-2))+SUMIFS(Trips!$I$5:$I$1004,Trips!$B$5:$B$1004,$A9,Trips!$L$5:$L$1004,EDATE($B$3,-2))-SUMIFS(Trips!$J$5:$J$1004,Trips!$B$5:$B$1004,$A9,Trips!$L$5:$L$1004,EDATE($B$3,-2))-SUMIFS(Expenses!$E$5:$E$1004,Expenses!$B$5:$B$1004,$A9,Expenses!$G$5:$G$1004,EDATE($B$3,-2))-Fleet!$O$8*IF(AND(Fleet!$A$8<>"",N(Fleet!$E$8)<=EOMONTH(EDATE($B$3,-2),0),OR(Fleet!$F$8="",N(Fleet!$F$8)>=EDATE($B$3,-2))),1,0))) | L9: =IF($A9="","",SUMIFS(Trips!$M$5:$M$1004,Trips!$B$5:$B$1004,$A9,Trips!$L$5:$L$1004,"<="&$B$3)-SUMIFS(Expenses!$E$5:$E$1004,Expenses!$B$5:$B$1004,$A9,Expenses!$G$5:$G$1004,"<="&$B$3)-Fleet!$O$8*IF(N(Fleet!$E$8)=0,0,MAX(0,(YEAR(IF(Fleet!$F$8="",EOMONTH($B$3,0),MIN(Fleet!$F$8,EOMONTH($B$3,0))))-YEAR(Fleet!$E$8))*12+MONTH(IF(Fleet!$F$8="",EOMONTH($B$3,0),MIN(Fleet!$F$8,EOMONTH($B$3,0))))-MONTH(Fleet!$E$8)+1))) | M9: =IF($A9="","",Fleet!$H$8) | N9: =IF(OR($A9="",N(M9)=0),"",L9/M9) | O9: =IF(OR($A9="",N(C9)=0),"",IF(AND(I9<0,J9<0,K9<0),"REVIEW: 3 losing months",IF(I9<Assumptions!$B$9,"Below net target",IF(E9<Assumptions!$B$8,"Low utilization","On track"))))
A10: =IF(Fleet!A9="","",Fleet!A9) | B10: =IF(Fleet!A9="","",Fleet!B9&" "&Fleet!C9) | C10: =IF($A10="","",IF(AND(Fleet!$A$9<>"",N(Fleet!$E$9)<=EOMONTH($B$3,0),OR(Fleet!$F$9="",N(Fleet!$F$9)>=$B$3)),1,0)) | D10: =IF($A10="","",SUMIFS(Trips!$E$5:$E$1004,Trips!$B$5:$B$1004,$A10,Trips!$L$5:$L$1004,$B$3)) | E10: =IF(OR($A10="",N(C10)=0),"",D10/DAY(EOMONTH($B$3,0))) | F10: =IF($A10="","",SUMIFS(Trips!$H$5:$H$1004,Trips!$B$5:$B$1004,$A10,Trips!$L$5:$L$1004,$B$3)+SUMIFS(Trips!$I$5:$I$1004,Trips!$B$5:$B$1004,$A10,Trips!$L$5:$L$1004,$B$3)) | G10: =IF($A10="","",SUMIFS(Trips!$J$5:$J$1004,Trips!$B$5:$B$1004,$A10,Trips!$L$5:$L$1004,$B$3)+SUMIFS(Expenses!$E$5:$E$1004,Expenses!$B$5:$B$1004,$A10,Expenses!$G$5:$G$1004,$B$3)) | H10: =IF($A10="","",Fleet!$O$9*C10) | I10: =IF($A10="","",F10-G10-H10) | J10: =IF($A10="","",(SUMIFS(Trips!$H$5:$H$1004,Trips!$B$5:$B$1004,$A10,Trips!$L$5:$L$1004,EDATE($B$3,-1))+SUMIFS(Trips!$I$5:$I$1004,Trips!$B$5:$B$1004,$A10,Trips!$L$5:$L$1004,EDATE($B$3,-1))-SUMIFS(Trips!$J$5:$J$1004,Trips!$B$5:$B$1004,$A10,Trips!$L$5:$L$1004,EDATE($B$3,-1))-SUMIFS(Expenses!$E$5:$E$1004,Expenses!$B$5:$B$1004,$A10,Expenses!$G$5:$G$1004,EDATE($B$3,-1))-Fleet!$O$9*IF(AND(Fleet!$A$9<>"",N(Fleet!$E$9)<=EOMONTH(EDATE($B$3,-1),0),OR(Fleet!$F$9="",N(Fleet!$F$9)>=EDATE($B$3,-1))),1,0))) | K10: =IF($A10="","",(SUMIFS(Trips!$H$5:$H$1004,Trips!$B$5:$B$1004,$A10,Trips!$L$5:$L$1004,EDATE($B$3,-2))+SUMIFS(Trips!$I$5:$I$1004,Trips!$B$5:$B$1004,$A10,Trips!$L$5:$L$1004,EDATE($B$3,-2))-SUMIFS(Trips!$J$5:$J$1004,Trips!$B$5:$B$1004,$A10,Trips!$L$5:$L$1004,EDATE($B$3,-2))-SUMIFS(Expenses!$E$5:$E$1004,Expenses!$B$5:$B$1004,$A10,Expenses!$G$5:$G$1004,EDATE($B$3,-2))-Fleet!$O$9*IF(AND(Fleet!$A$9<>"",N(Fleet!$E$9)<=EOMONTH(EDATE($B$3,-2),0),OR(Fleet!$F$9="",N(Fleet!$F$9)>=EDATE($B$3,-2))),1,0))) | L10: =IF($A10="","",SUMIFS(Trips!$M$5:$M$1004,Trips!$B$5:$B$1004,$A10,Trips!$L$5:$L$1004,"<="&$B$3)-SUMIFS(Expenses!$E$5:$E$1004,Expenses!$B$5:$B$1004,$A10,Expenses!$G$5:$G$1004,"<="&$B$3)-Fleet!$O$9*IF(N(Fleet!$E$9)=0,0,MAX(0,(YEAR(IF(Fleet!$F$9="",EOMONTH($B$3,0),MIN(Fleet!$F$9,EOMONTH($B$3,0))))-YEAR(Fleet!$E$9))*12+MONTH(IF(Fleet!$F$9="",EOMONTH($B$3,0),MIN(Fleet!$F$9,EOMONTH($B$3,0))))-MONTH(Fleet!$E$9)+1))) | M10: =IF($A10="","",Fleet!$H$9) | N10: =IF(OR($A10="",N(M10)=0),"",L10/M10) | O10: =IF(OR($A10="",N(C10)=0),"",IF(AND(I10<0,J10<0,K10<0),"REVIEW: 3 losing months",IF(I10<Assumptions!$B$9,"Below net target",IF(E10<Assumptions!$B$8,"Low utilization","On track"))))
A11: =IF(Fleet!A10="","",Fleet!A10) | B11: =IF(Fleet!A10="","",Fleet!B10&" "&Fleet!C10) | C11: =IF($A11="","",IF(AND(Fleet!$A$10<>"",N(Fleet!$E$10)<=EOMONTH($B$3,0),OR(Fleet!$F$10="",N(Fleet!$F$10)>=$B$3)),1,0)) | D11: =IF($A11="","",SUMIFS(Trips!$E$5:$E$1004,Trips!$B$5:$B$1004,$A11,Trips!$L$5:$L$1004,$B$3)) | E11: =IF(OR($A11="",N(C11)=0),"",D11/DAY(EOMONTH($B$3,0))) | F11: =IF($A11="","",SUMIFS(Trips!$H$5:$H$1004,Trips!$B$5:$B$1004,$A11,Trips!$L$5:$L$1004,$B$3)+SUMIFS(Trips!$I$5:$I$1004,Trips!$B$5:$B$1004,$A11,Trips!$L$5:$L$1004,$B$3)) | G11: =IF($A11="","",SUMIFS(Trips!$J$5:$J$1004,Trips!$B$5:$B$1004,$A11,Trips!$L$5:$L$1004,$B$3)+SUMIFS(Expenses!$E$5:$E$1004,Expenses!$B$5:$B$1004,$A11,Expenses!$G$5:$G$1004,$B$3)) | H11: =IF($A11="","",Fleet!$O$10*C11) | I11: =IF($A11="","",F11-G11-H11) | J11: =IF($A11="","",(SUMIFS(Trips!$H$5:$H$1004,Trips!$B$5:$B$1004,$A11,Trips!$L$5:$L$1004,EDATE($B$3,-1))+SUMIFS(Trips!$I$5:$I$1004,Trips!$B$5:$B$1004,$A11,Trips!$L$5:$L$1004,EDATE($B$3,-1))-SUMIFS(Trips!$J$5:$J$1004,Trips!$B$5:$B$1004,$A11,Trips!$L$5:$L$1004,EDATE($B$3,-1))-SUMIFS(Expenses!$E$5:$E$1004,Expenses!$B$5:$B$1004,$A11,Expenses!$G$5:$G$1004,EDATE($B$3,-1))-Fleet!$O$10*IF(AND(Fleet!$A$10<>"",N(Fleet!$E$10)<=EOMONTH(EDATE($B$3,-1),0),OR(Fleet!$F$10="",N(Fleet!$F$10)>=EDATE($B$3,-1))),1,0))) | K11: =IF($A11="","",(SUMIFS(Trips!$H$5:$H$1004,Trips!$B$5:$B$1004,$A11,Trips!$L$5:$L$1004,EDATE($B$3,-2))+SUMIFS(Trips!$I$5:$I$1004,Trips!$B$5:$B$1004,$A11,Trips!$L$5:$L$1004,EDATE($B$3,-2))-SUMIFS(Trips!$J$5:$J$1004,Trips!$B$5:$B$1004,$A11,Trips!$L$5:$L$1004,EDATE($B$3,-2))-SUMIFS(Expenses!$E$5:$E$1004,Expenses!$B$5:$B$1004,$A11,Expenses!$G$5:$G$1004,EDATE($B$3,-2))-Fleet!$O$10*IF(AND(Fleet!$A$10<>"",N(Fleet!$E$10)<=EOMONTH(EDATE($B$3,-2),0),OR(Fleet!$F$10="",N(Fleet!$F$10)>=EDATE($B$3,-2))),1,0))) | L11: =IF($A11="","",SUMIFS(Trips!$M$5:$M$1004,Trips!$B$5:$B$1004,$A11,Trips!$L$5:$L$1004,"<="&$B$3)-SUMIFS(Expenses!$E$5:$E$1004,Expenses!$B$5:$B$1004,$A11,Expenses!$G$5:$G$1004,"<="&$B$3)-Fleet!$O$10*IF(N(Fleet!$E$10)=0,0,MAX(0,(YEAR(IF(Fleet!$F$10="",EOMONTH($B$3,0),MIN(Fleet!$F$10,EOMONTH($B$3,0))))-YEAR(Fleet!$E$10))*12+MONTH(IF(Fleet!$F$10="",EOMONTH($B$3,0),MIN(Fleet!$F$10,EOMONTH($B$3,0))))-MONTH(Fleet!$E$10)+1))) | M11: =IF($A11="","",Fleet!$H$10) | N11: =IF(OR($A11="",N(M11)=0),"",L11/M11) | O11: =IF(OR($A11="",N(C11)=0),"",IF(AND(I11<0,J11<0,K11<0),"REVIEW: 3 losing months",IF(I11<Assumptions!$B$9,"Below net target",IF(E11<Assumptions!$B$8,"Low utilization","On track"))))
A12: =IF(Fleet!A11="","",Fleet!A11) | B12: =IF(Fleet!A11="","",Fleet!B11&" "&Fleet!C11) | C12: =IF($A12="","",IF(AND(Fleet!$A$11<>"",N(Fleet!$E$11)<=EOMONTH($B$3,0),OR(Fleet!$F$11="",N(Fleet!$F$11)>=$B$3)),1,0)) | D12: =IF($A12="","",SUMIFS(Trips!$E$5:$E$1004,Trips!$B$5:$B$1004,$A12,Trips!$L$5:$L$1004,$B$3)) | E12: =IF(OR($A12="",N(C12)=0),"",D12/DAY(EOMONTH($B$3,0))) | F12: =IF($A12="","",SUMIFS(Trips!$H$5:$H$1004,Trips!$B$5:$B$1004,$A12,Trips!$L$5:$L$1004,$B$3)+SUMIFS(Trips!$I$5:$I$1004,Trips!$B$5:$B$1004,$A12,Trips!$L$5:$L$1004,$B$3)) | G12: =IF($A12="","",SUMIFS(Trips!$J$5:$J$1004,Trips!$B$5:$B$1004,$A12,Trips!$L$5:$L$1004,$B$3)+SUMIFS(Expenses!$E$5:$E$1004,Expenses!$B$5:$B$1004,$A12,Expenses!$G$5:$G$1004,$B$3)) | H12: =IF($A12="","",Fleet!$O$11*C12) | I12: =IF($A12="","",F12-G12-H12) | J12: =IF($A12="","",(SUMIFS(Trips!$H$5:$H$1004,Trips!$B$5:$B$1004,$A12,Trips!$L$5:$L$1004,EDATE($B$3,-1))+SUMIFS(Trips!$I$5:$I$1004,Trips!$B$5:$B$1004,$A12,Trips!$L$5:$L$1004,EDATE($B$3,-1))-SUMIFS(Trips!$J$5:$J$1004,Trips!$B$5:$B$1004,$A12,Trips!$L$5:$L$1004,EDATE($B$3,-1))-SUMIFS(Expenses!$E$5:$E$1004,Expenses!$B$5:$B$1004,$A12,Expenses!$G$5:$G$1004,EDATE($B$3,-1))-Fleet!$O$11*IF(AND(Fleet!$A$11<>"",N(Fleet!$E$11)<=EOMONTH(EDATE($B$3,-1),0),OR(Fleet!$F$11="",N(Fleet!$F$11)>=EDATE($B$3,-1))),1,0))) | K12: =IF($A12="","",(SUMIFS(Trips!$H$5:$H$1004,Trips!$B$5:$B$1004,$A12,Trips!$L$5:$L$1004,EDATE($B$3,-2))+SUMIFS(Trips!$I$5:$I$1004,Trips!$B$5:$B$1004,$A12,Trips!$L$5:$L$1004,EDATE($B$3,-2))-SUMIFS(Trips!$J$5:$J$1004,Trips!$B$5:$B$1004,$A12,Trips!$L$5:$L$1004,EDATE($B$3,-2))-SUMIFS(Expenses!$E$5:$E$1004,Expenses!$B$5:$B$1004,$A12,Expenses!$G$5:$G$1004,EDATE($B$3,-2))-Fleet!$O$11*IF(AND(Fleet!$A$11<>"",N(Fleet!$E$11)<=EOMONTH(EDATE($B$3,-2),0),OR(Fleet!$F$11="",N(Fleet!$F$11)>=EDATE($B$3,-2))),1,0))) | L12: =IF($A12="","",SUMIFS(Trips!$M$5:$M$1004,Trips!$B$5:$B$1004,$A12,Trips!$L$5:$L$1004,"<="&$B$3)-SUMIFS(Expenses!$E$5:$E$1004,Expenses!$B$5:$B$1004,$A12,Expenses!$G$5:$G$1004,"<="&$B$3)-Fleet!$O$11*IF(N(Fleet!$E$11)=0,0,MAX(0,(YEAR(IF(Fleet!$F$11="",EOMONTH($B$3,0),MIN(Fleet!$F$11,EOMONTH($B$3,0))))-YEAR(Fleet!$E$11))*12+MONTH(IF(Fleet!$F$11="",EOMONTH($B$3,0),MIN(Fleet!$F$11,EOMONTH($B$3,0))))-MONTH(Fleet!$E$11)+1))) | M12: =IF($A12="","",Fleet!$H$11) | N12: =IF(OR($A12="",N(M12)=0),"",L12/M12) | O12: =IF(OR($A12="",N(C12)=0),"",IF(AND(I12<0,J12<0,K12<0),"REVIEW: 3 losing months",IF(I12<Assumptions!$B$9,"Below net target",IF(E12<Assumptions!$B$8,"Low utilization","On track"))))
A13: =IF(Fleet!A12="","",Fleet!A12) | B13: =IF(Fleet!A12="","",Fleet!B12&" "&Fleet!C12) | C13: =IF($A13="","",IF(AND(Fleet!$A$12<>"",N(Fleet!$E$12)<=EOMONTH($B$3,0),OR(Fleet!$F$12="",N(Fleet!$F$12)>=$B$3)),1,0)) | D13: =IF($A13="","",SUMIFS(Trips!$E$5:$E$1004,Trips!$B$5:$B$1004,$A13,Trips!$L$5:$L$1004,$B$3)) | E13: =IF(OR($A13="",N(C13)=0),"",D13/DAY(EOMONTH($B$3,0))) | F13: =IF($A13="","",SUMIFS(Trips!$H$5:$H$1004,Trips!$B$5:$B$1004,$A13,Trips!$L$5:$L$1004,$B$3)+SUMIFS(Trips!$I$5:$I$1004,Trips!$B$5:$B$1004,$A13,Trips!$L$5:$L$1004,$B$3)) | G13: =IF($A13="","",SUMIFS(Trips!$J$5:$J$1004,Trips!$B$5:$B$1004,$A13,Trips!$L$5:$L$1004,$B$3)+SUMIFS(Expenses!$E$5:$E$1004,Expenses!$B$5:$B$1004,$A13,Expenses!$G$5:$G$1004,$B$3)) | H13: =IF($A13="","",Fleet!$O$12*C13) | I13: =IF($A13="","",F13-G13-H13) | J13: =IF($A13="","",(SUMIFS(Trips!$H$5:$H$1004,Trips!$B$5:$B$1004,$A13,Trips!$L$5:$L$1004,EDATE($B$3,-1))+SUMIFS(Trips!$I$5:$I$1004,Trips!$B$5:$B$1004,$A13,Trips!$L$5:$L$1004,EDATE($B$3,-1))-SUMIFS(Trips!$J$5:$J$1004,Trips!$B$5:$B$1004,$A13,Trips!$L$5:$L$1004,EDATE($B$3,-1))-SUMIFS(Expenses!$E$5:$E$1004,Expenses!$B$5:$B$1004,$A13,Expenses!$G$5:$G$1004,EDATE($B$3,-1))-Fleet!$O$12*IF(AND(Fleet!$A$12<>"",N(Fleet!$E$12)<=EOMONTH(EDATE($B$3,-1),0),OR(Fleet!$F$12="",N(Fleet!$F$12)>=EDATE($B$3,-1))),1,0))) | K13: =IF($A13="","",(SUMIFS(Trips!$H$5:$H$1004,Trips!$B$5:$B$1004,$A13,Trips!$L$5:$L$1004,EDATE($B$3,-2))+SUMIFS(Trips!$I$5:$I$1004,Trips!$B$5:$B$1004,$A13,Trips!$L$5:$L$1004,EDATE($B$3,-2))-SUMIFS(Trips!$J$5:$J$1004,Trips!$B$5:$B$1004,$A13,Trips!$L$5:$L$1004,EDATE($B$3,-2))-SUMIFS(Expenses!$E$5:$E$1004,Expenses!$B$5:$B$1004,$A13,Expenses!$G$5:$G$1004,EDATE($B$3,-2))-Fleet!$O$12*IF(AND(Fleet!$A$12<>"",N(Fleet!$E$12)<=EOMONTH(EDATE($B$3,-2),0),OR(Fleet!$F$12="",N(Fleet!$F$12)>=EDATE($B$3,-2))),1,0))) | L13: =IF($A13="","",SUMIFS(Trips!$M$5:$M$1004,Trips!$B$5:$B$1004,$A13,Trips!$L$5:$L$1004,"<="&$B$3)-SUMIFS(Expenses!$E$5:$E$1004,Expenses!$B$5:$B$1004,$A13,Expenses!$G$5:$G$1004,"<="&$B$3)-Fleet!$O$12*IF(N(Fleet!$E$12)=0,0,MAX(0,(YEAR(IF(Fleet!$F$12="",EOMONTH($B$3,0),MIN(Fleet!$F$12,EOMONTH($B$3,0))))-YEAR(Fleet!$E$12))*12+MONTH(IF(Fleet!$F$12="",EOMONTH($B$3,0),MIN(Fleet!$F$12,EOMONTH($B$3,0))))-MONTH(Fleet!$E$12)+1))) | M13: =IF($A13="","",Fleet!$H$12) | N13: =IF(OR($A13="",N(M13)=0),"",L13/M13) | O13: =IF(OR($A13="",N(C13)=0),"",IF(AND(I13<0,J13<0,K13<0),"REVIEW: 3 losing months",IF(I13<Assumptions!$B$9,"Below net target",IF(E13<Assumptions!$B$8,"Low utilization","On track"))))
A14: =IF(Fleet!A13="","",Fleet!A13) | B14: =IF(Fleet!A13="","",Fleet!B13&" "&Fleet!C13) | C14: =IF($A14="","",IF(AND(Fleet!$A$13<>"",N(Fleet!$E$13)<=EOMONTH($B$3,0),OR(Fleet!$F$13="",N(Fleet!$F$13)>=$B$3)),1,0)) | D14: =IF($A14="","",SUMIFS(Trips!$E$5:$E$1004,Trips!$B$5:$B$1004,$A14,Trips!$L$5:$L$1004,$B$3)) | E14: =IF(OR($A14="",N(C14)=0),"",D14/DAY(EOMONTH($B$3,0))) | F14: =IF($A14="","",SUMIFS(Trips!$H$5:$H$1004,Trips!$B$5:$B$1004,$A14,Trips!$L$5:$L$1004,$B$3)+SUMIFS(Trips!$I$5:$I$1004,Trips!$B$5:$B$1004,$A14,Trips!$L$5:$L$1004,$B$3)) | G14: =IF($A14="","",SUMIFS(Trips!$J$5:$J$1004,Trips!$B$5:$B$1004,$A14,Trips!$L$5:$L$1004,$B$3)+SUMIFS(Expenses!$E$5:$E$1004,Expenses!$B$5:$B$1004,$A14,Expenses!$G$5:$G$1004,$B$3)) | H14: =IF($A14="","",Fleet!$O$13*C14) | I14: =IF($A14="","",F14-G14-H14) | J14: =IF($A14="","",(SUMIFS(Trips!$H$5:$H$1004,Trips!$B$5:$B$1004,$A14,Trips!$L$5:$L$1004,EDATE($B$3,-1))+SUMIFS(Trips!$I$5:$I$1004,Trips!$B$5:$B$1004,$A14,Trips!$L$5:$L$1004,EDATE($B$3,-1))-SUMIFS(Trips!$J$5:$J$1004,Trips!$B$5:$B$1004,$A14,Trips!$L$5:$L$1004,EDATE($B$3,-1))-SUMIFS(Expenses!$E$5:$E$1004,Expenses!$B$5:$B$1004,$A14,Expenses!$G$5:$G$1004,EDATE($B$3,-1))-Fleet!$O$13*IF(AND(Fleet!$A$13<>"",N(Fleet!$E$13)<=EOMONTH(EDATE($B$3,-1),0),OR(Fleet!$F$13="",N(Fleet!$F$13)>=EDATE($B$3,-1))),1,0))) | K14: =IF($A14="","",(SUMIFS(Trips!$H$5:$H$1004,Trips!$B$5:$B$1004,$A14,Trips!$L$5:$L$1004,EDATE($B$3,-2))+SUMIFS(Trips!$I$5:$I$1004,Trips!$B$5:$B$1004,$A14,Trips!$L$5:$L$1004,EDATE($B$3,-2))-SUMIFS(Trips!$J$5:$J$1004,Trips!$B$5:$B$1004,$A14,Trips!$L$5:$L$1004,EDATE($B$3,-2))-SUMIFS(Expenses!$E$5:$E$1004,Expenses!$B$5:$B$1004,$A14,Expenses!$G$5:$G$1004,EDATE($B$3,-2))-Fleet!$O$13*IF(AND(Fleet!$A$13<>"",N(Fleet!$E$13)<=EOMONTH(EDATE($B$3,-2),0),OR(Fleet!$F$13="",N(Fleet!$F$13)>=EDATE($B$3,-2))),1,0))) | L14: =IF($A14="","",SUMIFS(Trips!$M$5:$M$1004,Trips!$B$5:$B$1004,$A14,Trips!$L$5:$L$1004,"<="&$B$3)-SUMIFS(Expenses!$E$5:$E$1004,Expenses!$B$5:$B$1004,$A14,Expenses!$G$5:$G$1004,"<="&$B$3)-Fleet!$O$13*IF(N(Fleet!$E$13)=0,0,MAX(0,(YEAR(IF(Fleet!$F$13="",EOMONTH($B$3,0),MIN(Fleet!$F$13,EOMONTH($B$3,0))))-YEAR(Fleet!$E$13))*12+MONTH(IF(Fleet!$F$13="",EOMONTH($B$3,0),MIN(Fleet!$F$13,EOMONTH($B$3,0))))-MONTH(Fleet!$E$13)+1))) | M14: =IF($A14="","",Fleet!$H$13) | N14: =IF(OR($A14="",N(M14)=0),"",L14/M14) | O14: =IF(OR($A14="",N(C14)=0),"",IF(AND(I14<0,J14<0,K14<0),"REVIEW: 3 losing months",IF(I14<Assumptions!$B$9,"Below net target",IF(E14<Assumptions!$B$8,"Low utilization","On track"))))
A15: =IF(Fleet!A14="","",Fleet!A14) | B15: =IF(Fleet!A14="","",Fleet!B14&" "&Fleet!C14) | C15: =IF($A15="","",IF(AND(Fleet!$A$14<>"",N(Fleet!$E$14)<=EOMONTH($B$3,0),OR(Fleet!$F$14="",N(Fleet!$F$14)>=$B$3)),1,0)) | D15: =IF($A15="","",SUMIFS(Trips!$E$5:$E$1004,Trips!$B$5:$B$1004,$A15,Trips!$L$5:$L$1004,$B$3)) | E15: =IF(OR($A15="",N(C15)=0),"",D15/DAY(EOMONTH($B$3,0))) | F15: =IF($A15="","",SUMIFS(Trips!$H$5:$H$1004,Trips!$B$5:$B$1004,$A15,Trips!$L$5:$L$1004,$B$3)+SUMIFS(Trips!$I$5:$I$1004,Trips!$B$5:$B$1004,$A15,Trips!$L$5:$L$1004,$B$3)) | G15: =IF($A15="","",SUMIFS(Trips!$J$5:$J$1004,Trips!$B$5:$B$1004,$A15,Trips!$L$5:$L$1004,$B$3)+SUMIFS(Expenses!$E$5:$E$1004,Expenses!$B$5:$B$1004,$A15,Expenses!$G$5:$G$1004,$B$3)) | H15: =IF($A15="","",Fleet!$O$14*C15) | I15: =IF($A15="","",F15-G15-H15) | J15: =IF($A15="","",(SUMIFS(Trips!$H$5:$H$1004,Trips!$B$5:$B$1004,$A15,Trips!$L$5:$L$1004,EDATE($B$3,-1))+SUMIFS(Trips!$I$5:$I$1004,Trips!$B$5:$B$1004,$A15,Trips!$L$5:$L$1004,EDATE($B$3,-1))-SUMIFS(Trips!$J$5:$J$1004,Trips!$B$5:$B$1004,$A15,Trips!$L$5:$L$1004,EDATE($B$3,-1))-SUMIFS(Expenses!$E$5:$E$1004,Expenses!$B$5:$B$1004,$A15,Expenses!$G$5:$G$1004,EDATE($B$3,-1))-Fleet!$O$14*IF(AND(Fleet!$A$14<>"",N(Fleet!$E$14)<=EOMONTH(EDATE($B$3,-1),0),OR(Fleet!$F$14="",N(Fleet!$F$14)>=EDATE($B$3,-1))),1,0))) | K15: =IF($A15="","",(SUMIFS(Trips!$H$5:$H$1004,Trips!$B$5:$B$1004,$A15,Trips!$L$5:$L$1004,EDATE($B$3,-2))+SUMIFS(Trips!$I$5:$I$1004,Trips!$B$5:$B$1004,$A15,Trips!$L$5:$L$1004,EDATE($B$3,-2))-SUMIFS(Trips!$J$5:$J$1004,Trips!$B$5:$B$1004,$A15,Trips!$L$5:$L$1004,EDATE($B$3,-2))-SUMIFS(Expenses!$E$5:$E$1004,Expenses!$B$5:$B$1004,$A15,Expenses!$G$5:$G$1004,EDATE($B$3,-2))-Fleet!$O$14*IF(AND(Fleet!$A$14<>"",N(Fleet!$E$14)<=EOMONTH(EDATE($B$3,-2),0),OR(Fleet!$F$14="",N(Fleet!$F$14)>=EDATE($B$3,-2))),1,0))) | L15: =IF($A15="","",SUMIFS(Trips!$M$5:$M$1004,Trips!$B$5:$B$1004,$A15,Trips!$L$5:$L$1004,"<="&$B$3)-SUMIFS(Expenses!$E$5:$E$1004,Expenses!$B$5:$B$1004,$A15,Expenses!$G$5:$G$1004,"<="&$B$3)-Fleet!$O$14*IF(N(Fleet!$E$14)=0,0,MAX(0,(YEAR(IF(Fleet!$F$14="",EOMONTH($B$3,0),MIN(Fleet!$F$14,EOMONTH($B$3,0))))-YEAR(Fleet!$E$14))*12+MONTH(IF(Fleet!$F$14="",EOMONTH($B$3,0),MIN(Fleet!$F$14,EOMONTH($B$3,0))))-MONTH(Fleet!$E$14)+1))) | M15: =IF($A15="","",Fleet!$H$14) | N15: =IF(OR($A15="",N(M15)=0),"",L15/M15) | O15: =IF(OR($A15="",N(C15)=0),"",IF(AND(I15<0,J15<0,K15<0),"REVIEW: 3 losing months",IF(I15<Assumptions!$B$9,"Below net target",IF(E15<Assumptions!$B$8,"Low utilization","On track"))))
A16: =IF(Fleet!A15="","",Fleet!A15) | B16: =IF(Fleet!A15="","",Fleet!B15&" "&Fleet!C15) | C16: =IF($A16="","",IF(AND(Fleet!$A$15<>"",N(Fleet!$E$15)<=EOMONTH($B$3,0),OR(Fleet!$F$15="",N(Fleet!$F$15)>=$B$3)),1,0)) | D16: =IF($A16="","",SUMIFS(Trips!$E$5:$E$1004,Trips!$B$5:$B$1004,$A16,Trips!$L$5:$L$1004,$B$3)) | E16: =IF(OR($A16="",N(C16)=0),"",D16/DAY(EOMONTH($B$3,0))) | F16: =IF($A16="","",SUMIFS(Trips!$H$5:$H$1004,Trips!$B$5:$B$1004,$A16,Trips!$L$5:$L$1004,$B$3)+SUMIFS(Trips!$I$5:$I$1004,Trips!$B$5:$B$1004,$A16,Trips!$L$5:$L$1004,$B$3)) | G16: =IF($A16="","",SUMIFS(Trips!$J$5:$J$1004,Trips!$B$5:$B$1004,$A16,Trips!$L$5:$L$1004,$B$3)+SUMIFS(Expenses!$E$5:$E$1004,Expenses!$B$5:$B$1004,$A16,Expenses!$G$5:$G$1004,$B$3)) | H16: =IF($A16="","",Fleet!$O$15*C16) | I16: =IF($A16="","",F16-G16-H16) | J16: =IF($A16="","",(SUMIFS(Trips!$H$5:$H$1004,Trips!$B$5:$B$1004,$A16,Trips!$L$5:$L$1004,EDATE($B$3,-1))+SUMIFS(Trips!$I$5:$I$1004,Trips!$B$5:$B$1004,$A16,Trips!$L$5:$L$1004,EDATE($B$3,-1))-SUMIFS(Trips!$J$5:$J$1004,Trips!$B$5:$B$1004,$A16,Trips!$L$5:$L$1004,EDATE($B$3,-1))-SUMIFS(Expenses!$E$5:$E$1004,Expenses!$B$5:$B$1004,$A16,Expenses!$G$5:$G$1004,EDATE($B$3,-1))-Fleet!$O$15*IF(AND(Fleet!$A$15<>"",N(Fleet!$E$15)<=EOMONTH(EDATE($B$3,-1),0),OR(Fleet!$F$15="",N(Fleet!$F$15)>=EDATE($B$3,-1))),1,0))) | K16: =IF($A16="","",(SUMIFS(Trips!$H$5:$H$1004,Trips!$B$5:$B$1004,$A16,Trips!$L$5:$L$1004,EDATE($B$3,-2))+SUMIFS(Trips!$I$5:$I$1004,Trips!$B$5:$B$1004,$A16,Trips!$L$5:$L$1004,EDATE($B$3,-2))-SUMIFS(Trips!$J$5:$J$1004,Trips!$B$5:$B$1004,$A16,Trips!$L$5:$L$1004,EDATE($B$3,-2))-SUMIFS(Expenses!$E$5:$E$1004,Expenses!$B$5:$B$1004,$A16,Expenses!$G$5:$G$1004,EDATE($B$3,-2))-Fleet!$O$15*IF(AND(Fleet!$A$15<>"",N(Fleet!$E$15)<=EOMONTH(EDATE($B$3,-2),0),OR(Fleet!$F$15="",N(Fleet!$F$15)>=EDATE($B$3,-2))),1,0))) | L16: =IF($A16="","",SUMIFS(Trips!$M$5:$M$1004,Trips!$B$5:$B$1004,$A16,Trips!$L$5:$L$1004,"<="&$B$3)-SUMIFS(Expenses!$E$5:$E$1004,Expenses!$B$5:$B$1004,$A16,Expenses!$G$5:$G$1004,"<="&$B$3)-Fleet!$O$15*IF(N(Fleet!$E$15)=0,0,MAX(0,(YEAR(IF(Fleet!$F$15="",EOMONTH($B$3,0),MIN(Fleet!$F$15,EOMONTH($B$3,0))))-YEAR(Fleet!$E$15))*12+MONTH(IF(Fleet!$F$15="",EOMONTH($B$3,0),MIN(Fleet!$F$15,EOMONTH($B$3,0))))-MONTH(Fleet!$E$15)+1))) | M16: =IF($A16="","",Fleet!$H$15) | N16: =IF(OR($A16="",N(M16)=0),"",L16/M16) | O16: =IF(OR($A16="",N(C16)=0),"",IF(AND(I16<0,J16<0,K16<0),"REVIEW: 3 losing months",IF(I16<Assumptions!$B$9,"Below net target",IF(E16<Assumptions!$B$8,"Low utilization","On track"))))
A17: =IF(Fleet!A16="","",Fleet!A16) | B17: =IF(Fleet!A16="","",Fleet!B16&" "&Fleet!C16) | C17: =IF($A17="","",IF(AND(Fleet!$A$16<>"",N(Fleet!$E$16)<=EOMONTH($B$3,0),OR(Fleet!$F$16="",N(Fleet!$F$16)>=$B$3)),1,0)) | D17: =IF($A17="","",SUMIFS(Trips!$E$5:$E$1004,Trips!$B$5:$B$1004,$A17,Trips!$L$5:$L$1004,$B$3)) | E17: =IF(OR($A17="",N(C17)=0),"",D17/DAY(EOMONTH($B$3,0))) | F17: =IF($A17="","",SUMIFS(Trips!$H$5:$H$1004,Trips!$B$5:$B$1004,$A17,Trips!$L$5:$L$1004,$B$3)+SUMIFS(Trips!$I$5:$I$1004,Trips!$B$5:$B$1004,$A17,Trips!$L$5:$L$1004,$B$3)) | G17: =IF($A17="","",SUMIFS(Trips!$J$5:$J$1004,Trips!$B$5:$B$1004,$A17,Trips!$L$5:$L$1004,$B$3)+SUMIFS(Expenses!$E$5:$E$1004,Expenses!$B$5:$B$1004,$A17,Expenses!$G$5:$G$1004,$B$3)) | H17: =IF($A17="","",Fleet!$O$16*C17) | I17: =IF($A17="","",F17-G17-H17) | J17: =IF($A17="","",(SUMIFS(Trips!$H$5:$H$1004,Trips!$B$5:$B$1004,$A17,Trips!$L$5:$L$1004,EDATE($B$3,-1))+SUMIFS(Trips!$I$5:$I$1004,Trips!$B$5:$B$1004,$A17,Trips!$L$5:$L$1004,EDATE($B$3,-1))-SUMIFS(Trips!$J$5:$J$1004,Trips!$B$5:$B$1004,$A17,Trips!$L$5:$L$1004,EDATE($B$3,-1))-SUMIFS(Expenses!$E$5:$E$1004,Expenses!$B$5:$B$1004,$A17,Expenses!$G$5:$G$1004,EDATE($B$3,-1))-Fleet!$O$16*IF(AND(Fleet!$A$16<>"",N(Fleet!$E$16)<=EOMONTH(EDATE($B$3,-1),0),OR(Fleet!$F$16="",N(Fleet!$F$16)>=EDATE($B$3,-1))),1,0))) | K17: =IF($A17="","",(SUMIFS(Trips!$H$5:$H$1004,Trips!$B$5:$B$1004,$A17,Trips!$L$5:$L$1004,EDATE($B$3,-2))+SUMIFS(Trips!$I$5:$I$1004,Trips!$B$5:$B$1004,$A17,Trips!$L$5:$L$1004,EDATE($B$3,-2))-SUMIFS(Trips!$J$5:$J$1004,Trips!$B$5:$B$1004,$A17,Trips!$L$5:$L$1004,EDATE($B$3,-2))-SUMIFS(Expenses!$E$5:$E$1004,Expenses!$B$5:$B$1004,$A17,Expenses!$G$5:$G$1004,EDATE($B$3,-2))-Fleet!$O$16*IF(AND(Fleet!$A$16<>"",N(Fleet!$E$16)<=EOMONTH(EDATE($B$3,-2),0),OR(Fleet!$F$16="",N(Fleet!$F$16)>=EDATE($B$3,-2))),1,0))) | L17: =IF($A17="","",SUMIFS(Trips!$M$5:$M$1004,Trips!$B$5:$B$1004,$A17,Trips!$L$5:$L$1004,"<="&$B$3)-SUMIFS(Expenses!$E$5:$E$1004,Expenses!$B$5:$B$1004,$A17,Expenses!$G$5:$G$1004,"<="&$B$3)-Fleet!$O$16*IF(N(Fleet!$E$16)=0,0,MAX(0,(YEAR(IF(Fleet!$F$16="",EOMONTH($B$3,0),MIN(Fleet!$F$16,EOMONTH($B$3,0))))-YEAR(Fleet!$E$16))*12+MONTH(IF(Fleet!$F$16="",EOMONTH($B$3,0),MIN(Fleet!$F$16,EOMONTH($B$3,0))))-MONTH(Fleet!$E$16)+1))) | M17: =IF($A17="","",Fleet!$H$16) | N17: =IF(OR($A17="",N(M17)=0),"",L17/M17) | O17: =IF(OR($A17="",N(C17)=0),"",IF(AND(I17<0,J17<0,K17<0),"REVIEW: 3 losing months",IF(I17<Assumptions!$B$9,"Below net target",IF(E17<Assumptions!$B$8,"Low utilization","On track"))))
A18: =IF(Fleet!A17="","",Fleet!A17) | B18: =IF(Fleet!A17="","",Fleet!B17&" "&Fleet!C17) | C18: =IF($A18="","",IF(AND(Fleet!$A$17<>"",N(Fleet!$E$17)<=EOMONTH($B$3,0),OR(Fleet!$F$17="",N(Fleet!$F$17)>=$B$3)),1,0)) | D18: =IF($A18="","",SUMIFS(Trips!$E$5:$E$1004,Trips!$B$5:$B$1004,$A18,Trips!$L$5:$L$1004,$B$3)) | E18: =IF(OR($A18="",N(C18)=0),"",D18/DAY(EOMONTH($B$3,0))) | F18: =IF($A18="","",SUMIFS(Trips!$H$5:$H$1004,Trips!$B$5:$B$1004,$A18,Trips!$L$5:$L$1004,$B$3)+SUMIFS(Trips!$I$5:$I$1004,Trips!$B$5:$B$1004,$A18,Trips!$L$5:$L$1004,$B$3)) | G18: =IF($A18="","",SUMIFS(Trips!$J$5:$J$1004,Trips!$B$5:$B$1004,$A18,Trips!$L$5:$L$1004,$B$3)+SUMIFS(Expenses!$E$5:$E$1004,Expenses!$B$5:$B$1004,$A18,Expenses!$G$5:$G$1004,$B$3)) | H18: =IF($A18="","",Fleet!$O$17*C18) | I18: =IF($A18="","",F18-G18-H18) | J18: =IF($A18="","",(SUMIFS(Trips!$H$5:$H$1004,Trips!$B$5:$B$1004,$A18,Trips!$L$5:$L$1004,EDATE($B$3,-1))+SUMIFS(Trips!$I$5:$I$1004,Trips!$B$5:$B$1004,$A18,Trips!$L$5:$L$1004,EDATE($B$3,-1))-SUMIFS(Trips!$J$5:$J$1004,Trips!$B$5:$B$1004,$A18,Trips!$L$5:$L$1004,EDATE($B$3,-1))-SUMIFS(Expenses!$E$5:$E$1004,Expenses!$B$5:$B$1004,$A18,Expenses!$G$5:$G$1004,EDATE($B$3,-1))-Fleet!$O$17*IF(AND(Fleet!$A$17<>"",N(Fleet!$E$17)<=EOMONTH(EDATE($B$3,-1),0),OR(Fleet!$F$17="",N(Fleet!$F$17)>=EDATE($B$3,-1))),1,0))) | K18: =IF($A18="","",(SUMIFS(Trips!$H$5:$H$1004,Trips!$B$5:$B$1004,$A18,Trips!$L$5:$L$1004,EDATE($B$3,-2))+SUMIFS(Trips!$I$5:$I$1004,Trips!$B$5:$B$1004,$A18,Trips!$L$5:$L$1004,EDATE($B$3,-2))-SUMIFS(Trips!$J$5:$J$1004,Trips!$B$5:$B$1004,$A18,Trips!$L$5:$L$1004,EDATE($B$3,-2))-SUMIFS(Expenses!$E$5:$E$1004,Expenses!$B$5:$B$1004,$A18,Expenses!$G$5:$G$1004,EDATE($B$3,-2))-Fleet!$O$17*IF(AND(Fleet!$A$17<>"",N(Fleet!$E$17)<=EOMONTH(EDATE($B$3,-2),0),OR(Fleet!$F$17="",N(Fleet!$F$17)>=EDATE($B$3,-2))),1,0))) | L18: =IF($A18="","",SUMIFS(Trips!$M$5:$M$1004,Trips!$B$5:$B$1004,$A18,Trips!$L$5:$L$1004,"<="&$B$3)-SUMIFS(Expenses!$E$5:$E$1004,Expenses!$B$5:$B$1004,$A18,Expenses!$G$5:$G$1004,"<="&$B$3)-Fleet!$O$17*IF(N(Fleet!$E$17)=0,0,MAX(0,(YEAR(IF(Fleet!$F$17="",EOMONTH($B$3,0),MIN(Fleet!$F$17,EOMONTH($B$3,0))))-YEAR(Fleet!$E$17))*12+MONTH(IF(Fleet!$F$17="",EOMONTH($B$3,0),MIN(Fleet!$F$17,EOMONTH($B$3,0))))-MONTH(Fleet!$E$17)+1))) | M18: =IF($A18="","",Fleet!$H$17) | N18: =IF(OR($A18="",N(M18)=0),"",L18/M18) | O18: =IF(OR($A18="",N(C18)=0),"",IF(AND(I18<0,J18<0,K18<0),"REVIEW: 3 losing months",IF(I18<Assumptions!$B$9,"Below net target",IF(E18<Assumptions!$B$8,"Low utilization","On track"))))
A19: =IF(Fleet!A18="","",Fleet!A18) | B19: =IF(Fleet!A18="","",Fleet!B18&" "&Fleet!C18) | C19: =IF($A19="","",IF(AND(Fleet!$A$18<>"",N(Fleet!$E$18)<=EOMONTH($B$3,0),OR(Fleet!$F$18="",N(Fleet!$F$18)>=$B$3)),1,0)) | D19: =IF($A19="","",SUMIFS(Trips!$E$5:$E$1004,Trips!$B$5:$B$1004,$A19,Trips!$L$5:$L$1004,$B$3)) | E19: =IF(OR($A19="",N(C19)=0),"",D19/DAY(EOMONTH($B$3,0))) | F19: =IF($A19="","",SUMIFS(Trips!$H$5:$H$1004,Trips!$B$5:$B$1004,$A19,Trips!$L$5:$L$1004,$B$3)+SUMIFS(Trips!$I$5:$I$1004,Trips!$B$5:$B$1004,$A19,Trips!$L$5:$L$1004,$B$3)) | G19: =IF($A19="","",SUMIFS(Trips!$J$5:$J$1004,Trips!$B$5:$B$1004,$A19,Trips!$L$5:$L$1004,$B$3)+SUMIFS(Expenses!$E$5:$E$1004,Expenses!$B$5:$B$1004,$A19,Expenses!$G$5:$G$1004,$B$3)) | H19: =IF($A19="","",Fleet!$O$18*C19) | I19: =IF($A19="","",F19-G19-H19) | J19: =IF($A19="","",(SUMIFS(Trips!$H$5:$H$1004,Trips!$B$5:$B$1004,$A19,Trips!$L$5:$L$1004,EDATE($B$3,-1))+SUMIFS(Trips!$I$5:$I$1004,Trips!$B$5:$B$1004,$A19,Trips!$L$5:$L$1004,EDATE($B$3,-1))-SUMIFS(Trips!$J$5:$J$1004,Trips!$B$5:$B$1004,$A19,Trips!$L$5:$L$1004,EDATE($B$3,-1))-SUMIFS(Expenses!$E$5:$E$1004,Expenses!$B$5:$B$1004,$A19,Expenses!$G$5:$G$1004,EDATE($B$3,-1))-Fleet!$O$18*IF(AND(Fleet!$A$18<>"",N(Fleet!$E$18)<=EOMONTH(EDATE($B$3,-1),0),OR(Fleet!$F$18="",N(Fleet!$F$18)>=EDATE($B$3,-1))),1,0))) | K19: =IF($A19="","",(SUMIFS(Trips!$H$5:$H$1004,Trips!$B$5:$B$1004,$A19,Trips!$L$5:$L$1004,EDATE($B$3,-2))+SUMIFS(Trips!$I$5:$I$1004,Trips!$B$5:$B$1004,$A19,Trips!$L$5:$L$1004,EDATE($B$3,-2))-SUMIFS(Trips!$J$5:$J$1004,Trips!$B$5:$B$1004,$A19,Trips!$L$5:$L$1004,EDATE($B$3,-2))-SUMIFS(Expenses!$E$5:$E$1004,Expenses!$B$5:$B$1004,$A19,Expenses!$G$5:$G$1004,EDATE($B$3,-2))-Fleet!$O$18*IF(AND(Fleet!$A$18<>"",N(Fleet!$E$18)<=EOMONTH(EDATE($B$3,-2),0),OR(Fleet!$F$18="",N(Fleet!$F$18)>=EDATE($B$3,-2))),1,0))) | L19: =IF($A19="","",SUMIFS(Trips!$M$5:$M$1004,Trips!$B$5:$B$1004,$A19,Trips!$L$5:$L$1004,"<="&$B$3)-SUMIFS(Expenses!$E$5:$E$1004,Expenses!$B$5:$B$1004,$A19,Expenses!$G$5:$G$1004,"<="&$B$3)-Fleet!$O$18*IF(N(Fleet!$E$18)=0,0,MAX(0,(YEAR(IF(Fleet!$F$18="",EOMONTH($B$3,0),MIN(Fleet!$F$18,EOMONTH($B$3,0))))-YEAR(Fleet!$E$18))*12+MONTH(IF(Fleet!$F$18="",EOMONTH($B$3,0),MIN(Fleet!$F$18,EOMONTH($B$3,0))))-MONTH(Fleet!$E$18)+1))) | M19: =IF($A19="","",Fleet!$H$18) | N19: =IF(OR($A19="",N(M19)=0),"",L19/M19) | O19: =IF(OR($A19="",N(C19)=0),"",IF(AND(I19<0,J19<0,K19<0),"REVIEW: 3 losing months",IF(I19<Assumptions!$B$9,"Below net target",IF(E19<Assumptions!$B$8,"Low utilization","On track"))))
A20: =IF(Fleet!A19="","",Fleet!A19) | B20: =IF(Fleet!A19="","",Fleet!B19&" "&Fleet!C19) | C20: =IF($A20="","",IF(AND(Fleet!$A$19<>"",N(Fleet!$E$19)<=EOMONTH($B$3,0),OR(Fleet!$F$19="",N(Fleet!$F$19)>=$B$3)),1,0)) | D20: =IF($A20="","",SUMIFS(Trips!$E$5:$E$1004,Trips!$B$5:$B$1004,$A20,Trips!$L$5:$L$1004,$B$3)) | E20: =IF(OR($A20="",N(C20)=0),"",D20/DAY(EOMONTH($B$3,0))) | F20: =IF($A20="","",SUMIFS(Trips!$H$5:$H$1004,Trips!$B$5:$B$1004,$A20,Trips!$L$5:$L$1004,$B$3)+SUMIFS(Trips!$I$5:$I$1004,Trips!$B$5:$B$1004,$A20,Trips!$L$5:$L$1004,$B$3)) | G20: =IF($A20="","",SUMIFS(Trips!$J$5:$J$1004,Trips!$B$5:$B$1004,$A20,Trips!$L$5:$L$1004,$B$3)+SUMIFS(Expenses!$E$5:$E$1004,Expenses!$B$5:$B$1004,$A20,Expenses!$G$5:$G$1004,$B$3)) | H20: =IF($A20="","",Fleet!$O$19*C20) | I20: =IF($A20="","",F20-G20-H20) | J20: =IF($A20="","",(SUMIFS(Trips!$H$5:$H$1004,Trips!$B$5:$B$1004,$A20,Trips!$L$5:$L$1004,EDATE($B$3,-1))+SUMIFS(Trips!$I$5:$I$1004,Trips!$B$5:$B$1004,$A20,Trips!$L$5:$L$1004,EDATE($B$3,-1))-SUMIFS(Trips!$J$5:$J$1004,Trips!$B$5:$B$1004,$A20,Trips!$L$5:$L$1004,EDATE($B$3,-1))-SUMIFS(Expenses!$E$5:$E$1004,Expenses!$B$5:$B$1004,$A20,Expenses!$G$5:$G$1004,EDATE($B$3,-1))-Fleet!$O$19*IF(AND(Fleet!$A$19<>"",N(Fleet!$E$19)<=EOMONTH(EDATE($B$3,-1),0),OR(Fleet!$F$19="",N(Fleet!$F$19)>=EDATE($B$3,-1))),1,0))) | K20: =IF($A20="","",(SUMIFS(Trips!$H$5:$H$1004,Trips!$B$5:$B$1004,$A20,Trips!$L$5:$L$1004,EDATE($B$3,-2))+SUMIFS(Trips!$I$5:$I$1004,Trips!$B$5:$B$1004,$A20,Trips!$L$5:$L$1004,EDATE($B$3,-2))-SUMIFS(Trips!$J$5:$J$1004,Trips!$B$5:$B$1004,$A20,Trips!$L$5:$L$1004,EDATE($B$3,-2))-SUMIFS(Expenses!$E$5:$E$1004,Expenses!$B$5:$B$1004,$A20,Expenses!$G$5:$G$1004,EDATE($B$3,-2))-Fleet!$O$19*IF(AND(Fleet!$A$19<>"",N(Fleet!$E$19)<=EOMONTH(EDATE($B$3,-2),0),OR(Fleet!$F$19="",N(Fleet!$F$19)>=EDATE($B$3,-2))),1,0))) | L20: =IF($A20="","",SUMIFS(Trips!$M$5:$M$1004,Trips!$B$5:$B$1004,$A20,Trips!$L$5:$L$1004,"<="&$B$3)-SUMIFS(Expenses!$E$5:$E$1004,Expenses!$B$5:$B$1004,$A20,Expenses!$G$5:$G$1004,"<="&$B$3)-Fleet!$O$19*IF(N(Fleet!$E$19)=0,0,MAX(0,(YEAR(IF(Fleet!$F$19="",EOMONTH($B$3,0),MIN(Fleet!$F$19,EOMONTH($B$3,0))))-YEAR(Fleet!$E$19))*12+MONTH(IF(Fleet!$F$19="",EOMONTH($B$3,0),MIN(Fleet!$F$19,EOMONTH($B$3,0))))-MONTH(Fleet!$E$19)+1))) | M20: =IF($A20="","",Fleet!$H$19) | N20: =IF(OR($A20="",N(M20)=0),"",L20/M20) | O20: =IF(OR($A20="",N(C20)=0),"",IF(AND(I20<0,J20<0,K20<0),"REVIEW: 3 losing months",IF(I20<Assumptions!$B$9,"Below net target",IF(E20<Assumptions!$B$8,"Low utilization","On track"))))
A21: =IF(Fleet!A20="","",Fleet!A20) | B21: =IF(Fleet!A20="","",Fleet!B20&" "&Fleet!C20) | C21: =IF($A21="","",IF(AND(Fleet!$A$20<>"",N(Fleet!$E$20)<=EOMONTH($B$3,0),OR(Fleet!$F$20="",N(Fleet!$F$20)>=$B$3)),1,0)) | D21: =IF($A21="","",SUMIFS(Trips!$E$5:$E$1004,Trips!$B$5:$B$1004,$A21,Trips!$L$5:$L$1004,$B$3)) | E21: =IF(OR($A21="",N(C21)=0),"",D21/DAY(EOMONTH($B$3,0))) | F21: =IF($A21="","",SUMIFS(Trips!$H$5:$H$1004,Trips!$B$5:$B$1004,$A21,Trips!$L$5:$L$1004,$B$3)+SUMIFS(Trips!$I$5:$I$1004,Trips!$B$5:$B$1004,$A21,Trips!$L$5:$L$1004,$B$3)) | G21: =IF($A21="","",SUMIFS(Trips!$J$5:$J$1004,Trips!$B$5:$B$1004,$A21,Trips!$L$5:$L$1004,$B$3)+SUMIFS(Expenses!$E$5:$E$1004,Expenses!$B$5:$B$1004,$A21,Expenses!$G$5:$G$1004,$B$3)) | H21: =IF($A21="","",Fleet!$O$20*C21) | I21: =IF($A21="","",F21-G21-H21) | J21: =IF($A21="","",(SUMIFS(Trips!$H$5:$H$1004,Trips!$B$5:$B$1004,$A21,Trips!$L$5:$L$1004,EDATE($B$3,-1))+SUMIFS(Trips!$I$5:$I$1004,Trips!$B$5:$B$1004,$A21,Trips!$L$5:$L$1004,EDATE($B$3,-1))-SUMIFS(Trips!$J$5:$J$1004,Trips!$B$5:$B$1004,$A21,Trips!$L$5:$L$1004,EDATE($B$3,-1))-SUMIFS(Expenses!$E$5:$E$1004,Expenses!$B$5:$B$1004,$A21,Expenses!$G$5:$G$1004,EDATE($B$3,-1))-Fleet!$O$20*IF(AND(Fleet!$A$20<>"",N(Fleet!$E$20)<=EOMONTH(EDATE($B$3,-1),0),OR(Fleet!$F$20="",N(Fleet!$F$20)>=EDATE($B$3,-1))),1,0))) | K21: =IF($A21="","",(SUMIFS(Trips!$H$5:$H$1004,Trips!$B$5:$B$1004,$A21,Trips!$L$5:$L$1004,EDATE($B$3,-2))+SUMIFS(Trips!$I$5:$I$1004,Trips!$B$5:$B$1004,$A21,Trips!$L$5:$L$1004,EDATE($B$3,-2))-SUMIFS(Trips!$J$5:$J$1004,Trips!$B$5:$B$1004,$A21,Trips!$L$5:$L$1004,EDATE($B$3,-2))-SUMIFS(Expenses!$E$5:$E$1004,Expenses!$B$5:$B$1004,$A21,Expenses!$G$5:$G$1004,EDATE($B$3,-2))-Fleet!$O$20*IF(AND(Fleet!$A$20<>"",N(Fleet!$E$20)<=EOMONTH(EDATE($B$3,-2),0),OR(Fleet!$F$20="",N(Fleet!$F$20)>=EDATE($B$3,-2))),1,0))) | L21: =IF($A21="","",SUMIFS(Trips!$M$5:$M$1004,Trips!$B$5:$B$1004,$A21,Trips!$L$5:$L$1004,"<="&$B$3)-SUMIFS(Expenses!$E$5:$E$1004,Expenses!$B$5:$B$1004,$A21,Expenses!$G$5:$G$1004,"<="&$B$3)-Fleet!$O$20*IF(N(Fleet!$E$20)=0,0,MAX(0,(YEAR(IF(Fleet!$F$20="",EOMONTH($B$3,0),MIN(Fleet!$F$20,EOMONTH($B$3,0))))-YEAR(Fleet!$E$20))*12+MONTH(IF(Fleet!$F$20="",EOMONTH($B$3,0),MIN(Fleet!$F$20,EOMONTH($B$3,0))))-MONTH(Fleet!$E$20)+1))) | M21: =IF($A21="","",Fleet!$H$20) | N21: =IF(OR($A21="",N(M21)=0),"",L21/M21) | O21: =IF(OR($A21="",N(C21)=0),"",IF(AND(I21<0,J21<0,K21<0),"REVIEW: 3 losing months",IF(I21<Assumptions!$B$9,"Below net target",IF(E21<Assumptions!$B$8,"Low utilization","On track"))))
A22: =IF(Fleet!A21="","",Fleet!A21) | B22: =IF(Fleet!A21="","",Fleet!B21&" "&Fleet!C21) | C22: =IF($A22="","",IF(AND(Fleet!$A$21<>"",N(Fleet!$E$21)<=EOMONTH($B$3,0),OR(Fleet!$F$21="",N(Fleet!$F$21)>=$B$3)),1,0)) | D22: =IF($A22="","",SUMIFS(Trips!$E$5:$E$1004,Trips!$B$5:$B$1004,$A22,Trips!$L$5:$L$1004,$B$3)) | E22: =IF(OR($A22="",N(C22)=0),"",D22/DAY(EOMONTH($B$3,0))) | F22: =IF($A22="","",SUMIFS(Trips!$H$5:$H$1004,Trips!$B$5:$B$1004,$A22,Trips!$L$5:$L$1004,$B$3)+SUMIFS(Trips!$I$5:$I$1004,Trips!$B$5:$B$1004,$A22,Trips!$L$5:$L$1004,$B$3)) | G22: =IF($A22="","",SUMIFS(Trips!$J$5:$J$1004,Trips!$B$5:$B$1004,$A22,Trips!$L$5:$L$1004,$B$3)+SUMIFS(Expenses!$E$5:$E$1004,Expenses!$B$5:$B$1004,$A22,Expenses!$G$5:$G$1004,$B$3)) | H22: =IF($A22="","",Fleet!$O$21*C22) | I22: =IF($A22="","",F22-G22-H22) | J22: =IF($A22="","",(SUMIFS(Trips!$H$5:$H$1004,Trips!$B$5:$B$1004,$A22,Trips!$L$5:$L$1004,EDATE($B$3,-1))+SUMIFS(Trips!$I$5:$I$1004,Trips!$B$5:$B$1004,$A22,Trips!$L$5:$L$1004,EDATE($B$3,-1))-SUMIFS(Trips!$J$5:$J$1004,Trips!$B$5:$B$1004,$A22,Trips!$L$5:$L$1004,EDATE($B$3,-1))-SUMIFS(Expenses!$E$5:$E$1004,Expenses!$B$5:$B$1004,$A22,Expenses!$G$5:$G$1004,EDATE($B$3,-1))-Fleet!$O$21*IF(AND(Fleet!$A$21<>"",N(Fleet!$E$21)<=EOMONTH(EDATE($B$3,-1),0),OR(Fleet!$F$21="",N(Fleet!$F$21)>=EDATE($B$3,-1))),1,0))) | K22: =IF($A22="","",(SUMIFS(Trips!$H$5:$H$1004,Trips!$B$5:$B$1004,$A22,Trips!$L$5:$L$1004,EDATE($B$3,-2))+SUMIFS(Trips!$I$5:$I$1004,Trips!$B$5:$B$1004,$A22,Trips!$L$5:$L$1004,EDATE($B$3,-2))-SUMIFS(Trips!$J$5:$J$1004,Trips!$B$5:$B$1004,$A22,Trips!$L$5:$L$1004,EDATE($B$3,-2))-SUMIFS(Expenses!$E$5:$E$1004,Expenses!$B$5:$B$1004,$A22,Expenses!$G$5:$G$1004,EDATE($B$3,-2))-Fleet!$O$21*IF(AND(Fleet!$A$21<>"",N(Fleet!$E$21)<=EOMONTH(EDATE($B$3,-2),0),OR(Fleet!$F$21="",N(Fleet!$F$21)>=EDATE($B$3,-2))),1,0))) | L22: =IF($A22="","",SUMIFS(Trips!$M$5:$M$1004,Trips!$B$5:$B$1004,$A22,Trips!$L$5:$L$1004,"<="&$B$3)-SUMIFS(Expenses!$E$5:$E$1004,Expenses!$B$5:$B$1004,$A22,Expenses!$G$5:$G$1004,"<="&$B$3)-Fleet!$O$21*IF(N(Fleet!$E$21)=0,0,MAX(0,(YEAR(IF(Fleet!$F$21="",EOMONTH($B$3,0),MIN(Fleet!$F$21,EOMONTH($B$3,0))))-YEAR(Fleet!$E$21))*12+MONTH(IF(Fleet!$F$21="",EOMONTH($B$3,0),MIN(Fleet!$F$21,EOMONTH($B$3,0))))-MONTH(Fleet!$E$21)+1))) | M22: =IF($A22="","",Fleet!$H$21) | N22: =IF(OR($A22="",N(M22)=0),"",L22/M22) | O22: =IF(OR($A22="",N(C22)=0),"",IF(AND(I22<0,J22<0,K22<0),"REVIEW: 3 losing months",IF(I22<Assumptions!$B$9,"Below net target",IF(E22<Assumptions!$B$8,"Low utilization","On track"))))
A23: =IF(Fleet!A22="","",Fleet!A22) | B23: =IF(Fleet!A22="","",Fleet!B22&" "&Fleet!C22) | C23: =IF($A23="","",IF(AND(Fleet!$A$22<>"",N(Fleet!$E$22)<=EOMONTH($B$3,0),OR(Fleet!$F$22="",N(Fleet!$F$22)>=$B$3)),1,0)) | D23: =IF($A23="","",SUMIFS(Trips!$E$5:$E$1004,Trips!$B$5:$B$1004,$A23,Trips!$L$5:$L$1004,$B$3)) | E23: =IF(OR($A23="",N(C23)=0),"",D23/DAY(EOMONTH($B$3,0))) | F23: =IF($A23="","",SUMIFS(Trips!$H$5:$H$1004,Trips!$B$5:$B$1004,$A23,Trips!$L$5:$L$1004,$B$3)+SUMIFS(Trips!$I$5:$I$1004,Trips!$B$5:$B$1004,$A23,Trips!$L$5:$L$1004,$B$3)) | G23: =IF($A23="","",SUMIFS(Trips!$J$5:$J$1004,Trips!$B$5:$B$1004,$A23,Trips!$L$5:$L$1004,$B$3)+SUMIFS(Expenses!$E$5:$E$1004,Expenses!$B$5:$B$1004,$A23,Expenses!$G$5:$G$1004,$B$3)) | H23: =IF($A23="","",Fleet!$O$22*C23) | I23: =IF($A23="","",F23-G23-H23) | J23: =IF($A23="","",(SUMIFS(Trips!$H$5:$H$1004,Trips!$B$5:$B$1004,$A23,Trips!$L$5:$L$1004,EDATE($B$3,-1))+SUMIFS(Trips!$I$5:$I$1004,Trips!$B$5:$B$1004,$A23,Trips!$L$5:$L$1004,EDATE($B$3,-1))-SUMIFS(Trips!$J$5:$J$1004,Trips!$B$5:$B$1004,$A23,Trips!$L$5:$L$1004,EDATE($B$3,-1))-SUMIFS(Expenses!$E$5:$E$1004,Expenses!$B$5:$B$1004,$A23,Expenses!$G$5:$G$1004,EDATE($B$3,-1))-Fleet!$O$22*IF(AND(Fleet!$A$22<>"",N(Fleet!$E$22)<=EOMONTH(EDATE($B$3,-1),0),OR(Fleet!$F$22="",N(Fleet!$F$22)>=EDATE($B$3,-1))),1,0))) | K23: =IF($A23="","",(SUMIFS(Trips!$H$5:$H$1004,Trips!$B$5:$B$1004,$A23,Trips!$L$5:$L$1004,EDATE($B$3,-2))+SUMIFS(Trips!$I$5:$I$1004,Trips!$B$5:$B$1004,$A23,Trips!$L$5:$L$1004,EDATE($B$3,-2))-SUMIFS(Trips!$J$5:$J$1004,Trips!$B$5:$B$1004,$A23,Trips!$L$5:$L$1004,EDATE($B$3,-2))-SUMIFS(Expenses!$E$5:$E$1004,Expenses!$B$5:$B$1004,$A23,Expenses!$G$5:$G$1004,EDATE($B$3,-2))-Fleet!$O$22*IF(AND(Fleet!$A$22<>"",N(Fleet!$E$22)<=EOMONTH(EDATE($B$3,-2),0),OR(Fleet!$F$22="",N(Fleet!$F$22)>=EDATE($B$3,-2))),1,0))) | L23: =IF($A23="","",SUMIFS(Trips!$M$5:$M$1004,Trips!$B$5:$B$1004,$A23,Trips!$L$5:$L$1004,"<="&$B$3)-SUMIFS(Expenses!$E$5:$E$1004,Expenses!$B$5:$B$1004,$A23,Expenses!$G$5:$G$1004,"<="&$B$3)-Fleet!$O$22*IF(N(Fleet!$E$22)=0,0,MAX(0,(YEAR(IF(Fleet!$F$22="",EOMONTH($B$3,0),MIN(Fleet!$F$22,EOMONTH($B$3,0))))-YEAR(Fleet!$E$22))*12+MONTH(IF(Fleet!$F$22="",EOMONTH($B$3,0),MIN(Fleet!$F$22,EOMONTH($B$3,0))))-MONTH(Fleet!$E$22)+1))) | M23: =IF($A23="","",Fleet!$H$22) | N23: =IF(OR($A23="",N(M23)=0),"",L23/M23) | O23: =IF(OR($A23="",N(C23)=0),"",IF(AND(I23<0,J23<0,K23<0),"REVIEW: 3 losing months",IF(I23<Assumptions!$B$9,"Below net target",IF(E23<Assumptions!$B$8,"Low utilization","On track"))))
A24: =IF(Fleet!A23="","",Fleet!A23) | B24: =IF(Fleet!A23="","",Fleet!B23&" "&Fleet!C23) | C24: =IF($A24="","",IF(AND(Fleet!$A$23<>"",N(Fleet!$E$23)<=EOMONTH($B$3,0),OR(Fleet!$F$23="",N(Fleet!$F$23)>=$B$3)),1,0)) | D24: =IF($A24="","",SUMIFS(Trips!$E$5:$E$1004,Trips!$B$5:$B$1004,$A24,Trips!$L$5:$L$1004,$B$3)) | E24: =IF(OR($A24="",N(C24)=0),"",D24/DAY(EOMONTH($B$3,0))) | F24: =IF($A24="","",SUMIFS(Trips!$H$5:$H$1004,Trips!$B$5:$B$1004,$A24,Trips!$L$5:$L$1004,$B$3)+SUMIFS(Trips!$I$5:$I$1004,Trips!$B$5:$B$1004,$A24,Trips!$L$5:$L$1004,$B$3)) | G24: =IF($A24="","",SUMIFS(Trips!$J$5:$J$1004,Trips!$B$5:$B$1004,$A24,Trips!$L$5:$L$1004,$B$3)+SUMIFS(Expenses!$E$5:$E$1004,Expenses!$B$5:$B$1004,$A24,Expenses!$G$5:$G$1004,$B$3)) | H24: =IF($A24="","",Fleet!$O$23*C24) | I24: =IF($A24="","",F24-G24-H24) | J24: =IF($A24="","",(SUMIFS(Trips!$H$5:$H$1004,Trips!$B$5:$B$1004,$A24,Trips!$L$5:$L$1004,EDATE($B$3,-1))+SUMIFS(Trips!$I$5:$I$1004,Trips!$B$5:$B$1004,$A24,Trips!$L$5:$L$1004,EDATE($B$3,-1))-SUMIFS(Trips!$J$5:$J$1004,Trips!$B$5:$B$1004,$A24,Trips!$L$5:$L$1004,EDATE($B$3,-1))-SUMIFS(Expenses!$E$5:$E$1004,Expenses!$B$5:$B$1004,$A24,Expenses!$G$5:$G$1004,EDATE($B$3,-1))-Fleet!$O$23*IF(AND(Fleet!$A$23<>"",N(Fleet!$E$23)<=EOMONTH(EDATE($B$3,-1),0),OR(Fleet!$F$23="",N(Fleet!$F$23)>=EDATE($B$3,-1))),1,0))) | K24: =IF($A24="","",(SUMIFS(Trips!$H$5:$H$1004,Trips!$B$5:$B$1004,$A24,Trips!$L$5:$L$1004,EDATE($B$3,-2))+SUMIFS(Trips!$I$5:$I$1004,Trips!$B$5:$B$1004,$A24,Trips!$L$5:$L$1004,EDATE($B$3,-2))-SUMIFS(Trips!$J$5:$J$1004,Trips!$B$5:$B$1004,$A24,Trips!$L$5:$L$1004,EDATE($B$3,-2))-SUMIFS(Expenses!$E$5:$E$1004,Expenses!$B$5:$B$1004,$A24,Expenses!$G$5:$G$1004,EDATE($B$3,-2))-Fleet!$O$23*IF(AND(Fleet!$A$23<>"",N(Fleet!$E$23)<=EOMONTH(EDATE($B$3,-2),0),OR(Fleet!$F$23="",N(Fleet!$F$23)>=EDATE($B$3,-2))),1,0))) | L24: =IF($A24="","",SUMIFS(Trips!$M$5:$M$1004,Trips!$B$5:$B$1004,$A24,Trips!$L$5:$L$1004,"<="&$B$3)-SUMIFS(Expenses!$E$5:$E$1004,Expenses!$B$5:$B$1004,$A24,Expenses!$G$5:$G$1004,"<="&$B$3)-Fleet!$O$23*IF(N(Fleet!$E$23)=0,0,MAX(0,(YEAR(IF(Fleet!$F$23="",EOMONTH($B$3,0),MIN(Fleet!$F$23,EOMONTH($B$3,0))))-YEAR(Fleet!$E$23))*12+MONTH(IF(Fleet!$F$23="",EOMONTH($B$3,0),MIN(Fleet!$F$23,EOMONTH($B$3,0))))-MONTH(Fleet!$E$23)+1))) | M24: =IF($A24="","",Fleet!$H$23) | N24: =IF(OR($A24="",N(M24)=0),"",L24/M24) | O24: =IF(OR($A24="",N(C24)=0),"",IF(AND(I24<0,J24<0,K24<0),"REVIEW: 3 losing months",IF(I24<Assumptions!$B$9,"Below net target",IF(E24<Assumptions!$B$8,"Low utilization","On track"))))
A25: =IF(Fleet!A24="","",Fleet!A24) | B25: =IF(Fleet!A24="","",Fleet!B24&" "&Fleet!C24) | C25: =IF($A25="","",IF(AND(Fleet!$A$24<>"",N(Fleet!$E$24)<=EOMONTH($B$3,0),OR(Fleet!$F$24="",N(Fleet!$F$24)>=$B$3)),1,0)) | D25: =IF($A25="","",SUMIFS(Trips!$E$5:$E$1004,Trips!$B$5:$B$1004,$A25,Trips!$L$5:$L$1004,$B$3)) | E25: =IF(OR($A25="",N(C25)=0),"",D25/DAY(EOMONTH($B$3,0))) | F25: =IF($A25="","",SUMIFS(Trips!$H$5:$H$1004,Trips!$B$5:$B$1004,$A25,Trips!$L$5:$L$1004,$B$3)+SUMIFS(Trips!$I$5:$I$1004,Trips!$B$5:$B$1004,$A25,Trips!$L$5:$L$1004,$B$3)) | G25: =IF($A25="","",SUMIFS(Trips!$J$5:$J$1004,Trips!$B$5:$B$1004,$A25,Trips!$L$5:$L$1004,$B$3)+SUMIFS(Expenses!$E$5:$E$1004,Expenses!$B$5:$B$1004,$A25,Expenses!$G$5:$G$1004,$B$3)) | H25: =IF($A25="","",Fleet!$O$24*C25) | I25: =IF($A25="","",F25-G25-H25) | J25: =IF($A25="","",(SUMIFS(Trips!$H$5:$H$1004,Trips!$B$5:$B$1004,$A25,Trips!$L$5:$L$1004,EDATE($B$3,-1))+SUMIFS(Trips!$I$5:$I$1004,Trips!$B$5:$B$1004,$A25,Trips!$L$5:$L$1004,EDATE($B$3,-1))-SUMIFS(Trips!$J$5:$J$1004,Trips!$B$5:$B$1004,$A25,Trips!$L$5:$L$1004,EDATE($B$3,-1))-SUMIFS(Expenses!$E$5:$E$1004,Expenses!$B$5:$B$1004,$A25,Expenses!$G$5:$G$1004,EDATE($B$3,-1))-Fleet!$O$24*IF(AND(Fleet!$A$24<>"",N(Fleet!$E$24)<=EOMONTH(EDATE($B$3,-1),0),OR(Fleet!$F$24="",N(Fleet!$F$24)>=EDATE($B$3,-1))),1,0))) | K25: =IF($A25="","",(SUMIFS(Trips!$H$5:$H$1004,Trips!$B$5:$B$1004,$A25,Trips!$L$5:$L$1004,EDATE($B$3,-2))+SUMIFS(Trips!$I$5:$I$1004,Trips!$B$5:$B$1004,$A25,Trips!$L$5:$L$1004,EDATE($B$3,-2))-SUMIFS(Trips!$J$5:$J$1004,Trips!$B$5:$B$1004,$A25,Trips!$L$5:$L$1004,EDATE($B$3,-2))-SUMIFS(Expenses!$E$5:$E$1004,Expenses!$B$5:$B$1004,$A25,Expenses!$G$5:$G$1004,EDATE($B$3,-2))-Fleet!$O$24*IF(AND(Fleet!$A$24<>"",N(Fleet!$E$24)<=EOMONTH(EDATE($B$3,-2),0),OR(Fleet!$F$24="",N(Fleet!$F$24)>=EDATE($B$3,-2))),1,0))) | L25: =IF($A25="","",SUMIFS(Trips!$M$5:$M$1004,Trips!$B$5:$B$1004,$A25,Trips!$L$5:$L$1004,"<="&$B$3)-SUMIFS(Expenses!$E$5:$E$1004,Expenses!$B$5:$B$1004,$A25,Expenses!$G$5:$G$1004,"<="&$B$3)-Fleet!$O$24*IF(N(Fleet!$E$24)=0,0,MAX(0,(YEAR(IF(Fleet!$F$24="",EOMONTH($B$3,0),MIN(Fleet!$F$24,EOMONTH($B$3,0))))-YEAR(Fleet!$E$24))*12+MONTH(IF(Fleet!$F$24="",EOMONTH($B$3,0),MIN(Fleet!$F$24,EOMONTH($B$3,0))))-MONTH(Fleet!$E$24)+1))) | M25: =IF($A25="","",Fleet!$H$24) | N25: =IF(OR($A25="",N(M25)=0),"",L25/M25) | O25: =IF(OR($A25="",N(C25)=0),"",IF(AND(I25<0,J25<0,K25<0),"REVIEW: 3 losing months",IF(I25<Assumptions!$B$9,"Below net target",IF(E25<Assumptions!$B$8,"Low utilization","On track"))))
A26: =IF(Fleet!A25="","",Fleet!A25) | B26: =IF(Fleet!A25="","",Fleet!B25&" "&Fleet!C25) | C26: =IF($A26="","",IF(AND(Fleet!$A$25<>"",N(Fleet!$E$25)<=EOMONTH($B$3,0),OR(Fleet!$F$25="",N(Fleet!$F$25)>=$B$3)),1,0)) | D26: =IF($A26="","",SUMIFS(Trips!$E$5:$E$1004,Trips!$B$5:$B$1004,$A26,Trips!$L$5:$L$1004,$B$3)) | E26: =IF(OR($A26="",N(C26)=0),"",D26/DAY(EOMONTH($B$3,0))) | F26: =IF($A26="","",SUMIFS(Trips!$H$5:$H$1004,Trips!$B$5:$B$1004,$A26,Trips!$L$5:$L$1004,$B$3)+SUMIFS(Trips!$I$5:$I$1004,Trips!$B$5:$B$1004,$A26,Trips!$L$5:$L$1004,$B$3)) | G26: =IF($A26="","",SUMIFS(Trips!$J$5:$J$1004,Trips!$B$5:$B$1004,$A26,Trips!$L$5:$L$1004,$B$3)+SUMIFS(Expenses!$E$5:$E$1004,Expenses!$B$5:$B$1004,$A26,Expenses!$G$5:$G$1004,$B$3)) | H26: =IF($A26="","",Fleet!$O$25*C26) | I26: =IF($A26="","",F26-G26-H26) | J26: =IF($A26="","",(SUMIFS(Trips!$H$5:$H$1004,Trips!$B$5:$B$1004,$A26,Trips!$L$5:$L$1004,EDATE($B$3,-1))+SUMIFS(Trips!$I$5:$I$1004,Trips!$B$5:$B$1004,$A26,Trips!$L$5:$L$1004,EDATE($B$3,-1))-SUMIFS(Trips!$J$5:$J$1004,Trips!$B$5:$B$1004,$A26,Trips!$L$5:$L$1004,EDATE($B$3,-1))-SUMIFS(Expenses!$E$5:$E$1004,Expenses!$B$5:$B$1004,$A26,Expenses!$G$5:$G$1004,EDATE($B$3,-1))-Fleet!$O$25*IF(AND(Fleet!$A$25<>"",N(Fleet!$E$25)<=EOMONTH(EDATE($B$3,-1),0),OR(Fleet!$F$25="",N(Fleet!$F$25)>=EDATE($B$3,-1))),1,0))) | K26: =IF($A26="","",(SUMIFS(Trips!$H$5:$H$1004,Trips!$B$5:$B$1004,$A26,Trips!$L$5:$L$1004,EDATE($B$3,-2))+SUMIFS(Trips!$I$5:$I$1004,Trips!$B$5:$B$1004,$A26,Trips!$L$5:$L$1004,EDATE($B$3,-2))-SUMIFS(Trips!$J$5:$J$1004,Trips!$B$5:$B$1004,$A26,Trips!$L$5:$L$1004,EDATE($B$3,-2))-SUMIFS(Expenses!$E$5:$E$1004,Expenses!$B$5:$B$1004,$A26,Expenses!$G$5:$G$1004,EDATE($B$3,-2))-Fleet!$O$25*IF(AND(Fleet!$A$25<>"",N(Fleet!$E$25)<=EOMONTH(EDATE($B$3,-2),0),OR(Fleet!$F$25="",N(Fleet!$F$25)>=EDATE($B$3,-2))),1,0))) | L26: =IF($A26="","",SUMIFS(Trips!$M$5:$M$1004,Trips!$B$5:$B$1004,$A26,Trips!$L$5:$L$1004,"<="&$B$3)-SUMIFS(Expenses!$E$5:$E$1004,Expenses!$B$5:$B$1004,$A26,Expenses!$G$5:$G$1004,"<="&$B$3)-Fleet!$O$25*IF(N(Fleet!$E$25)=0,0,MAX(0,(YEAR(IF(Fleet!$F$25="",EOMONTH($B$3,0),MIN(Fleet!$F$25,EOMONTH($B$3,0))))-YEAR(Fleet!$E$25))*12+MONTH(IF(Fleet!$F$25="",EOMONTH($B$3,0),MIN(Fleet!$F$25,EOMONTH($B$3,0))))-MONTH(Fleet!$E$25)+1))) | M26: =IF($A26="","",Fleet!$H$25) | N26: =IF(OR($A26="",N(M26)=0),"",L26/M26) | O26: =IF(OR($A26="",N(C26)=0),"",IF(AND(I26<0,J26<0,K26<0),"REVIEW: 3 losing months",IF(I26<Assumptions!$B$9,"Below net target",IF(E26<Assumptions!$B$8,"Low utilization","On track"))))
A27: =IF(Fleet!A26="","",Fleet!A26) | B27: =IF(Fleet!A26="","",Fleet!B26&" "&Fleet!C26) | C27: =IF($A27="","",IF(AND(Fleet!$A$26<>"",N(Fleet!$E$26)<=EOMONTH($B$3,0),OR(Fleet!$F$26="",N(Fleet!$F$26)>=$B$3)),1,0)) | D27: =IF($A27="","",SUMIFS(Trips!$E$5:$E$1004,Trips!$B$5:$B$1004,$A27,Trips!$L$5:$L$1004,$B$3)) | E27: =IF(OR($A27="",N(C27)=0),"",D27/DAY(EOMONTH($B$3,0))) | F27: =IF($A27="","",SUMIFS(Trips!$H$5:$H$1004,Trips!$B$5:$B$1004,$A27,Trips!$L$5:$L$1004,$B$3)+SUMIFS(Trips!$I$5:$I$1004,Trips!$B$5:$B$1004,$A27,Trips!$L$5:$L$1004,$B$3)) | G27: =IF($A27="","",SUMIFS(Trips!$J$5:$J$1004,Trips!$B$5:$B$1004,$A27,Trips!$L$5:$L$1004,$B$3)+SUMIFS(Expenses!$E$5:$E$1004,Expenses!$B$5:$B$1004,$A27,Expenses!$G$5:$G$1004,$B$3)) | H27: =IF($A27="","",Fleet!$O$26*C27) | I27: =IF($A27="","",F27-G27-H27) | J27: =IF($A27="","",(SUMIFS(Trips!$H$5:$H$1004,Trips!$B$5:$B$1004,$A27,Trips!$L$5:$L$1004,EDATE($B$3,-1))+SUMIFS(Trips!$I$5:$I$1004,Trips!$B$5:$B$1004,$A27,Trips!$L$5:$L$1004,EDATE($B$3,-1))-SUMIFS(Trips!$J$5:$J$1004,Trips!$B$5:$B$1004,$A27,Trips!$L$5:$L$1004,EDATE($B$3,-1))-SUMIFS(Expenses!$E$5:$E$1004,Expenses!$B$5:$B$1004,$A27,Expenses!$G$5:$G$1004,EDATE($B$3,-1))-Fleet!$O$26*IF(AND(Fleet!$A$26<>"",N(Fleet!$E$26)<=EOMONTH(EDATE($B$3,-1),0),OR(Fleet!$F$26="",N(Fleet!$F$26)>=EDATE($B$3,-1))),1,0))) | K27: =IF($A27="","",(SUMIFS(Trips!$H$5:$H$1004,Trips!$B$5:$B$1004,$A27,Trips!$L$5:$L$1004,EDATE($B$3,-2))+SUMIFS(Trips!$I$5:$I$1004,Trips!$B$5:$B$1004,$A27,Trips!$L$5:$L$1004,EDATE($B$3,-2))-SUMIFS(Trips!$J$5:$J$1004,Trips!$B$5:$B$1004,$A27,Trips!$L$5:$L$1004,EDATE($B$3,-2))-SUMIFS(Expenses!$E$5:$E$1004,Expenses!$B$5:$B$1004,$A27,Expenses!$G$5:$G$1004,EDATE($B$3,-2))-Fleet!$O$26*IF(AND(Fleet!$A$26<>"",N(Fleet!$E$26)<=EOMONTH(EDATE($B$3,-2),0),OR(Fleet!$F$26="",N(Fleet!$F$26)>=EDATE($B$3,-2))),1,0))) | L27: =IF($A27="","",SUMIFS(Trips!$M$5:$M$1004,Trips!$B$5:$B$1004,$A27,Trips!$L$5:$L$1004,"<="&$B$3)-SUMIFS(Expenses!$E$5:$E$1004,Expenses!$B$5:$B$1004,$A27,Expenses!$G$5:$G$1004,"<="&$B$3)-Fleet!$O$26*IF(N(Fleet!$E$26)=0,0,MAX(0,(YEAR(IF(Fleet!$F$26="",EOMONTH($B$3,0),MIN(Fleet!$F$26,EOMONTH($B$3,0))))-YEAR(Fleet!$E$26))*12+MONTH(IF(Fleet!$F$26="",EOMONTH($B$3,0),MIN(Fleet!$F$26,EOMONTH($B$3,0))))-MONTH(Fleet!$E$26)+1))) | M27: =IF($A27="","",Fleet!$H$26) | N27: =IF(OR($A27="",N(M27)=0),"",L27/M27) | O27: =IF(OR($A27="",N(C27)=0),"",IF(AND(I27<0,J27<0,K27<0),"REVIEW: 3 losing months",IF(I27<Assumptions!$B$9,"Below net target",IF(E27<Assumptions!$B$8,"Low utilization","On track"))))
A28: =IF(Fleet!A27="","",Fleet!A27) | B28: =IF(Fleet!A27="","",Fleet!B27&" "&Fleet!C27) | C28: =IF($A28="","",IF(AND(Fleet!$A$27<>"",N(Fleet!$E$27)<=EOMONTH($B$3,0),OR(Fleet!$F$27="",N(Fleet!$F$27)>=$B$3)),1,0)) | D28: =IF($A28="","",SUMIFS(Trips!$E$5:$E$1004,Trips!$B$5:$B$1004,$A28,Trips!$L$5:$L$1004,$B$3)) | E28: =IF(OR($A28="",N(C28)=0),"",D28/DAY(EOMONTH($B$3,0))) | F28: =IF($A28="","",SUMIFS(Trips!$H$5:$H$1004,Trips!$B$5:$B$1004,$A28,Trips!$L$5:$L$1004,$B$3)+SUMIFS(Trips!$I$5:$I$1004,Trips!$B$5:$B$1004,$A28,Trips!$L$5:$L$1004,$B$3)) | G28: =IF($A28="","",SUMIFS(Trips!$J$5:$J$1004,Trips!$B$5:$B$1004,$A28,Trips!$L$5:$L$1004,$B$3)+SUMIFS(Expenses!$E$5:$E$1004,Expenses!$B$5:$B$1004,$A28,Expenses!$G$5:$G$1004,$B$3)) | H28: =IF($A28="","",Fleet!$O$27*C28) | I28: =IF($A28="","",F28-G28-H28) | J28: =IF($A28="","",(SUMIFS(Trips!$H$5:$H$1004,Trips!$B$5:$B$1004,$A28,Trips!$L$5:$L$1004,EDATE($B$3,-1))+SUMIFS(Trips!$I$5:$I$1004,Trips!$B$5:$B$1004,$A28,Trips!$L$5:$L$1004,EDATE($B$3,-1))-SUMIFS(Trips!$J$5:$J$1004,Trips!$B$5:$B$1004,$A28,Trips!$L$5:$L$1004,EDATE($B$3,-1))-SUMIFS(Expenses!$E$5:$E$1004,Expenses!$B$5:$B$1004,$A28,Expenses!$G$5:$G$1004,EDATE($B$3,-1))-Fleet!$O$27*IF(AND(Fleet!$A$27<>"",N(Fleet!$E$27)<=EOMONTH(EDATE($B$3,-1),0),OR(Fleet!$F$27="",N(Fleet!$F$27)>=EDATE($B$3,-1))),1,0))) | K28: =IF($A28="","",(SUMIFS(Trips!$H$5:$H$1004,Trips!$B$5:$B$1004,$A28,Trips!$L$5:$L$1004,EDATE($B$3,-2))+SUMIFS(Trips!$I$5:$I$1004,Trips!$B$5:$B$1004,$A28,Trips!$L$5:$L$1004,EDATE($B$3,-2))-SUMIFS(Trips!$J$5:$J$1004,Trips!$B$5:$B$1004,$A28,Trips!$L$5:$L$1004,EDATE($B$3,-2))-SUMIFS(Expenses!$E$5:$E$1004,Expenses!$B$5:$B$1004,$A28,Expenses!$G$5:$G$1004,EDATE($B$3,-2))-Fleet!$O$27*IF(AND(Fleet!$A$27<>"",N(Fleet!$E$27)<=EOMONTH(EDATE($B$3,-2),0),OR(Fleet!$F$27="",N(Fleet!$F$27)>=EDATE($B$3,-2))),1,0))) | L28: =IF($A28="","",SUMIFS(Trips!$M$5:$M$1004,Trips!$B$5:$B$1004,$A28,Trips!$L$5:$L$1004,"<="&$B$3)-SUMIFS(Expenses!$E$5:$E$1004,Expenses!$B$5:$B$1004,$A28,Expenses!$G$5:$G$1004,"<="&$B$3)-Fleet!$O$27*IF(N(Fleet!$E$27)=0,0,MAX(0,(YEAR(IF(Fleet!$F$27="",EOMONTH($B$3,0),MIN(Fleet!$F$27,EOMONTH($B$3,0))))-YEAR(Fleet!$E$27))*12+MONTH(IF(Fleet!$F$27="",EOMONTH($B$3,0),MIN(Fleet!$F$27,EOMONTH($B$3,0))))-MONTH(Fleet!$E$27)+1))) | M28: =IF($A28="","",Fleet!$H$27) | N28: =IF(OR($A28="",N(M28)=0),"",L28/M28) | O28: =IF(OR($A28="",N(C28)=0),"",IF(AND(I28<0,J28<0,K28<0),"REVIEW: 3 losing months",IF(I28<Assumptions!$B$9,"Below net target",IF(E28<Assumptions!$B$8,"Low utilization","On track"))))
A29: =IF(Fleet!A28="","",Fleet!A28) | B29: =IF(Fleet!A28="","",Fleet!B28&" "&Fleet!C28) | C29: =IF($A29="","",IF(AND(Fleet!$A$28<>"",N(Fleet!$E$28)<=EOMONTH($B$3,0),OR(Fleet!$F$28="",N(Fleet!$F$28)>=$B$3)),1,0)) | D29: =IF($A29="","",SUMIFS(Trips!$E$5:$E$1004,Trips!$B$5:$B$1004,$A29,Trips!$L$5:$L$1004,$B$3)) | E29: =IF(OR($A29="",N(C29)=0),"",D29/DAY(EOMONTH($B$3,0))) | F29: =IF($A29="","",SUMIFS(Trips!$H$5:$H$1004,Trips!$B$5:$B$1004,$A29,Trips!$L$5:$L$1004,$B$3)+SUMIFS(Trips!$I$5:$I$1004,Trips!$B$5:$B$1004,$A29,Trips!$L$5:$L$1004,$B$3)) | G29: =IF($A29="","",SUMIFS(Trips!$J$5:$J$1004,Trips!$B$5:$B$1004,$A29,Trips!$L$5:$L$1004,$B$3)+SUMIFS(Expenses!$E$5:$E$1004,Expenses!$B$5:$B$1004,$A29,Expenses!$G$5:$G$1004,$B$3)) | H29: =IF($A29="","",Fleet!$O$28*C29) | I29: =IF($A29="","",F29-G29-H29) | J29: =IF($A29="","",(SUMIFS(Trips!$H$5:$H$1004,Trips!$B$5:$B$1004,$A29,Trips!$L$5:$L$1004,EDATE($B$3,-1))+SUMIFS(Trips!$I$5:$I$1004,Trips!$B$5:$B$1004,$A29,Trips!$L$5:$L$1004,EDATE($B$3,-1))-SUMIFS(Trips!$J$5:$J$1004,Trips!$B$5:$B$1004,$A29,Trips!$L$5:$L$1004,EDATE($B$3,-1))-SUMIFS(Expenses!$E$5:$E$1004,Expenses!$B$5:$B$1004,$A29,Expenses!$G$5:$G$1004,EDATE($B$3,-1))-Fleet!$O$28*IF(AND(Fleet!$A$28<>"",N(Fleet!$E$28)<=EOMONTH(EDATE($B$3,-1),0),OR(Fleet!$F$28="",N(Fleet!$F$28)>=EDATE($B$3,-1))),1,0))) | K29: =IF($A29="","",(SUMIFS(Trips!$H$5:$H$1004,Trips!$B$5:$B$1004,$A29,Trips!$L$5:$L$1004,EDATE($B$3,-2))+SUMIFS(Trips!$I$5:$I$1004,Trips!$B$5:$B$1004,$A29,Trips!$L$5:$L$1004,EDATE($B$3,-2))-SUMIFS(Trips!$J$5:$J$1004,Trips!$B$5:$B$1004,$A29,Trips!$L$5:$L$1004,EDATE($B$3,-2))-SUMIFS(Expenses!$E$5:$E$1004,Expenses!$B$5:$B$1004,$A29,Expenses!$G$5:$G$1004,EDATE($B$3,-2))-Fleet!$O$28*IF(AND(Fleet!$A$28<>"",N(Fleet!$E$28)<=EOMONTH(EDATE($B$3,-2),0),OR(Fleet!$F$28="",N(Fleet!$F$28)>=EDATE($B$3,-2))),1,0))) | L29: =IF($A29="","",SUMIFS(Trips!$M$5:$M$1004,Trips!$B$5:$B$1004,$A29,Trips!$L$5:$L$1004,"<="&$B$3)-SUMIFS(Expenses!$E$5:$E$1004,Expenses!$B$5:$B$1004,$A29,Expenses!$G$5:$G$1004,"<="&$B$3)-Fleet!$O$28*IF(N(Fleet!$E$28)=0,0,MAX(0,(YEAR(IF(Fleet!$F$28="",EOMONTH($B$3,0),MIN(Fleet!$F$28,EOMONTH($B$3,0))))-YEAR(Fleet!$E$28))*12+MONTH(IF(Fleet!$F$28="",EOMONTH($B$3,0),MIN(Fleet!$F$28,EOMONTH($B$3,0))))-MONTH(Fleet!$E$28)+1))) | M29: =IF($A29="","",Fleet!$H$28) | N29: =IF(OR($A29="",N(M29)=0),"",L29/M29) | O29: =IF(OR($A29="",N(C29)=0),"",IF(AND(I29<0,J29<0,K29<0),"REVIEW: 3 losing months",IF(I29<Assumptions!$B$9,"Below net target",IF(E29<Assumptions!$B$8,"Low utilization","On track"))))
A30: =IF(Fleet!A29="","",Fleet!A29) | B30: =IF(Fleet!A29="","",Fleet!B29&" "&Fleet!C29) | C30: =IF($A30="","",IF(AND(Fleet!$A$29<>"",N(Fleet!$E$29)<=EOMONTH($B$3,0),OR(Fleet!$F$29="",N(Fleet!$F$29)>=$B$3)),1,0)) | D30: =IF($A30="","",SUMIFS(Trips!$E$5:$E$1004,Trips!$B$5:$B$1004,$A30,Trips!$L$5:$L$1004,$B$3)) | E30: =IF(OR($A30="",N(C30)=0),"",D30/DAY(EOMONTH($B$3,0))) | F30: =IF($A30="","",SUMIFS(Trips!$H$5:$H$1004,Trips!$B$5:$B$1004,$A30,Trips!$L$5:$L$1004,$B$3)+SUMIFS(Trips!$I$5:$I$1004,Trips!$B$5:$B$1004,$A30,Trips!$L$5:$L$1004,$B$3)) | G30: =IF($A30="","",SUMIFS(Trips!$J$5:$J$1004,Trips!$B$5:$B$1004,$A30,Trips!$L$5:$L$1004,$B$3)+SUMIFS(Expenses!$E$5:$E$1004,Expenses!$B$5:$B$1004,$A30,Expenses!$G$5:$G$1004,$B$3)) | H30: =IF($A30="","",Fleet!$O$29*C30) | I30: =IF($A30="","",F30-G30-H30) | J30: =IF($A30="","",(SUMIFS(Trips!$H$5:$H$1004,Trips!$B$5:$B$1004,$A30,Trips!$L$5:$L$1004,EDATE($B$3,-1))+SUMIFS(Trips!$I$5:$I$1004,Trips!$B$5:$B$1004,$A30,Trips!$L$5:$L$1004,EDATE($B$3,-1))-SUMIFS(Trips!$J$5:$J$1004,Trips!$B$5:$B$1004,$A30,Trips!$L$5:$L$1004,EDATE($B$3,-1))-SUMIFS(Expenses!$E$5:$E$1004,Expenses!$B$5:$B$1004,$A30,Expenses!$G$5:$G$1004,EDATE($B$3,-1))-Fleet!$O$29*IF(AND(Fleet!$A$29<>"",N(Fleet!$E$29)<=EOMONTH(EDATE($B$3,-1),0),OR(Fleet!$F$29="",N(Fleet!$F$29)>=EDATE($B$3,-1))),1,0))) | K30: =IF($A30="","",(SUMIFS(Trips!$H$5:$H$1004,Trips!$B$5:$B$1004,$A30,Trips!$L$5:$L$1004,EDATE($B$3,-2))+SUMIFS(Trips!$I$5:$I$1004,Trips!$B$5:$B$1004,$A30,Trips!$L$5:$L$1004,EDATE($B$3,-2))-SUMIFS(Trips!$J$5:$J$1004,Trips!$B$5:$B$1004,$A30,Trips!$L$5:$L$1004,EDATE($B$3,-2))-SUMIFS(Expenses!$E$5:$E$1004,Expenses!$B$5:$B$1004,$A30,Expenses!$G$5:$G$1004,EDATE($B$3,-2))-Fleet!$O$29*IF(AND(Fleet!$A$29<>"",N(Fleet!$E$29)<=EOMONTH(EDATE($B$3,-2),0),OR(Fleet!$F$29="",N(Fleet!$F$29)>=EDATE($B$3,-2))),1,0))) | L30: =IF($A30="","",SUMIFS(Trips!$M$5:$M$1004,Trips!$B$5:$B$1004,$A30,Trips!$L$5:$L$1004,"<="&$B$3)-SUMIFS(Expenses!$E$5:$E$1004,Expenses!$B$5:$B$1004,$A30,Expenses!$G$5:$G$1004,"<="&$B$3)-Fleet!$O$29*IF(N(Fleet!$E$29)=0,0,MAX(0,(YEAR(IF(Fleet!$F$29="",EOMONTH($B$3,0),MIN(Fleet!$F$29,EOMONTH($B$3,0))))-YEAR(Fleet!$E$29))*12+MONTH(IF(Fleet!$F$29="",EOMONTH($B$3,0),MIN(Fleet!$F$29,EOMONTH($B$3,0))))-MONTH(Fleet!$E$29)+1))) | M30: =IF($A30="","",Fleet!$H$29) | N30: =IF(OR($A30="",N(M30)=0),"",L30/M30) | O30: =IF(OR($A30="",N(C30)=0),"",IF(AND(I30<0,J30<0,K30<0),"REVIEW: 3 losing months",IF(I30<Assumptions!$B$9,"Below net target",IF(E30<Assumptions!$B$8,"Low utilization","On track"))))
A31: =IF(Fleet!A30="","",Fleet!A30) | B31: =IF(Fleet!A30="","",Fleet!B30&" "&Fleet!C30) | C31: =IF($A31="","",IF(AND(Fleet!$A$30<>"",N(Fleet!$E$30)<=EOMONTH($B$3,0),OR(Fleet!$F$30="",N(Fleet!$F$30)>=$B$3)),1,0)) | D31: =IF($A31="","",SUMIFS(Trips!$E$5:$E$1004,Trips!$B$5:$B$1004,$A31,Trips!$L$5:$L$1004,$B$3)) | E31: =IF(OR($A31="",N(C31)=0),"",D31/DAY(EOMONTH($B$3,0))) | F31: =IF($A31="","",SUMIFS(Trips!$H$5:$H$1004,Trips!$B$5:$B$1004,$A31,Trips!$L$5:$L$1004,$B$3)+SUMIFS(Trips!$I$5:$I$1004,Trips!$B$5:$B$1004,$A31,Trips!$L$5:$L$1004,$B$3)) | G31: =IF($A31="","",SUMIFS(Trips!$J$5:$J$1004,Trips!$B$5:$B$1004,$A31,Trips!$L$5:$L$1004,$B$3)+SUMIFS(Expenses!$E$5:$E$1004,Expenses!$B$5:$B$1004,$A31,Expenses!$G$5:$G$1004,$B$3)) | H31: =IF($A31="","",Fleet!$O$30*C31) | I31: =IF($A31="","",F31-G31-H31) | J31: =IF($A31="","",(SUMIFS(Trips!$H$5:$H$1004,Trips!$B$5:$B$1004,$A31,Trips!$L$5:$L$1004,EDATE($B$3,-1))+SUMIFS(Trips!$I$5:$I$1004,Trips!$B$5:$B$1004,$A31,Trips!$L$5:$L$1004,EDATE($B$3,-1))-SUMIFS(Trips!$J$5:$J$1004,Trips!$B$5:$B$1004,$A31,Trips!$L$5:$L$1004,EDATE($B$3,-1))-SUMIFS(Expenses!$E$5:$E$1004,Expenses!$B$5:$B$1004,$A31,Expenses!$G$5:$G$1004,EDATE($B$3,-1))-Fleet!$O$30*IF(AND(Fleet!$A$30<>"",N(Fleet!$E$30)<=EOMONTH(EDATE($B$3,-1),0),OR(Fleet!$F$30="",N(Fleet!$F$30)>=EDATE($B$3,-1))),1,0))) | K31: =IF($A31="","",(SUMIFS(Trips!$H$5:$H$1004,Trips!$B$5:$B$1004,$A31,Trips!$L$5:$L$1004,EDATE($B$3,-2))+SUMIFS(Trips!$I$5:$I$1004,Trips!$B$5:$B$1004,$A31,Trips!$L$5:$L$1004,EDATE($B$3,-2))-SUMIFS(Trips!$J$5:$J$1004,Trips!$B$5:$B$1004,$A31,Trips!$L$5:$L$1004,EDATE($B$3,-2))-SUMIFS(Expenses!$E$5:$E$1004,Expenses!$B$5:$B$1004,$A31,Expenses!$G$5:$G$1004,EDATE($B$3,-2))-Fleet!$O$30*IF(AND(Fleet!$A$30<>"",N(Fleet!$E$30)<=EOMONTH(EDATE($B$3,-2),0),OR(Fleet!$F$30="",N(Fleet!$F$30)>=EDATE($B$3,-2))),1,0))) | L31: =IF($A31="","",SUMIFS(Trips!$M$5:$M$1004,Trips!$B$5:$B$1004,$A31,Trips!$L$5:$L$1004,"<="&$B$3)-SUMIFS(Expenses!$E$5:$E$1004,Expenses!$B$5:$B$1004,$A31,Expenses!$G$5:$G$1004,"<="&$B$3)-Fleet!$O$30*IF(N(Fleet!$E$30)=0,0,MAX(0,(YEAR(IF(Fleet!$F$30="",EOMONTH($B$3,0),MIN(Fleet!$F$30,EOMONTH($B$3,0))))-YEAR(Fleet!$E$30))*12+MONTH(IF(Fleet!$F$30="",EOMONTH($B$3,0),MIN(Fleet!$F$30,EOMONTH($B$3,0))))-MONTH(Fleet!$E$30)+1))) | M31: =IF($A31="","",Fleet!$H$30) | N31: =IF(OR($A31="",N(M31)=0),"",L31/M31) | O31: =IF(OR($A31="",N(C31)=0),"",IF(AND(I31<0,J31<0,K31<0),"REVIEW: 3 losing months",IF(I31<Assumptions!$B$9,"Below net target",IF(E31<Assumptions!$B$8,"Low utilization","On track"))))
A32: =IF(Fleet!A31="","",Fleet!A31) | B32: =IF(Fleet!A31="","",Fleet!B31&" "&Fleet!C31) | C32: =IF($A32="","",IF(AND(Fleet!$A$31<>"",N(Fleet!$E$31)<=EOMONTH($B$3,0),OR(Fleet!$F$31="",N(Fleet!$F$31)>=$B$3)),1,0)) | D32: =IF($A32="","",SUMIFS(Trips!$E$5:$E$1004,Trips!$B$5:$B$1004,$A32,Trips!$L$5:$L$1004,$B$3)) | E32: =IF(OR($A32="",N(C32)=0),"",D32/DAY(EOMONTH($B$3,0))) | F32: =IF($A32="","",SUMIFS(Trips!$H$5:$H$1004,Trips!$B$5:$B$1004,$A32,Trips!$L$5:$L$1004,$B$3)+SUMIFS(Trips!$I$5:$I$1004,Trips!$B$5:$B$1004,$A32,Trips!$L$5:$L$1004,$B$3)) | G32: =IF($A32="","",SUMIFS(Trips!$J$5:$J$1004,Trips!$B$5:$B$1004,$A32,Trips!$L$5:$L$1004,$B$3)+SUMIFS(Expenses!$E$5:$E$1004,Expenses!$B$5:$B$1004,$A32,Expenses!$G$5:$G$1004,$B$3)) | H32: =IF($A32="","",Fleet!$O$31*C32) | I32: =IF($A32="","",F32-G32-H32) | J32: =IF($A32="","",(SUMIFS(Trips!$H$5:$H$1004,Trips!$B$5:$B$1004,$A32,Trips!$L$5:$L$1004,EDATE($B$3,-1))+SUMIFS(Trips!$I$5:$I$1004,Trips!$B$5:$B$1004,$A32,Trips!$L$5:$L$1004,EDATE($B$3,-1))-SUMIFS(Trips!$J$5:$J$1004,Trips!$B$5:$B$1004,$A32,Trips!$L$5:$L$1004,EDATE($B$3,-1))-SUMIFS(Expenses!$E$5:$E$1004,Expenses!$B$5:$B$1004,$A32,Expenses!$G$5:$G$1004,EDATE($B$3,-1))-Fleet!$O$31*IF(AND(Fleet!$A$31<>"",N(Fleet!$E$31)<=EOMONTH(EDATE($B$3,-1),0),OR(Fleet!$F$31="",N(Fleet!$F$31)>=EDATE($B$3,-1))),1,0))) | K32: =IF($A32="","",(SUMIFS(Trips!$H$5:$H$1004,Trips!$B$5:$B$1004,$A32,Trips!$L$5:$L$1004,EDATE($B$3,-2))+SUMIFS(Trips!$I$5:$I$1004,Trips!$B$5:$B$1004,$A32,Trips!$L$5:$L$1004,EDATE($B$3,-2))-SUMIFS(Trips!$J$5:$J$1004,Trips!$B$5:$B$1004,$A32,Trips!$L$5:$L$1004,EDATE($B$3,-2))-SUMIFS(Expenses!$E$5:$E$1004,Expenses!$B$5:$B$1004,$A32,Expenses!$G$5:$G$1004,EDATE($B$3,-2))-Fleet!$O$31*IF(AND(Fleet!$A$31<>"",N(Fleet!$E$31)<=EOMONTH(EDATE($B$3,-2),0),OR(Fleet!$F$31="",N(Fleet!$F$31)>=EDATE($B$3,-2))),1,0))) | L32: =IF($A32="","",SUMIFS(Trips!$M$5:$M$1004,Trips!$B$5:$B$1004,$A32,Trips!$L$5:$L$1004,"<="&$B$3)-SUMIFS(Expenses!$E$5:$E$1004,Expenses!$B$5:$B$1004,$A32,Expenses!$G$5:$G$1004,"<="&$B$3)-Fleet!$O$31*IF(N(Fleet!$E$31)=0,0,MAX(0,(YEAR(IF(Fleet!$F$31="",EOMONTH($B$3,0),MIN(Fleet!$F$31,EOMONTH($B$3,0))))-YEAR(Fleet!$E$31))*12+MONTH(IF(Fleet!$F$31="",EOMONTH($B$3,0),MIN(Fleet!$F$31,EOMONTH($B$3,0))))-MONTH(Fleet!$E$31)+1))) | M32: =IF($A32="","",Fleet!$H$31) | N32: =IF(OR($A32="",N(M32)=0),"",L32/M32) | O32: =IF(OR($A32="",N(C32)=0),"",IF(AND(I32<0,J32<0,K32<0),"REVIEW: 3 losing months",IF(I32<Assumptions!$B$9,"Below net target",IF(E32<Assumptions!$B$8,"Low utilization","On track"))))
A33: =IF(Fleet!A32="","",Fleet!A32) | B33: =IF(Fleet!A32="","",Fleet!B32&" "&Fleet!C32) | C33: =IF($A33="","",IF(AND(Fleet!$A$32<>"",N(Fleet!$E$32)<=EOMONTH($B$3,0),OR(Fleet!$F$32="",N(Fleet!$F$32)>=$B$3)),1,0)) | D33: =IF($A33="","",SUMIFS(Trips!$E$5:$E$1004,Trips!$B$5:$B$1004,$A33,Trips!$L$5:$L$1004,$B$3)) | E33: =IF(OR($A33="",N(C33)=0),"",D33/DAY(EOMONTH($B$3,0))) | F33: =IF($A33="","",SUMIFS(Trips!$H$5:$H$1004,Trips!$B$5:$B$1004,$A33,Trips!$L$5:$L$1004,$B$3)+SUMIFS(Trips!$I$5:$I$1004,Trips!$B$5:$B$1004,$A33,Trips!$L$5:$L$1004,$B$3)) | G33: =IF($A33="","",SUMIFS(Trips!$J$5:$J$1004,Trips!$B$5:$B$1004,$A33,Trips!$L$5:$L$1004,$B$3)+SUMIFS(Expenses!$E$5:$E$1004,Expenses!$B$5:$B$1004,$A33,Expenses!$G$5:$G$1004,$B$3)) | H33: =IF($A33="","",Fleet!$O$32*C33) | I33: =IF($A33="","",F33-G33-H33) | J33: =IF($A33="","",(SUMIFS(Trips!$H$5:$H$1004,Trips!$B$5:$B$1004,$A33,Trips!$L$5:$L$1004,EDATE($B$3,-1))+SUMIFS(Trips!$I$5:$I$1004,Trips!$B$5:$B$1004,$A33,Trips!$L$5:$L$1004,EDATE($B$3,-1))-SUMIFS(Trips!$J$5:$J$1004,Trips!$B$5:$B$1004,$A33,Trips!$L$5:$L$1004,EDATE($B$3,-1))-SUMIFS(Expenses!$E$5:$E$1004,Expenses!$B$5:$B$1004,$A33,Expenses!$G$5:$G$1004,EDATE($B$3,-1))-Fleet!$O$32*IF(AND(Fleet!$A$32<>"",N(Fleet!$E$32)<=EOMONTH(EDATE($B$3,-1),0),OR(Fleet!$F$32="",N(Fleet!$F$32)>=EDATE($B$3,-1))),1,0))) | K33: =IF($A33="","",(SUMIFS(Trips!$H$5:$H$1004,Trips!$B$5:$B$1004,$A33,Trips!$L$5:$L$1004,EDATE($B$3,-2))+SUMIFS(Trips!$I$5:$I$1004,Trips!$B$5:$B$1004,$A33,Trips!$L$5:$L$1004,EDATE($B$3,-2))-SUMIFS(Trips!$J$5:$J$1004,Trips!$B$5:$B$1004,$A33,Trips!$L$5:$L$1004,EDATE($B$3,-2))-SUMIFS(Expenses!$E$5:$E$1004,Expenses!$B$5:$B$1004,$A33,Expenses!$G$5:$G$1004,EDATE($B$3,-2))-Fleet!$O$32*IF(AND(Fleet!$A$32<>"",N(Fleet!$E$32)<=EOMONTH(EDATE($B$3,-2),0),OR(Fleet!$F$32="",N(Fleet!$F$32)>=EDATE($B$3,-2))),1,0))) | L33: =IF($A33="","",SUMIFS(Trips!$M$5:$M$1004,Trips!$B$5:$B$1004,$A33,Trips!$L$5:$L$1004,"<="&$B$3)-SUMIFS(Expenses!$E$5:$E$1004,Expenses!$B$5:$B$1004,$A33,Expenses!$G$5:$G$1004,"<="&$B$3)-Fleet!$O$32*IF(N(Fleet!$E$32)=0,0,MAX(0,(YEAR(IF(Fleet!$F$32="",EOMONTH($B$3,0),MIN(Fleet!$F$32,EOMONTH($B$3,0))))-YEAR(Fleet!$E$32))*12+MONTH(IF(Fleet!$F$32="",EOMONTH($B$3,0),MIN(Fleet!$F$32,EOMONTH($B$3,0))))-MONTH(Fleet!$E$32)+1))) | M33: =IF($A33="","",Fleet!$H$32) | N33: =IF(OR($A33="",N(M33)=0),"",L33/M33) | O33: =IF(OR($A33="",N(C33)=0),"",IF(AND(I33<0,J33<0,K33<0),"REVIEW: 3 losing months",IF(I33<Assumptions!$B$9,"Below net target",IF(E33<Assumptions!$B$8,"Low utilization","On track"))))
A34: =IF(Fleet!A33="","",Fleet!A33) | B34: =IF(Fleet!A33="","",Fleet!B33&" "&Fleet!C33) | C34: =IF($A34="","",IF(AND(Fleet!$A$33<>"",N(Fleet!$E$33)<=EOMONTH($B$3,0),OR(Fleet!$F$33="",N(Fleet!$F$33)>=$B$3)),1,0)) | D34: =IF($A34="","",SUMIFS(Trips!$E$5:$E$1004,Trips!$B$5:$B$1004,$A34,Trips!$L$5:$L$1004,$B$3)) | E34: =IF(OR($A34="",N(C34)=0),"",D34/DAY(EOMONTH($B$3,0))) | F34: =IF($A34="","",SUMIFS(Trips!$H$5:$H$1004,Trips!$B$5:$B$1004,$A34,Trips!$L$5:$L$1004,$B$3)+SUMIFS(Trips!$I$5:$I$1004,Trips!$B$5:$B$1004,$A34,Trips!$L$5:$L$1004,$B$3)) | G34: =IF($A34="","",SUMIFS(Trips!$J$5:$J$1004,Trips!$B$5:$B$1004,$A34,Trips!$L$5:$L$1004,$B$3)+SUMIFS(Expenses!$E$5:$E$1004,Expenses!$B$5:$B$1004,$A34,Expenses!$G$5:$G$1004,$B$3)) | H34: =IF($A34="","",Fleet!$O$33*C34) | I34: =IF($A34="","",F34-G34-H34) | J34: =IF($A34="","",(SUMIFS(Trips!$H$5:$H$1004,Trips!$B$5:$B$1004,$A34,Trips!$L$5:$L$1004,EDATE($B$3,-1))+SUMIFS(Trips!$I$5:$I$1004,Trips!$B$5:$B$1004,$A34,Trips!$L$5:$L$1004,EDATE($B$3,-1))-SUMIFS(Trips!$J$5:$J$1004,Trips!$B$5:$B$1004,$A34,Trips!$L$5:$L$1004,EDATE($B$3,-1))-SUMIFS(Expenses!$E$5:$E$1004,Expenses!$B$5:$B$1004,$A34,Expenses!$G$5:$G$1004,EDATE($B$3,-1))-Fleet!$O$33*IF(AND(Fleet!$A$33<>"",N(Fleet!$E$33)<=EOMONTH(EDATE($B$3,-1),0),OR(Fleet!$F$33="",N(Fleet!$F$33)>=EDATE($B$3,-1))),1,0))) | K34: =IF($A34="","",(SUMIFS(Trips!$H$5:$H$1004,Trips!$B$5:$B$1004,$A34,Trips!$L$5:$L$1004,EDATE($B$3,-2))+SUMIFS(Trips!$I$5:$I$1004,Trips!$B$5:$B$1004,$A34,Trips!$L$5:$L$1004,EDATE($B$3,-2))-SUMIFS(Trips!$J$5:$J$1004,Trips!$B$5:$B$1004,$A34,Trips!$L$5:$L$1004,EDATE($B$3,-2))-SUMIFS(Expenses!$E$5:$E$1004,Expenses!$B$5:$B$1004,$A34,Expenses!$G$5:$G$1004,EDATE($B$3,-2))-Fleet!$O$33*IF(AND(Fleet!$A$33<>"",N(Fleet!$E$33)<=EOMONTH(EDATE($B$3,-2),0),OR(Fleet!$F$33="",N(Fleet!$F$33)>=EDATE($B$3,-2))),1,0))) | L34: =IF($A34="","",SUMIFS(Trips!$M$5:$M$1004,Trips!$B$5:$B$1004,$A34,Trips!$L$5:$L$1004,"<="&$B$3)-SUMIFS(Expenses!$E$5:$E$1004,Expenses!$B$5:$B$1004,$A34,Expenses!$G$5:$G$1004,"<="&$B$3)-Fleet!$O$33*IF(N(Fleet!$E$33)=0,0,MAX(0,(YEAR(IF(Fleet!$F$33="",EOMONTH($B$3,0),MIN(Fleet!$F$33,EOMONTH($B$3,0))))-YEAR(Fleet!$E$33))*12+MONTH(IF(Fleet!$F$33="",EOMONTH($B$3,0),MIN(Fleet!$F$33,EOMONTH($B$3,0))))-MONTH(Fleet!$E$33)+1))) | M34: =IF($A34="","",Fleet!$H$33) | N34: =IF(OR($A34="",N(M34)=0),"",L34/M34) | O34: =IF(OR($A34="",N(C34)=0),"",IF(AND(I34<0,J34<0,K34<0),"REVIEW: 3 losing months",IF(I34<Assumptions!$B$9,"Below net target",IF(E34<Assumptions!$B$8,"Low utilization","On track"))))
A35: =IF(Fleet!A34="","",Fleet!A34) | B35: =IF(Fleet!A34="","",Fleet!B34&" "&Fleet!C34) | C35: =IF($A35="","",IF(AND(Fleet!$A$34<>"",N(Fleet!$E$34)<=EOMONTH($B$3,0),OR(Fleet!$F$34="",N(Fleet!$F$34)>=$B$3)),1,0)) | D35: =IF($A35="","",SUMIFS(Trips!$E$5:$E$1004,Trips!$B$5:$B$1004,$A35,Trips!$L$5:$L$1004,$B$3)) | E35: =IF(OR($A35="",N(C35)=0),"",D35/DAY(EOMONTH($B$3,0))) | F35: =IF($A35="","",SUMIFS(Trips!$H$5:$H$1004,Trips!$B$5:$B$1004,$A35,Trips!$L$5:$L$1004,$B$3)+SUMIFS(Trips!$I$5:$I$1004,Trips!$B$5:$B$1004,$A35,Trips!$L$5:$L$1004,$B$3)) | G35: =IF($A35="","",SUMIFS(Trips!$J$5:$J$1004,Trips!$B$5:$B$1004,$A35,Trips!$L$5:$L$1004,$B$3)+SUMIFS(Expenses!$E$5:$E$1004,Expenses!$B$5:$B$1004,$A35,Expenses!$G$5:$G$1004,$B$3)) | H35: =IF($A35="","",Fleet!$O$34*C35) | I35: =IF($A35="","",F35-G35-H35) | J35: =IF($A35="","",(SUMIFS(Trips!$H$5:$H$1004,Trips!$B$5:$B$1004,$A35,Trips!$L$5:$L$1004,EDATE($B$3,-1))+SUMIFS(Trips!$I$5:$I$1004,Trips!$B$5:$B$1004,$A35,Trips!$L$5:$L$1004,EDATE($B$3,-1))-SUMIFS(Trips!$J$5:$J$1004,Trips!$B$5:$B$1004,$A35,Trips!$L$5:$L$1004,EDATE($B$3,-1))-SUMIFS(Expenses!$E$5:$E$1004,Expenses!$B$5:$B$1004,$A35,Expenses!$G$5:$G$1004,EDATE($B$3,-1))-Fleet!$O$34*IF(AND(Fleet!$A$34<>"",N(Fleet!$E$34)<=EOMONTH(EDATE($B$3,-1),0),OR(Fleet!$F$34="",N(Fleet!$F$34)>=EDATE($B$3,-1))),1,0))) | K35: =IF($A35="","",(SUMIFS(Trips!$H$5:$H$1004,Trips!$B$5:$B$1004,$A35,Trips!$L$5:$L$1004,EDATE($B$3,-2))+SUMIFS(Trips!$I$5:$I$1004,Trips!$B$5:$B$1004,$A35,Trips!$L$5:$L$1004,EDATE($B$3,-2))-SUMIFS(Trips!$J$5:$J$1004,Trips!$B$5:$B$1004,$A35,Trips!$L$5:$L$1004,EDATE($B$3,-2))-SUMIFS(Expenses!$E$5:$E$1004,Expenses!$B$5:$B$1004,$A35,Expenses!$G$5:$G$1004,EDATE($B$3,-2))-Fleet!$O$34*IF(AND(Fleet!$A$34<>"",N(Fleet!$E$34)<=EOMONTH(EDATE($B$3,-2),0),OR(Fleet!$F$34="",N(Fleet!$F$34)>=EDATE($B$3,-2))),1,0))) | L35: =IF($A35="","",SUMIFS(Trips!$M$5:$M$1004,Trips!$B$5:$B$1004,$A35,Trips!$L$5:$L$1004,"<="&$B$3)-SUMIFS(Expenses!$E$5:$E$1004,Expenses!$B$5:$B$1004,$A35,Expenses!$G$5:$G$1004,"<="&$B$3)-Fleet!$O$34*IF(N(Fleet!$E$34)=0,0,MAX(0,(YEAR(IF(Fleet!$F$34="",EOMONTH($B$3,0),MIN(Fleet!$F$34,EOMONTH($B$3,0))))-YEAR(Fleet!$E$34))*12+MONTH(IF(Fleet!$F$34="",EOMONTH($B$3,0),MIN(Fleet!$F$34,EOMONTH($B$3,0))))-MONTH(Fleet!$E$34)+1))) | M35: =IF($A35="","",Fleet!$H$34) | N35: =IF(OR($A35="",N(M35)=0),"",L35/M35) | O35: =IF(OR($A35="",N(C35)=0),"",IF(AND(I35<0,J35<0,K35<0),"REVIEW: 3 losing months",IF(I35<Assumptions!$B$9,"Below net target",IF(E35<Assumptions!$B$8,"Low utilization","On track"))))
A36: =IF(Fleet!A35="","",Fleet!A35) | B36: =IF(Fleet!A35="","",Fleet!B35&" "&Fleet!C35) | C36: =IF($A36="","",IF(AND(Fleet!$A$35<>"",N(Fleet!$E$35)<=EOMONTH($B$3,0),OR(Fleet!$F$35="",N(Fleet!$F$35)>=$B$3)),1,0)) | D36: =IF($A36="","",SUMIFS(Trips!$E$5:$E$1004,Trips!$B$5:$B$1004,$A36,Trips!$L$5:$L$1004,$B$3)) | E36: =IF(OR($A36="",N(C36)=0),"",D36/DAY(EOMONTH($B$3,0))) | F36: =IF($A36="","",SUMIFS(Trips!$H$5:$H$1004,Trips!$B$5:$B$1004,$A36,Trips!$L$5:$L$1004,$B$3)+SUMIFS(Trips!$I$5:$I$1004,Trips!$B$5:$B$1004,$A36,Trips!$L$5:$L$1004,$B$3)) | G36: =IF($A36="","",SUMIFS(Trips!$J$5:$J$1004,Trips!$B$5:$B$1004,$A36,Trips!$L$5:$L$1004,$B$3)+SUMIFS(Expenses!$E$5:$E$1004,Expenses!$B$5:$B$1004,$A36,Expenses!$G$5:$G$1004,$B$3)) | H36: =IF($A36="","",Fleet!$O$35*C36) | I36: =IF($A36="","",F36-G36-H36) | J36: =IF($A36="","",(SUMIFS(Trips!$H$5:$H$1004,Trips!$B$5:$B$1004,$A36,Trips!$L$5:$L$1004,EDATE($B$3,-1))+SUMIFS(Trips!$I$5:$I$1004,Trips!$B$5:$B$1004,$A36,Trips!$L$5:$L$1004,EDATE($B$3,-1))-SUMIFS(Trips!$J$5:$J$1004,Trips!$B$5:$B$1004,$A36,Trips!$L$5:$L$1004,EDATE($B$3,-1))-SUMIFS(Expenses!$E$5:$E$1004,Expenses!$B$5:$B$1004,$A36,Expenses!$G$5:$G$1004,EDATE($B$3,-1))-Fleet!$O$35*IF(AND(Fleet!$A$35<>"",N(Fleet!$E$35)<=EOMONTH(EDATE($B$3,-1),0),OR(Fleet!$F$35="",N(Fleet!$F$35)>=EDATE($B$3,-1))),1,0))) | K36: =IF($A36="","",(SUMIFS(Trips!$H$5:$H$1004,Trips!$B$5:$B$1004,$A36,Trips!$L$5:$L$1004,EDATE($B$3,-2))+SUMIFS(Trips!$I$5:$I$1004,Trips!$B$5:$B$1004,$A36,Trips!$L$5:$L$1004,EDATE($B$3,-2))-SUMIFS(Trips!$J$5:$J$1004,Trips!$B$5:$B$1004,$A36,Trips!$L$5:$L$1004,EDATE($B$3,-2))-SUMIFS(Expenses!$E$5:$E$1004,Expenses!$B$5:$B$1004,$A36,Expenses!$G$5:$G$1004,EDATE($B$3,-2))-Fleet!$O$35*IF(AND(Fleet!$A$35<>"",N(Fleet!$E$35)<=EOMONTH(EDATE($B$3,-2),0),OR(Fleet!$F$35="",N(Fleet!$F$35)>=EDATE($B$3,-2))),1,0))) | L36: =IF($A36="","",SUMIFS(Trips!$M$5:$M$1004,Trips!$B$5:$B$1004,$A36,Trips!$L$5:$L$1004,"<="&$B$3)-SUMIFS(Expenses!$E$5:$E$1004,Expenses!$B$5:$B$1004,$A36,Expenses!$G$5:$G$1004,"<="&$B$3)-Fleet!$O$35*IF(N(Fleet!$E$35)=0,0,MAX(0,(YEAR(IF(Fleet!$F$35="",EOMONTH($B$3,0),MIN(Fleet!$F$35,EOMONTH($B$3,0))))-YEAR(Fleet!$E$35))*12+MONTH(IF(Fleet!$F$35="",EOMONTH($B$3,0),MIN(Fleet!$F$35,EOMONTH($B$3,0))))-MONTH(Fleet!$E$35)+1))) | M36: =IF($A36="","",Fleet!$H$35) | N36: =IF(OR($A36="",N(M36)=0),"",L36/M36) | O36: =IF(OR($A36="",N(C36)=0),"",IF(AND(I36<0,J36<0,K36<0),"REVIEW: 3 losing months",IF(I36<Assumptions!$B$9,"Below net target",IF(E36<Assumptions!$B$8,"Low utilization","On track"))))
A37: =IF(Fleet!A36="","",Fleet!A36) | B37: =IF(Fleet!A36="","",Fleet!B36&" "&Fleet!C36) | C37: =IF($A37="","",IF(AND(Fleet!$A$36<>"",N(Fleet!$E$36)<=EOMONTH($B$3,0),OR(Fleet!$F$36="",N(Fleet!$F$36)>=$B$3)),1,0)) | D37: =IF($A37="","",SUMIFS(Trips!$E$5:$E$1004,Trips!$B$5:$B$1004,$A37,Trips!$L$5:$L$1004,$B$3)) | E37: =IF(OR($A37="",N(C37)=0),"",D37/DAY(EOMONTH($B$3,0))) | F37: =IF($A37="","",SUMIFS(Trips!$H$5:$H$1004,Trips!$B$5:$B$1004,$A37,Trips!$L$5:$L$1004,$B$3)+SUMIFS(Trips!$I$5:$I$1004,Trips!$B$5:$B$1004,$A37,Trips!$L$5:$L$1004,$B$3)) | G37: =IF($A37="","",SUMIFS(Trips!$J$5:$J$1004,Trips!$B$5:$B$1004,$A37,Trips!$L$5:$L$1004,$B$3)+SUMIFS(Expenses!$E$5:$E$1004,Expenses!$B$5:$B$1004,$A37,Expenses!$G$5:$G$1004,$B$3)) | H37: =IF($A37="","",Fleet!$O$36*C37) | I37: =IF($A37="","",F37-G37-H37) | J37: =IF($A37="","",(SUMIFS(Trips!$H$5:$H$1004,Trips!$B$5:$B$1004,$A37,Trips!$L$5:$L$1004,EDATE($B$3,-1))+SUMIFS(Trips!$I$5:$I$1004,Trips!$B$5:$B$1004,$A37,Trips!$L$5:$L$1004,EDATE($B$3,-1))-SUMIFS(Trips!$J$5:$J$1004,Trips!$B$5:$B$1004,$A37,Trips!$L$5:$L$1004,EDATE($B$3,-1))-SUMIFS(Expenses!$E$5:$E$1004,Expenses!$B$5:$B$1004,$A37,Expenses!$G$5:$G$1004,EDATE($B$3,-1))-Fleet!$O$36*IF(AND(Fleet!$A$36<>"",N(Fleet!$E$36)<=EOMONTH(EDATE($B$3,-1),0),OR(Fleet!$F$36="",N(Fleet!$F$36)>=EDATE($B$3,-1))),1,0))) | K37: =IF($A37="","",(SUMIFS(Trips!$H$5:$H$1004,Trips!$B$5:$B$1004,$A37,Trips!$L$5:$L$1004,EDATE($B$3,-2))+SUMIFS(Trips!$I$5:$I$1004,Trips!$B$5:$B$1004,$A37,Trips!$L$5:$L$1004,EDATE($B$3,-2))-SUMIFS(Trips!$J$5:$J$1004,Trips!$B$5:$B$1004,$A37,Trips!$L$5:$L$1004,EDATE($B$3,-2))-SUMIFS(Expenses!$E$5:$E$1004,Expenses!$B$5:$B$1004,$A37,Expenses!$G$5:$G$1004,EDATE($B$3,-2))-Fleet!$O$36*IF(AND(Fleet!$A$36<>"",N(Fleet!$E$36)<=EOMONTH(EDATE($B$3,-2),0),OR(Fleet!$F$36="",N(Fleet!$F$36)>=EDATE($B$3,-2))),1,0))) | L37: =IF($A37="","",SUMIFS(Trips!$M$5:$M$1004,Trips!$B$5:$B$1004,$A37,Trips!$L$5:$L$1004,"<="&$B$3)-SUMIFS(Expenses!$E$5:$E$1004,Expenses!$B$5:$B$1004,$A37,Expenses!$G$5:$G$1004,"<="&$B$3)-Fleet!$O$36*IF(N(Fleet!$E$36)=0,0,MAX(0,(YEAR(IF(Fleet!$F$36="",EOMONTH($B$3,0),MIN(Fleet!$F$36,EOMONTH($B$3,0))))-YEAR(Fleet!$E$36))*12+MONTH(IF(Fleet!$F$36="",EOMONTH($B$3,0),MIN(Fleet!$F$36,EOMONTH($B$3,0))))-MONTH(Fleet!$E$36)+1))) | M37: =IF($A37="","",Fleet!$H$36) | N37: =IF(OR($A37="",N(M37)=0),"",L37/M37) | O37: =IF(OR($A37="",N(C37)=0),"",IF(AND(I37<0,J37<0,K37<0),"REVIEW: 3 losing months",IF(I37<Assumptions!$B$9,"Below net target",IF(E37<Assumptions!$B$8,"Low utilization","On track"))))
A38: =IF(Fleet!A37="","",Fleet!A37) | B38: =IF(Fleet!A37="","",Fleet!B37&" "&Fleet!C37) | C38: =IF($A38="","",IF(AND(Fleet!$A$37<>"",N(Fleet!$E$37)<=EOMONTH($B$3,0),OR(Fleet!$F$37="",N(Fleet!$F$37)>=$B$3)),1,0)) | D38: =IF($A38="","",SUMIFS(Trips!$E$5:$E$1004,Trips!$B$5:$B$1004,$A38,Trips!$L$5:$L$1004,$B$3)) | E38: =IF(OR($A38="",N(C38)=0),"",D38/DAY(EOMONTH($B$3,0))) | F38: =IF($A38="","",SUMIFS(Trips!$H$5:$H$1004,Trips!$B$5:$B$1004,$A38,Trips!$L$5:$L$1004,$B$3)+SUMIFS(Trips!$I$5:$I$1004,Trips!$B$5:$B$1004,$A38,Trips!$L$5:$L$1004,$B$3)) | G38: =IF($A38="","",SUMIFS(Trips!$J$5:$J$1004,Trips!$B$5:$B$1004,$A38,Trips!$L$5:$L$1004,$B$3)+SUMIFS(Expenses!$E$5:$E$1004,Expenses!$B$5:$B$1004,$A38,Expenses!$G$5:$G$1004,$B$3)) | H38: =IF($A38="","",Fleet!$O$37*C38) | I38: =IF($A38="","",F38-G38-H38) | J38: =IF($A38="","",(SUMIFS(Trips!$H$5:$H$1004,Trips!$B$5:$B$1004,$A38,Trips!$L$5:$L$1004,EDATE($B$3,-1))+SUMIFS(Trips!$I$5:$I$1004,Trips!$B$5:$B$1004,$A38,Trips!$L$5:$L$1004,EDATE($B$3,-1))-SUMIFS(Trips!$J$5:$J$1004,Trips!$B$5:$B$1004,$A38,Trips!$L$5:$L$1004,EDATE($B$3,-1))-SUMIFS(Expenses!$E$5:$E$1004,Expenses!$B$5:$B$1004,$A38,Expenses!$G$5:$G$1004,EDATE($B$3,-1))-Fleet!$O$37*IF(AND(Fleet!$A$37<>"",N(Fleet!$E$37)<=EOMONTH(EDATE($B$3,-1),0),OR(Fleet!$F$37="",N(Fleet!$F$37)>=EDATE($B$3,-1))),1,0))) | K38: =IF($A38="","",(SUMIFS(Trips!$H$5:$H$1004,Trips!$B$5:$B$1004,$A38,Trips!$L$5:$L$1004,EDATE($B$3,-2))+SUMIFS(Trips!$I$5:$I$1004,Trips!$B$5:$B$1004,$A38,Trips!$L$5:$L$1004,EDATE($B$3,-2))-SUMIFS(Trips!$J$5:$J$1004,Trips!$B$5:$B$1004,$A38,Trips!$L$5:$L$1004,EDATE($B$3,-2))-SUMIFS(Expenses!$E$5:$E$1004,Expenses!$B$5:$B$1004,$A38,Expenses!$G$5:$G$1004,EDATE($B$3,-2))-Fleet!$O$37*IF(AND(Fleet!$A$37<>"",N(Fleet!$E$37)<=EOMONTH(EDATE($B$3,-2),0),OR(Fleet!$F$37="",N(Fleet!$F$37)>=EDATE($B$3,-2))),1,0))) | L38: =IF($A38="","",SUMIFS(Trips!$M$5:$M$1004,Trips!$B$5:$B$1004,$A38,Trips!$L$5:$L$1004,"<="&$B$3)-SUMIFS(Expenses!$E$5:$E$1004,Expenses!$B$5:$B$1004,$A38,Expenses!$G$5:$G$1004,"<="&$B$3)-Fleet!$O$37*IF(N(Fleet!$E$37)=0,0,MAX(0,(YEAR(IF(Fleet!$F$37="",EOMONTH($B$3,0),MIN(Fleet!$F$37,EOMONTH($B$3,0))))-YEAR(Fleet!$E$37))*12+MONTH(IF(Fleet!$F$37="",EOMONTH($B$3,0),MIN(Fleet!$F$37,EOMONTH($B$3,0))))-MONTH(Fleet!$E$37)+1))) | M38: =IF($A38="","",Fleet!$H$37) | N38: =IF(OR($A38="",N(M38)=0),"",L38/M38) | O38: =IF(OR($A38="",N(C38)=0),"",IF(AND(I38<0,J38<0,K38<0),"REVIEW: 3 losing months",IF(I38<Assumptions!$B$9,"Below net target",IF(E38<Assumptions!$B$8,"Low utilization","On track"))))
A39: =IF(Fleet!A38="","",Fleet!A38) | B39: =IF(Fleet!A38="","",Fleet!B38&" "&Fleet!C38) | C39: =IF($A39="","",IF(AND(Fleet!$A$38<>"",N(Fleet!$E$38)<=EOMONTH($B$3,0),OR(Fleet!$F$38="",N(Fleet!$F$38)>=$B$3)),1,0)) | D39: =IF($A39="","",SUMIFS(Trips!$E$5:$E$1004,Trips!$B$5:$B$1004,$A39,Trips!$L$5:$L$1004,$B$3)) | E39: =IF(OR($A39="",N(C39)=0),"",D39/DAY(EOMONTH($B$3,0))) | F39: =IF($A39="","",SUMIFS(Trips!$H$5:$H$1004,Trips!$B$5:$B$1004,$A39,Trips!$L$5:$L$1004,$B$3)+SUMIFS(Trips!$I$5:$I$1004,Trips!$B$5:$B$1004,$A39,Trips!$L$5:$L$1004,$B$3)) | G39: =IF($A39="","",SUMIFS(Trips!$J$5:$J$1004,Trips!$B$5:$B$1004,$A39,Trips!$L$5:$L$1004,$B$3)+SUMIFS(Expenses!$E$5:$E$1004,Expenses!$B$5:$B$1004,$A39,Expenses!$G$5:$G$1004,$B$3)) | H39: =IF($A39="","",Fleet!$O$38*C39) | I39: =IF($A39="","",F39-G39-H39) | J39: =IF($A39="","",(SUMIFS(Trips!$H$5:$H$1004,Trips!$B$5:$B$1004,$A39,Trips!$L$5:$L$1004,EDATE($B$3,-1))+SUMIFS(Trips!$I$5:$I$1004,Trips!$B$5:$B$1004,$A39,Trips!$L$5:$L$1004,EDATE($B$3,-1))-SUMIFS(Trips!$J$5:$J$1004,Trips!$B$5:$B$1004,$A39,Trips!$L$5:$L$1004,EDATE($B$3,-1))-SUMIFS(Expenses!$E$5:$E$1004,Expenses!$B$5:$B$1004,$A39,Expenses!$G$5:$G$1004,EDATE($B$3,-1))-Fleet!$O$38*IF(AND(Fleet!$A$38<>"",N(Fleet!$E$38)<=EOMONTH(EDATE($B$3,-1),0),OR(Fleet!$F$38="",N(Fleet!$F$38)>=EDATE($B$3,-1))),1,0))) | K39: =IF($A39="","",(SUMIFS(Trips!$H$5:$H$1004,Trips!$B$5:$B$1004,$A39,Trips!$L$5:$L$1004,EDATE($B$3,-2))+SUMIFS(Trips!$I$5:$I$1004,Trips!$B$5:$B$1004,$A39,Trips!$L$5:$L$1004,EDATE($B$3,-2))-SUMIFS(Trips!$J$5:$J$1004,Trips!$B$5:$B$1004,$A39,Trips!$L$5:$L$1004,EDATE($B$3,-2))-SUMIFS(Expenses!$E$5:$E$1004,Expenses!$B$5:$B$1004,$A39,Expenses!$G$5:$G$1004,EDATE($B$3,-2))-Fleet!$O$38*IF(AND(Fleet!$A$38<>"",N(Fleet!$E$38)<=EOMONTH(EDATE($B$3,-2),0),OR(Fleet!$F$38="",N(Fleet!$F$38)>=EDATE($B$3,-2))),1,0))) | L39: =IF($A39="","",SUMIFS(Trips!$M$5:$M$1004,Trips!$B$5:$B$1004,$A39,Trips!$L$5:$L$1004,"<="&$B$3)-SUMIFS(Expenses!$E$5:$E$1004,Expenses!$B$5:$B$1004,$A39,Expenses!$G$5:$G$1004,"<="&$B$3)-Fleet!$O$38*IF(N(Fleet!$E$38)=0,0,MAX(0,(YEAR(IF(Fleet!$F$38="",EOMONTH($B$3,0),MIN(Fleet!$F$38,EOMONTH($B$3,0))))-YEAR(Fleet!$E$38))*12+MONTH(IF(Fleet!$F$38="",EOMONTH($B$3,0),MIN(Fleet!$F$38,EOMONTH($B$3,0))))-MONTH(Fleet!$E$38)+1))) | M39: =IF($A39="","",Fleet!$H$38) | N39: =IF(OR($A39="",N(M39)=0),"",L39/M39) | O39: =IF(OR($A39="",N(C39)=0),"",IF(AND(I39<0,J39<0,K39<0),"REVIEW: 3 losing months",IF(I39<Assumptions!$B$9,"Below net target",IF(E39<Assumptions!$B$8,"Low utilization","On track"))))
A40: =IF(Fleet!A39="","",Fleet!A39) | B40: =IF(Fleet!A39="","",Fleet!B39&" "&Fleet!C39) | C40: =IF($A40="","",IF(AND(Fleet!$A$39<>"",N(Fleet!$E$39)<=EOMONTH($B$3,0),OR(Fleet!$F$39="",N(Fleet!$F$39)>=$B$3)),1,0)) | D40: =IF($A40="","",SUMIFS(Trips!$E$5:$E$1004,Trips!$B$5:$B$1004,$A40,Trips!$L$5:$L$1004,$B$3)) | E40: =IF(OR($A40="",N(C40)=0),"",D40/DAY(EOMONTH($B$3,0))) | F40: =IF($A40="","",SUMIFS(Trips!$H$5:$H$1004,Trips!$B$5:$B$1004,$A40,Trips!$L$5:$L$1004,$B$3)+SUMIFS(Trips!$I$5:$I$1004,Trips!$B$5:$B$1004,$A40,Trips!$L$5:$L$1004,$B$3)) | G40: =IF($A40="","",SUMIFS(Trips!$J$5:$J$1004,Trips!$B$5:$B$1004,$A40,Trips!$L$5:$L$1004,$B$3)+SUMIFS(Expenses!$E$5:$E$1004,Expenses!$B$5:$B$1004,$A40,Expenses!$G$5:$G$1004,$B$3)) | H40: =IF($A40="","",Fleet!$O$39*C40) | I40: =IF($A40="","",F40-G40-H40) | J40: =IF($A40="","",(SUMIFS(Trips!$H$5:$H$1004,Trips!$B$5:$B$1004,$A40,Trips!$L$5:$L$1004,EDATE($B$3,-1))+SUMIFS(Trips!$I$5:$I$1004,Trips!$B$5:$B$1004,$A40,Trips!$L$5:$L$1004,EDATE($B$3,-1))-SUMIFS(Trips!$J$5:$J$1004,Trips!$B$5:$B$1004,$A40,Trips!$L$5:$L$1004,EDATE($B$3,-1))-SUMIFS(Expenses!$E$5:$E$1004,Expenses!$B$5:$B$1004,$A40,Expenses!$G$5:$G$1004,EDATE($B$3,-1))-Fleet!$O$39*IF(AND(Fleet!$A$39<>"",N(Fleet!$E$39)<=EOMONTH(EDATE($B$3,-1),0),OR(Fleet!$F$39="",N(Fleet!$F$39)>=EDATE($B$3,-1))),1,0))) | K40: =IF($A40="","",(SUMIFS(Trips!$H$5:$H$1004,Trips!$B$5:$B$1004,$A40,Trips!$L$5:$L$1004,EDATE($B$3,-2))+SUMIFS(Trips!$I$5:$I$1004,Trips!$B$5:$B$1004,$A40,Trips!$L$5:$L$1004,EDATE($B$3,-2))-SUMIFS(Trips!$J$5:$J$1004,Trips!$B$5:$B$1004,$A40,Trips!$L$5:$L$1004,EDATE($B$3,-2))-SUMIFS(Expenses!$E$5:$E$1004,Expenses!$B$5:$B$1004,$A40,Expenses!$G$5:$G$1004,EDATE($B$3,-2))-Fleet!$O$39*IF(AND(Fleet!$A$39<>"",N(Fleet!$E$39)<=EOMONTH(EDATE($B$3,-2),0),OR(Fleet!$F$39="",N(Fleet!$F$39)>=EDATE($B$3,-2))),1,0))) | L40: =IF($A40="","",SUMIFS(Trips!$M$5:$M$1004,Trips!$B$5:$B$1004,$A40,Trips!$L$5:$L$1004,"<="&$B$3)-SUMIFS(Expenses!$E$5:$E$1004,Expenses!$B$5:$B$1004,$A40,Expenses!$G$5:$G$1004,"<="&$B$3)-Fleet!$O$39*IF(N(Fleet!$E$39)=0,0,MAX(0,(YEAR(IF(Fleet!$F$39="",EOMONTH($B$3,0),MIN(Fleet!$F$39,EOMONTH($B$3,0))))-YEAR(Fleet!$E$39))*12+MONTH(IF(Fleet!$F$39="",EOMONTH($B$3,0),MIN(Fleet!$F$39,EOMONTH($B$3,0))))-MONTH(Fleet!$E$39)+1))) | M40: =IF($A40="","",Fleet!$H$39) | N40: =IF(OR($A40="",N(M40)=0),"",L40/M40) | O40: =IF(OR($A40="",N(C40)=0),"",IF(AND(I40<0,J40<0,K40<0),"REVIEW: 3 losing months",IF(I40<Assumptions!$B$9,"Below net target",IF(E40<Assumptions!$B$8,"Low utilization","On track"))))
A41: =IF(Fleet!A40="","",Fleet!A40) | B41: =IF(Fleet!A40="","",Fleet!B40&" "&Fleet!C40) | C41: =IF($A41="","",IF(AND(Fleet!$A$40<>"",N(Fleet!$E$40)<=EOMONTH($B$3,0),OR(Fleet!$F$40="",N(Fleet!$F$40)>=$B$3)),1,0)) | D41: =IF($A41="","",SUMIFS(Trips!$E$5:$E$1004,Trips!$B$5:$B$1004,$A41,Trips!$L$5:$L$1004,$B$3)) | E41: =IF(OR($A41="",N(C41)=0),"",D41/DAY(EOMONTH($B$3,0))) | F41: =IF($A41="","",SUMIFS(Trips!$H$5:$H$1004,Trips!$B$5:$B$1004,$A41,Trips!$L$5:$L$1004,$B$3)+SUMIFS(Trips!$I$5:$I$1004,Trips!$B$5:$B$1004,$A41,Trips!$L$5:$L$1004,$B$3)) | G41: =IF($A41="","",SUMIFS(Trips!$J$5:$J$1004,Trips!$B$5:$B$1004,$A41,Trips!$L$5:$L$1004,$B$3)+SUMIFS(Expenses!$E$5:$E$1004,Expenses!$B$5:$B$1004,$A41,Expenses!$G$5:$G$1004,$B$3)) | H41: =IF($A41="","",Fleet!$O$40*C41) | I41: =IF($A41="","",F41-G41-H41) | J41: =IF($A41="","",(SUMIFS(Trips!$H$5:$H$1004,Trips!$B$5:$B$1004,$A41,Trips!$L$5:$L$1004,EDATE($B$3,-1))+SUMIFS(Trips!$I$5:$I$1004,Trips!$B$5:$B$1004,$A41,Trips!$L$5:$L$1004,EDATE($B$3,-1))-SUMIFS(Trips!$J$5:$J$1004,Trips!$B$5:$B$1004,$A41,Trips!$L$5:$L$1004,EDATE($B$3,-1))-SUMIFS(Expenses!$E$5:$E$1004,Expenses!$B$5:$B$1004,$A41,Expenses!$G$5:$G$1004,EDATE($B$3,-1))-Fleet!$O$40*IF(AND(Fleet!$A$40<>"",N(Fleet!$E$40)<=EOMONTH(EDATE($B$3,-1),0),OR(Fleet!$F$40="",N(Fleet!$F$40)>=EDATE($B$3,-1))),1,0))) | K41: =IF($A41="","",(SUMIFS(Trips!$H$5:$H$1004,Trips!$B$5:$B$1004,$A41,Trips!$L$5:$L$1004,EDATE($B$3,-2))+SUMIFS(Trips!$I$5:$I$1004,Trips!$B$5:$B$1004,$A41,Trips!$L$5:$L$1004,EDATE($B$3,-2))-SUMIFS(Trips!$J$5:$J$1004,Trips!$B$5:$B$1004,$A41,Trips!$L$5:$L$1004,EDATE($B$3,-2))-SUMIFS(Expenses!$E$5:$E$1004,Expenses!$B$5:$B$1004,$A41,Expenses!$G$5:$G$1004,EDATE($B$3,-2))-Fleet!$O$40*IF(AND(Fleet!$A$40<>"",N(Fleet!$E$40)<=EOMONTH(EDATE($B$3,-2),0),OR(Fleet!$F$40="",N(Fleet!$F$40)>=EDATE($B$3,-2))),1,0))) | L41: =IF($A41="","",SUMIFS(Trips!$M$5:$M$1004,Trips!$B$5:$B$1004,$A41,Trips!$L$5:$L$1004,"<="&$B$3)-SUMIFS(Expenses!$E$5:$E$1004,Expenses!$B$5:$B$1004,$A41,Expenses!$G$5:$G$1004,"<="&$B$3)-Fleet!$O$40*IF(N(Fleet!$E$40)=0,0,MAX(0,(YEAR(IF(Fleet!$F$40="",EOMONTH($B$3,0),MIN(Fleet!$F$40,EOMONTH($B$3,0))))-YEAR(Fleet!$E$40))*12+MONTH(IF(Fleet!$F$40="",EOMONTH($B$3,0),MIN(Fleet!$F$40,EOMONTH($B$3,0))))-MONTH(Fleet!$E$40)+1))) | M41: =IF($A41="","",Fleet!$H$40) | N41: =IF(OR($A41="",N(M41)=0),"",L41/M41) | O41: =IF(OR($A41="",N(C41)=0),"",IF(AND(I41<0,J41<0,K41<0),"REVIEW: 3 losing months",IF(I41<Assumptions!$B$9,"Below net target",IF(E41<Assumptions!$B$8,"Low utilization","On track"))))
A42: =IF(Fleet!A41="","",Fleet!A41) | B42: =IF(Fleet!A41="","",Fleet!B41&" "&Fleet!C41) | C42: =IF($A42="","",IF(AND(Fleet!$A$41<>"",N(Fleet!$E$41)<=EOMONTH($B$3,0),OR(Fleet!$F$41="",N(Fleet!$F$41)>=$B$3)),1,0)) | D42: =IF($A42="","",SUMIFS(Trips!$E$5:$E$1004,Trips!$B$5:$B$1004,$A42,Trips!$L$5:$L$1004,$B$3)) | E42: =IF(OR($A42="",N(C42)=0),"",D42/DAY(EOMONTH($B$3,0))) | F42: =IF($A42="","",SUMIFS(Trips!$H$5:$H$1004,Trips!$B$5:$B$1004,$A42,Trips!$L$5:$L$1004,$B$3)+SUMIFS(Trips!$I$5:$I$1004,Trips!$B$5:$B$1004,$A42,Trips!$L$5:$L$1004,$B$3)) | G42: =IF($A42="","",SUMIFS(Trips!$J$5:$J$1004,Trips!$B$5:$B$1004,$A42,Trips!$L$5:$L$1004,$B$3)+SUMIFS(Expenses!$E$5:$E$1004,Expenses!$B$5:$B$1004,$A42,Expenses!$G$5:$G$1004,$B$3)) | H42: =IF($A42="","",Fleet!$O$41*C42) | I42: =IF($A42="","",F42-G42-H42) | J42: =IF($A42="","",(SUMIFS(Trips!$H$5:$H$1004,Trips!$B$5:$B$1004,$A42,Trips!$L$5:$L$1004,EDATE($B$3,-1))+SUMIFS(Trips!$I$5:$I$1004,Trips!$B$5:$B$1004,$A42,Trips!$L$5:$L$1004,EDATE($B$3,-1))-SUMIFS(Trips!$J$5:$J$1004,Trips!$B$5:$B$1004,$A42,Trips!$L$5:$L$1004,EDATE($B$3,-1))-SUMIFS(Expenses!$E$5:$E$1004,Expenses!$B$5:$B$1004,$A42,Expenses!$G$5:$G$1004,EDATE($B$3,-1))-Fleet!$O$41*IF(AND(Fleet!$A$41<>"",N(Fleet!$E$41)<=EOMONTH(EDATE($B$3,-1),0),OR(Fleet!$F$41="",N(Fleet!$F$41)>=EDATE($B$3,-1))),1,0))) | K42: =IF($A42="","",(SUMIFS(Trips!$H$5:$H$1004,Trips!$B$5:$B$1004,$A42,Trips!$L$5:$L$1004,EDATE($B$3,-2))+SUMIFS(Trips!$I$5:$I$1004,Trips!$B$5:$B$1004,$A42,Trips!$L$5:$L$1004,EDATE($B$3,-2))-SUMIFS(Trips!$J$5:$J$1004,Trips!$B$5:$B$1004,$A42,Trips!$L$5:$L$1004,EDATE($B$3,-2))-SUMIFS(Expenses!$E$5:$E$1004,Expenses!$B$5:$B$1004,$A42,Expenses!$G$5:$G$1004,EDATE($B$3,-2))-Fleet!$O$41*IF(AND(Fleet!$A$41<>"",N(Fleet!$E$41)<=EOMONTH(EDATE($B$3,-2),0),OR(Fleet!$F$41="",N(Fleet!$F$41)>=EDATE($B$3,-2))),1,0))) | L42: =IF($A42="","",SUMIFS(Trips!$M$5:$M$1004,Trips!$B$5:$B$1004,$A42,Trips!$L$5:$L$1004,"<="&$B$3)-SUMIFS(Expenses!$E$5:$E$1004,Expenses!$B$5:$B$1004,$A42,Expenses!$G$5:$G$1004,"<="&$B$3)-Fleet!$O$41*IF(N(Fleet!$E$41)=0,0,MAX(0,(YEAR(IF(Fleet!$F$41="",EOMONTH($B$3,0),MIN(Fleet!$F$41,EOMONTH($B$3,0))))-YEAR(Fleet!$E$41))*12+MONTH(IF(Fleet!$F$41="",EOMONTH($B$3,0),MIN(Fleet!$F$41,EOMONTH($B$3,0))))-MONTH(Fleet!$E$41)+1))) | M42: =IF($A42="","",Fleet!$H$41) | N42: =IF(OR($A42="",N(M42)=0),"",L42/M42) | O42: =IF(OR($A42="",N(C42)=0),"",IF(AND(I42<0,J42<0,K42<0),"REVIEW: 3 losing months",IF(I42<Assumptions!$B$9,"Below net target",IF(E42<Assumptions!$B$8,"Low utilization","On track"))))
A43: =IF(Fleet!A42="","",Fleet!A42) | B43: =IF(Fleet!A42="","",Fleet!B42&" "&Fleet!C42) | C43: =IF($A43="","",IF(AND(Fleet!$A$42<>"",N(Fleet!$E$42)<=EOMONTH($B$3,0),OR(Fleet!$F$42="",N(Fleet!$F$42)>=$B$3)),1,0)) | D43: =IF($A43="","",SUMIFS(Trips!$E$5:$E$1004,Trips!$B$5:$B$1004,$A43,Trips!$L$5:$L$1004,$B$3)) | E43: =IF(OR($A43="",N(C43)=0),"",D43/DAY(EOMONTH($B$3,0))) | F43: =IF($A43="","",SUMIFS(Trips!$H$5:$H$1004,Trips!$B$5:$B$1004,$A43,Trips!$L$5:$L$1004,$B$3)+SUMIFS(Trips!$I$5:$I$1004,Trips!$B$5:$B$1004,$A43,Trips!$L$5:$L$1004,$B$3)) | G43: =IF($A43="","",SUMIFS(Trips!$J$5:$J$1004,Trips!$B$5:$B$1004,$A43,Trips!$L$5:$L$1004,$B$3)+SUMIFS(Expenses!$E$5:$E$1004,Expenses!$B$5:$B$1004,$A43,Expenses!$G$5:$G$1004,$B$3)) | H43: =IF($A43="","",Fleet!$O$42*C43) | I43: =IF($A43="","",F43-G43-H43) | J43: =IF($A43="","",(SUMIFS(Trips!$H$5:$H$1004,Trips!$B$5:$B$1004,$A43,Trips!$L$5:$L$1004,EDATE($B$3,-1))+SUMIFS(Trips!$I$5:$I$1004,Trips!$B$5:$B$1004,$A43,Trips!$L$5:$L$1004,EDATE($B$3,-1))-SUMIFS(Trips!$J$5:$J$1004,Trips!$B$5:$B$1004,$A43,Trips!$L$5:$L$1004,EDATE($B$3,-1))-SUMIFS(Expenses!$E$5:$E$1004,Expenses!$B$5:$B$1004,$A43,Expenses!$G$5:$G$1004,EDATE($B$3,-1))-Fleet!$O$42*IF(AND(Fleet!$A$42<>"",N(Fleet!$E$42)<=EOMONTH(EDATE($B$3,-1),0),OR(Fleet!$F$42="",N(Fleet!$F$42)>=EDATE($B$3,-1))),1,0))) | K43: =IF($A43="","",(SUMIFS(Trips!$H$5:$H$1004,Trips!$B$5:$B$1004,$A43,Trips!$L$5:$L$1004,EDATE($B$3,-2))+SUMIFS(Trips!$I$5:$I$1004,Trips!$B$5:$B$1004,$A43,Trips!$L$5:$L$1004,EDATE($B$3,-2))-SUMIFS(Trips!$J$5:$J$1004,Trips!$B$5:$B$1004,$A43,Trips!$L$5:$L$1004,EDATE($B$3,-2))-SUMIFS(Expenses!$E$5:$E$1004,Expenses!$B$5:$B$1004,$A43,Expenses!$G$5:$G$1004,EDATE($B$3,-2))-Fleet!$O$42*IF(AND(Fleet!$A$42<>"",N(Fleet!$E$42)<=EOMONTH(EDATE($B$3,-2),0),OR(Fleet!$F$42="",N(Fleet!$F$42)>=EDATE($B$3,-2))),1,0))) | L43: =IF($A43="","",SUMIFS(Trips!$M$5:$M$1004,Trips!$B$5:$B$1004,$A43,Trips!$L$5:$L$1004,"<="&$B$3)-SUMIFS(Expenses!$E$5:$E$1004,Expenses!$B$5:$B$1004,$A43,Expenses!$G$5:$G$1004,"<="&$B$3)-Fleet!$O$42*IF(N(Fleet!$E$42)=0,0,MAX(0,(YEAR(IF(Fleet!$F$42="",EOMONTH($B$3,0),MIN(Fleet!$F$42,EOMONTH($B$3,0))))-YEAR(Fleet!$E$42))*12+MONTH(IF(Fleet!$F$42="",EOMONTH($B$3,0),MIN(Fleet!$F$42,EOMONTH($B$3,0))))-MONTH(Fleet!$E$42)+1))) | M43: =IF($A43="","",Fleet!$H$42) | N43: =IF(OR($A43="",N(M43)=0),"",L43/M43) | O43: =IF(OR($A43="",N(C43)=0),"",IF(AND(I43<0,J43<0,K43<0),"REVIEW: 3 losing months",IF(I43<Assumptions!$B$9,"Below net target",IF(E43<Assumptions!$B$8,"Low utilization","On track"))))
A44: =IF(Fleet!A43="","",Fleet!A43) | B44: =IF(Fleet!A43="","",Fleet!B43&" "&Fleet!C43) | C44: =IF($A44="","",IF(AND(Fleet!$A$43<>"",N(Fleet!$E$43)<=EOMONTH($B$3,0),OR(Fleet!$F$43="",N(Fleet!$F$43)>=$B$3)),1,0)) | D44: =IF($A44="","",SUMIFS(Trips!$E$5:$E$1004,Trips!$B$5:$B$1004,$A44,Trips!$L$5:$L$1004,$B$3)) | E44: =IF(OR($A44="",N(C44)=0),"",D44/DAY(EOMONTH($B$3,0))) | F44: =IF($A44="","",SUMIFS(Trips!$H$5:$H$1004,Trips!$B$5:$B$1004,$A44,Trips!$L$5:$L$1004,$B$3)+SUMIFS(Trips!$I$5:$I$1004,Trips!$B$5:$B$1004,$A44,Trips!$L$5:$L$1004,$B$3)) | G44: =IF($A44="","",SUMIFS(Trips!$J$5:$J$1004,Trips!$B$5:$B$1004,$A44,Trips!$L$5:$L$1004,$B$3)+SUMIFS(Expenses!$E$5:$E$1004,Expenses!$B$5:$B$1004,$A44,Expenses!$G$5:$G$1004,$B$3)) | H44: =IF($A44="","",Fleet!$O$43*C44) | I44: =IF($A44="","",F44-G44-H44) | J44: =IF($A44="","",(SUMIFS(Trips!$H$5:$H$1004,Trips!$B$5:$B$1004,$A44,Trips!$L$5:$L$1004,EDATE($B$3,-1))+SUMIFS(Trips!$I$5:$I$1004,Trips!$B$5:$B$1004,$A44,Trips!$L$5:$L$1004,EDATE($B$3,-1))-SUMIFS(Trips!$J$5:$J$1004,Trips!$B$5:$B$1004,$A44,Trips!$L$5:$L$1004,EDATE($B$3,-1))-SUMIFS(Expenses!$E$5:$E$1004,Expenses!$B$5:$B$1004,$A44,Expenses!$G$5:$G$1004,EDATE($B$3,-1))-Fleet!$O$43*IF(AND(Fleet!$A$43<>"",N(Fleet!$E$43)<=EOMONTH(EDATE($B$3,-1),0),OR(Fleet!$F$43="",N(Fleet!$F$43)>=EDATE($B$3,-1))),1,0))) | K44: =IF($A44="","",(SUMIFS(Trips!$H$5:$H$1004,Trips!$B$5:$B$1004,$A44,Trips!$L$5:$L$1004,EDATE($B$3,-2))+SUMIFS(Trips!$I$5:$I$1004,Trips!$B$5:$B$1004,$A44,Trips!$L$5:$L$1004,EDATE($B$3,-2))-SUMIFS(Trips!$J$5:$J$1004,Trips!$B$5:$B$1004,$A44,Trips!$L$5:$L$1004,EDATE($B$3,-2))-SUMIFS(Expenses!$E$5:$E$1004,Expenses!$B$5:$B$1004,$A44,Expenses!$G$5:$G$1004,EDATE($B$3,-2))-Fleet!$O$43*IF(AND(Fleet!$A$43<>"",N(Fleet!$E$43)<=EOMONTH(EDATE($B$3,-2),0),OR(Fleet!$F$43="",N(Fleet!$F$43)>=EDATE($B$3,-2))),1,0))) | L44: =IF($A44="","",SUMIFS(Trips!$M$5:$M$1004,Trips!$B$5:$B$1004,$A44,Trips!$L$5:$L$1004,"<="&$B$3)-SUMIFS(Expenses!$E$5:$E$1004,Expenses!$B$5:$B$1004,$A44,Expenses!$G$5:$G$1004,"<="&$B$3)-Fleet!$O$43*IF(N(Fleet!$E$43)=0,0,MAX(0,(YEAR(IF(Fleet!$F$43="",EOMONTH($B$3,0),MIN(Fleet!$F$43,EOMONTH($B$3,0))))-YEAR(Fleet!$E$43))*12+MONTH(IF(Fleet!$F$43="",EOMONTH($B$3,0),MIN(Fleet!$F$43,EOMONTH($B$3,0))))-MONTH(Fleet!$E$43)+1))) | M44: =IF($A44="","",Fleet!$H$43) | N44: =IF(OR($A44="",N(M44)=0),"",L44/M44) | O44: =IF(OR($A44="",N(C44)=0),"",IF(AND(I44<0,J44<0,K44<0),"REVIEW: 3 losing months",IF(I44<Assumptions!$B$9,"Below net target",IF(E44<Assumptions!$B$8,"Low utilization","On track"))))
A45: =IF(Fleet!A44="","",Fleet!A44) | B45: =IF(Fleet!A44="","",Fleet!B44&" "&Fleet!C44) | C45: =IF($A45="","",IF(AND(Fleet!$A$44<>"",N(Fleet!$E$44)<=EOMONTH($B$3,0),OR(Fleet!$F$44="",N(Fleet!$F$44)>=$B$3)),1,0)) | D45: =IF($A45="","",SUMIFS(Trips!$E$5:$E$1004,Trips!$B$5:$B$1004,$A45,Trips!$L$5:$L$1004,$B$3)) | E45: =IF(OR($A45="",N(C45)=0),"",D45/DAY(EOMONTH($B$3,0))) | F45: =IF($A45="","",SUMIFS(Trips!$H$5:$H$1004,Trips!$B$5:$B$1004,$A45,Trips!$L$5:$L$1004,$B$3)+SUMIFS(Trips!$I$5:$I$1004,Trips!$B$5:$B$1004,$A45,Trips!$L$5:$L$1004,$B$3)) | G45: =IF($A45="","",SUMIFS(Trips!$J$5:$J$1004,Trips!$B$5:$B$1004,$A45,Trips!$L$5:$L$1004,$B$3)+SUMIFS(Expenses!$E$5:$E$1004,Expenses!$B$5:$B$1004,$A45,Expenses!$G$5:$G$1004,$B$3)) | H45: =IF($A45="","",Fleet!$O$44*C45) | I45: =IF($A45="","",F45-G45-H45) | J45: =IF($A45="","",(SUMIFS(Trips!$H$5:$H$1004,Trips!$B$5:$B$1004,$A45,Trips!$L$5:$L$1004,EDATE($B$3,-1))+SUMIFS(Trips!$I$5:$I$1004,Trips!$B$5:$B$1004,$A45,Trips!$L$5:$L$1004,EDATE($B$3,-1))-SUMIFS(Trips!$J$5:$J$1004,Trips!$B$5:$B$1004,$A45,Trips!$L$5:$L$1004,EDATE($B$3,-1))-SUMIFS(Expenses!$E$5:$E$1004,Expenses!$B$5:$B$1004,$A45,Expenses!$G$5:$G$1004,EDATE($B$3,-1))-Fleet!$O$44*IF(AND(Fleet!$A$44<>"",N(Fleet!$E$44)<=EOMONTH(EDATE($B$3,-1),0),OR(Fleet!$F$44="",N(Fleet!$F$44)>=EDATE($B$3,-1))),1,0))) | K45: =IF($A45="","",(SUMIFS(Trips!$H$5:$H$1004,Trips!$B$5:$B$1004,$A45,Trips!$L$5:$L$1004,EDATE($B$3,-2))+SUMIFS(Trips!$I$5:$I$1004,Trips!$B$5:$B$1004,$A45,Trips!$L$5:$L$1004,EDATE($B$3,-2))-SUMIFS(Trips!$J$5:$J$1004,Trips!$B$5:$B$1004,$A45,Trips!$L$5:$L$1004,EDATE($B$3,-2))-SUMIFS(Expenses!$E$5:$E$1004,Expenses!$B$5:$B$1004,$A45,Expenses!$G$5:$G$1004,EDATE($B$3,-2))-Fleet!$O$44*IF(AND(Fleet!$A$44<>"",N(Fleet!$E$44)<=EOMONTH(EDATE($B$3,-2),0),OR(Fleet!$F$44="",N(Fleet!$F$44)>=EDATE($B$3,-2))),1,0))) | L45: =IF($A45="","",SUMIFS(Trips!$M$5:$M$1004,Trips!$B$5:$B$1004,$A45,Trips!$L$5:$L$1004,"<="&$B$3)-SUMIFS(Expenses!$E$5:$E$1004,Expenses!$B$5:$B$1004,$A45,Expenses!$G$5:$G$1004,"<="&$B$3)-Fleet!$O$44*IF(N(Fleet!$E$44)=0,0,MAX(0,(YEAR(IF(Fleet!$F$44="",EOMONTH($B$3,0),MIN(Fleet!$F$44,EOMONTH($B$3,0))))-YEAR(Fleet!$E$44))*12+MONTH(IF(Fleet!$F$44="",EOMONTH($B$3,0),MIN(Fleet!$F$44,EOMONTH($B$3,0))))-MONTH(Fleet!$E$44)+1))) | M45: =IF($A45="","",Fleet!$H$44) | N45: =IF(OR($A45="",N(M45)=0),"",L45/M45) | O45: =IF(OR($A45="",N(C45)=0),"",IF(AND(I45<0,J45<0,K45<0),"REVIEW: 3 losing months",IF(I45<Assumptions!$B$9,"Below net target",IF(E45<Assumptions!$B$8,"Low utilization","On track"))))
A46: =IF(Fleet!A45="","",Fleet!A45) | B46: =IF(Fleet!A45="","",Fleet!B45&" "&Fleet!C45) | C46: =IF($A46="","",IF(AND(Fleet!$A$45<>"",N(Fleet!$E$45)<=EOMONTH($B$3,0),OR(Fleet!$F$45="",N(Fleet!$F$45)>=$B$3)),1,0)) | D46: =IF($A46="","",SUMIFS(Trips!$E$5:$E$1004,Trips!$B$5:$B$1004,$A46,Trips!$L$5:$L$1004,$B$3)) | E46: =IF(OR($A46="",N(C46)=0),"",D46/DAY(EOMONTH($B$3,0))) | F46: =IF($A46="","",SUMIFS(Trips!$H$5:$H$1004,Trips!$B$5:$B$1004,$A46,Trips!$L$5:$L$1004,$B$3)+SUMIFS(Trips!$I$5:$I$1004,Trips!$B$5:$B$1004,$A46,Trips!$L$5:$L$1004,$B$3)) | G46: =IF($A46="","",SUMIFS(Trips!$J$5:$J$1004,Trips!$B$5:$B$1004,$A46,Trips!$L$5:$L$1004,$B$3)+SUMIFS(Expenses!$E$5:$E$1004,Expenses!$B$5:$B$1004,$A46,Expenses!$G$5:$G$1004,$B$3)) | H46: =IF($A46="","",Fleet!$O$45*C46) | I46: =IF($A46="","",F46-G46-H46) | J46: =IF($A46="","",(SUMIFS(Trips!$H$5:$H$1004,Trips!$B$5:$B$1004,$A46,Trips!$L$5:$L$1004,EDATE($B$3,-1))+SUMIFS(Trips!$I$5:$I$1004,Trips!$B$5:$B$1004,$A46,Trips!$L$5:$L$1004,EDATE($B$3,-1))-SUMIFS(Trips!$J$5:$J$1004,Trips!$B$5:$B$1004,$A46,Trips!$L$5:$L$1004,EDATE($B$3,-1))-SUMIFS(Expenses!$E$5:$E$1004,Expenses!$B$5:$B$1004,$A46,Expenses!$G$5:$G$1004,EDATE($B$3,-1))-Fleet!$O$45*IF(AND(Fleet!$A$45<>"",N(Fleet!$E$45)<=EOMONTH(EDATE($B$3,-1),0),OR(Fleet!$F$45="",N(Fleet!$F$45)>=EDATE($B$3,-1))),1,0))) | K46: =IF($A46="","",(SUMIFS(Trips!$H$5:$H$1004,Trips!$B$5:$B$1004,$A46,Trips!$L$5:$L$1004,EDATE($B$3,-2))+SUMIFS(Trips!$I$5:$I$1004,Trips!$B$5:$B$1004,$A46,Trips!$L$5:$L$1004,EDATE($B$3,-2))-SUMIFS(Trips!$J$5:$J$1004,Trips!$B$5:$B$1004,$A46,Trips!$L$5:$L$1004,EDATE($B$3,-2))-SUMIFS(Expenses!$E$5:$E$1004,Expenses!$B$5:$B$1004,$A46,Expenses!$G$5:$G$1004,EDATE($B$3,-2))-Fleet!$O$45*IF(AND(Fleet!$A$45<>"",N(Fleet!$E$45)<=EOMONTH(EDATE($B$3,-2),0),OR(Fleet!$F$45="",N(Fleet!$F$45)>=EDATE($B$3,-2))),1,0))) | L46: =IF($A46="","",SUMIFS(Trips!$M$5:$M$1004,Trips!$B$5:$B$1004,$A46,Trips!$L$5:$L$1004,"<="&$B$3)-SUMIFS(Expenses!$E$5:$E$1004,Expenses!$B$5:$B$1004,$A46,Expenses!$G$5:$G$1004,"<="&$B$3)-Fleet!$O$45*IF(N(Fleet!$E$45)=0,0,MAX(0,(YEAR(IF(Fleet!$F$45="",EOMONTH($B$3,0),MIN(Fleet!$F$45,EOMONTH($B$3,0))))-YEAR(Fleet!$E$45))*12+MONTH(IF(Fleet!$F$45="",EOMONTH($B$3,0),MIN(Fleet!$F$45,EOMONTH($B$3,0))))-MONTH(Fleet!$E$45)+1))) | M46: =IF($A46="","",Fleet!$H$45) | N46: =IF(OR($A46="",N(M46)=0),"",L46/M46) | O46: =IF(OR($A46="",N(C46)=0),"",IF(AND(I46<0,J46<0,K46<0),"REVIEW: 3 losing months",IF(I46<Assumptions!$B$9,"Below net target",IF(E46<Assumptions!$B$8,"Low utilization","On track"))))
A47: =IF(Fleet!A46="","",Fleet!A46) | B47: =IF(Fleet!A46="","",Fleet!B46&" "&Fleet!C46) | C47: =IF($A47="","",IF(AND(Fleet!$A$46<>"",N(Fleet!$E$46)<=EOMONTH($B$3,0),OR(Fleet!$F$46="",N(Fleet!$F$46)>=$B$3)),1,0)) | D47: =IF($A47="","",SUMIFS(Trips!$E$5:$E$1004,Trips!$B$5:$B$1004,$A47,Trips!$L$5:$L$1004,$B$3)) | E47: =IF(OR($A47="",N(C47)=0),"",D47/DAY(EOMONTH($B$3,0))) | F47: =IF($A47="","",SUMIFS(Trips!$H$5:$H$1004,Trips!$B$5:$B$1004,$A47,Trips!$L$5:$L$1004,$B$3)+SUMIFS(Trips!$I$5:$I$1004,Trips!$B$5:$B$1004,$A47,Trips!$L$5:$L$1004,$B$3)) | G47: =IF($A47="","",SUMIFS(Trips!$J$5:$J$1004,Trips!$B$5:$B$1004,$A47,Trips!$L$5:$L$1004,$B$3)+SUMIFS(Expenses!$E$5:$E$1004,Expenses!$B$5:$B$1004,$A47,Expenses!$G$5:$G$1004,$B$3)) | H47: =IF($A47="","",Fleet!$O$46*C47) | I47: =IF($A47="","",F47-G47-H47) | J47: =IF($A47="","",(SUMIFS(Trips!$H$5:$H$1004,Trips!$B$5:$B$1004,$A47,Trips!$L$5:$L$1004,EDATE($B$3,-1))+SUMIFS(Trips!$I$5:$I$1004,Trips!$B$5:$B$1004,$A47,Trips!$L$5:$L$1004,EDATE($B$3,-1))-SUMIFS(Trips!$J$5:$J$1004,Trips!$B$5:$B$1004,$A47,Trips!$L$5:$L$1004,EDATE($B$3,-1))-SUMIFS(Expenses!$E$5:$E$1004,Expenses!$B$5:$B$1004,$A47,Expenses!$G$5:$G$1004,EDATE($B$3,-1))-Fleet!$O$46*IF(AND(Fleet!$A$46<>"",N(Fleet!$E$46)<=EOMONTH(EDATE($B$3,-1),0),OR(Fleet!$F$46="",N(Fleet!$F$46)>=EDATE($B$3,-1))),1,0))) | K47: =IF($A47="","",(SUMIFS(Trips!$H$5:$H$1004,Trips!$B$5:$B$1004,$A47,Trips!$L$5:$L$1004,EDATE($B$3,-2))+SUMIFS(Trips!$I$5:$I$1004,Trips!$B$5:$B$1004,$A47,Trips!$L$5:$L$1004,EDATE($B$3,-2))-SUMIFS(Trips!$J$5:$J$1004,Trips!$B$5:$B$1004,$A47,Trips!$L$5:$L$1004,EDATE($B$3,-2))-SUMIFS(Expenses!$E$5:$E$1004,Expenses!$B$5:$B$1004,$A47,Expenses!$G$5:$G$1004,EDATE($B$3,-2))-Fleet!$O$46*IF(AND(Fleet!$A$46<>"",N(Fleet!$E$46)<=EOMONTH(EDATE($B$3,-2),0),OR(Fleet!$F$46="",N(Fleet!$F$46)>=EDATE($B$3,-2))),1,0))) | L47: =IF($A47="","",SUMIFS(Trips!$M$5:$M$1004,Trips!$B$5:$B$1004,$A47,Trips!$L$5:$L$1004,"<="&$B$3)-SUMIFS(Expenses!$E$5:$E$1004,Expenses!$B$5:$B$1004,$A47,Expenses!$G$5:$G$1004,"<="&$B$3)-Fleet!$O$46*IF(N(Fleet!$E$46)=0,0,MAX(0,(YEAR(IF(Fleet!$F$46="",EOMONTH($B$3,0),MIN(Fleet!$F$46,EOMONTH($B$3,0))))-YEAR(Fleet!$E$46))*12+MONTH(IF(Fleet!$F$46="",EOMONTH($B$3,0),MIN(Fleet!$F$46,EOMONTH($B$3,0))))-MONTH(Fleet!$E$46)+1))) | M47: =IF($A47="","",Fleet!$H$46) | N47: =IF(OR($A47="",N(M47)=0),"",L47/M47) | O47: =IF(OR($A47="",N(C47)=0),"",IF(AND(I47<0,J47<0,K47<0),"REVIEW: 3 losing months",IF(I47<Assumptions!$B$9,"Below net target",IF(E47<Assumptions!$B$8,"Low utilization","On track"))))
A48: =IF(Fleet!A47="","",Fleet!A47) | B48: =IF(Fleet!A47="","",Fleet!B47&" "&Fleet!C47) | C48: =IF($A48="","",IF(AND(Fleet!$A$47<>"",N(Fleet!$E$47)<=EOMONTH($B$3,0),OR(Fleet!$F$47="",N(Fleet!$F$47)>=$B$3)),1,0)) | D48: =IF($A48="","",SUMIFS(Trips!$E$5:$E$1004,Trips!$B$5:$B$1004,$A48,Trips!$L$5:$L$1004,$B$3)) | E48: =IF(OR($A48="",N(C48)=0),"",D48/DAY(EOMONTH($B$3,0))) | F48: =IF($A48="","",SUMIFS(Trips!$H$5:$H$1004,Trips!$B$5:$B$1004,$A48,Trips!$L$5:$L$1004,$B$3)+SUMIFS(Trips!$I$5:$I$1004,Trips!$B$5:$B$1004,$A48,Trips!$L$5:$L$1004,$B$3)) | G48: =IF($A48="","",SUMIFS(Trips!$J$5:$J$1004,Trips!$B$5:$B$1004,$A48,Trips!$L$5:$L$1004,$B$3)+SUMIFS(Expenses!$E$5:$E$1004,Expenses!$B$5:$B$1004,$A48,Expenses!$G$5:$G$1004,$B$3)) | H48: =IF($A48="","",Fleet!$O$47*C48) | I48: =IF($A48="","",F48-G48-H48) | J48: =IF($A48="","",(SUMIFS(Trips!$H$5:$H$1004,Trips!$B$5:$B$1004,$A48,Trips!$L$5:$L$1004,EDATE($B$3,-1))+SUMIFS(Trips!$I$5:$I$1004,Trips!$B$5:$B$1004,$A48,Trips!$L$5:$L$1004,EDATE($B$3,-1))-SUMIFS(Trips!$J$5:$J$1004,Trips!$B$5:$B$1004,$A48,Trips!$L$5:$L$1004,EDATE($B$3,-1))-SUMIFS(Expenses!$E$5:$E$1004,Expenses!$B$5:$B$1004,$A48,Expenses!$G$5:$G$1004,EDATE($B$3,-1))-Fleet!$O$47*IF(AND(Fleet!$A$47<>"",N(Fleet!$E$47)<=EOMONTH(EDATE($B$3,-1),0),OR(Fleet!$F$47="",N(Fleet!$F$47)>=EDATE($B$3,-1))),1,0))) | K48: =IF($A48="","",(SUMIFS(Trips!$H$5:$H$1004,Trips!$B$5:$B$1004,$A48,Trips!$L$5:$L$1004,EDATE($B$3,-2))+SUMIFS(Trips!$I$5:$I$1004,Trips!$B$5:$B$1004,$A48,Trips!$L$5:$L$1004,EDATE($B$3,-2))-SUMIFS(Trips!$J$5:$J$1004,Trips!$B$5:$B$1004,$A48,Trips!$L$5:$L$1004,EDATE($B$3,-2))-SUMIFS(Expenses!$E$5:$E$1004,Expenses!$B$5:$B$1004,$A48,Expenses!$G$5:$G$1004,EDATE($B$3,-2))-Fleet!$O$47*IF(AND(Fleet!$A$47<>"",N(Fleet!$E$47)<=EOMONTH(EDATE($B$3,-2),0),OR(Fleet!$F$47="",N(Fleet!$F$47)>=EDATE($B$3,-2))),1,0))) | L48: =IF($A48="","",SUMIFS(Trips!$M$5:$M$1004,Trips!$B$5:$B$1004,$A48,Trips!$L$5:$L$1004,"<="&$B$3)-SUMIFS(Expenses!$E$5:$E$1004,Expenses!$B$5:$B$1004,$A48,Expenses!$G$5:$G$1004,"<="&$B$3)-Fleet!$O$47*IF(N(Fleet!$E$47)=0,0,MAX(0,(YEAR(IF(Fleet!$F$47="",EOMONTH($B$3,0),MIN(Fleet!$F$47,EOMONTH($B$3,0))))-YEAR(Fleet!$E$47))*12+MONTH(IF(Fleet!$F$47="",EOMONTH($B$3,0),MIN(Fleet!$F$47,EOMONTH($B$3,0))))-MONTH(Fleet!$E$47)+1))) | M48: =IF($A48="","",Fleet!$H$47) | N48: =IF(OR($A48="",N(M48)=0),"",L48/M48) | O48: =IF(OR($A48="",N(C48)=0),"",IF(AND(I48<0,J48<0,K48<0),"REVIEW: 3 losing months",IF(I48<Assumptions!$B$9,"Below net target",IF(E48<Assumptions!$B$8,"Low utilization","On track"))))
A49: =IF(Fleet!A48="","",Fleet!A48) | B49: =IF(Fleet!A48="","",Fleet!B48&" "&Fleet!C48) | C49: =IF($A49="","",IF(AND(Fleet!$A$48<>"",N(Fleet!$E$48)<=EOMONTH($B$3,0),OR(Fleet!$F$48="",N(Fleet!$F$48)>=$B$3)),1,0)) | D49: =IF($A49="","",SUMIFS(Trips!$E$5:$E$1004,Trips!$B$5:$B$1004,$A49,Trips!$L$5:$L$1004,$B$3)) | E49: =IF(OR($A49="",N(C49)=0),"",D49/DAY(EOMONTH($B$3,0))) | F49: =IF($A49="","",SUMIFS(Trips!$H$5:$H$1004,Trips!$B$5:$B$1004,$A49,Trips!$L$5:$L$1004,$B$3)+SUMIFS(Trips!$I$5:$I$1004,Trips!$B$5:$B$1004,$A49,Trips!$L$5:$L$1004,$B$3)) | G49: =IF($A49="","",SUMIFS(Trips!$J$5:$J$1004,Trips!$B$5:$B$1004,$A49,Trips!$L$5:$L$1004,$B$3)+SUMIFS(Expenses!$E$5:$E$1004,Expenses!$B$5:$B$1004,$A49,Expenses!$G$5:$G$1004,$B$3)) | H49: =IF($A49="","",Fleet!$O$48*C49) | I49: =IF($A49="","",F49-G49-H49) | J49: =IF($A49="","",(SUMIFS(Trips!$H$5:$H$1004,Trips!$B$5:$B$1004,$A49,Trips!$L$5:$L$1004,EDATE($B$3,-1))+SUMIFS(Trips!$I$5:$I$1004,Trips!$B$5:$B$1004,$A49,Trips!$L$5:$L$1004,EDATE($B$3,-1))-SUMIFS(Trips!$J$5:$J$1004,Trips!$B$5:$B$1004,$A49,Trips!$L$5:$L$1004,EDATE($B$3,-1))-SUMIFS(Expenses!$E$5:$E$1004,Expenses!$B$5:$B$1004,$A49,Expenses!$G$5:$G$1004,EDATE($B$3,-1))-Fleet!$O$48*IF(AND(Fleet!$A$48<>"",N(Fleet!$E$48)<=EOMONTH(EDATE($B$3,-1),0),OR(Fleet!$F$48="",N(Fleet!$F$48)>=EDATE($B$3,-1))),1,0))) | K49: =IF($A49="","",(SUMIFS(Trips!$H$5:$H$1004,Trips!$B$5:$B$1004,$A49,Trips!$L$5:$L$1004,EDATE($B$3,-2))+SUMIFS(Trips!$I$5:$I$1004,Trips!$B$5:$B$1004,$A49,Trips!$L$5:$L$1004,EDATE($B$3,-2))-SUMIFS(Trips!$J$5:$J$1004,Trips!$B$5:$B$1004,$A49,Trips!$L$5:$L$1004,EDATE($B$3,-2))-SUMIFS(Expenses!$E$5:$E$1004,Expenses!$B$5:$B$1004,$A49,Expenses!$G$5:$G$1004,EDATE($B$3,-2))-Fleet!$O$48*IF(AND(Fleet!$A$48<>"",N(Fleet!$E$48)<=EOMONTH(EDATE($B$3,-2),0),OR(Fleet!$F$48="",N(Fleet!$F$48)>=EDATE($B$3,-2))),1,0))) | L49: =IF($A49="","",SUMIFS(Trips!$M$5:$M$1004,Trips!$B$5:$B$1004,$A49,Trips!$L$5:$L$1004,"<="&$B$3)-SUMIFS(Expenses!$E$5:$E$1004,Expenses!$B$5:$B$1004,$A49,Expenses!$G$5:$G$1004,"<="&$B$3)-Fleet!$O$48*IF(N(Fleet!$E$48)=0,0,MAX(0,(YEAR(IF(Fleet!$F$48="",EOMONTH($B$3,0),MIN(Fleet!$F$48,EOMONTH($B$3,0))))-YEAR(Fleet!$E$48))*12+MONTH(IF(Fleet!$F$48="",EOMONTH($B$3,0),MIN(Fleet!$F$48,EOMONTH($B$3,0))))-MONTH(Fleet!$E$48)+1))) | M49: =IF($A49="","",Fleet!$H$48) | N49: =IF(OR($A49="",N(M49)=0),"",L49/M49) | O49: =IF(OR($A49="",N(C49)=0),"",IF(AND(I49<0,J49<0,K49<0),"REVIEW: 3 losing months",IF(I49<Assumptions!$B$9,"Below net target",IF(E49<Assumptions!$B$8,"Low utilization","On track"))))
A50: =IF(Fleet!A49="","",Fleet!A49) | B50: =IF(Fleet!A49="","",Fleet!B49&" "&Fleet!C49) | C50: =IF($A50="","",IF(AND(Fleet!$A$49<>"",N(Fleet!$E$49)<=EOMONTH($B$3,0),OR(Fleet!$F$49="",N(Fleet!$F$49)>=$B$3)),1,0)) | D50: =IF($A50="","",SUMIFS(Trips!$E$5:$E$1004,Trips!$B$5:$B$1004,$A50,Trips!$L$5:$L$1004,$B$3)) | E50: =IF(OR($A50="",N(C50)=0),"",D50/DAY(EOMONTH($B$3,0))) | F50: =IF($A50="","",SUMIFS(Trips!$H$5:$H$1004,Trips!$B$5:$B$1004,$A50,Trips!$L$5:$L$1004,$B$3)+SUMIFS(Trips!$I$5:$I$1004,Trips!$B$5:$B$1004,$A50,Trips!$L$5:$L$1004,$B$3)) | G50: =IF($A50="","",SUMIFS(Trips!$J$5:$J$1004,Trips!$B$5:$B$1004,$A50,Trips!$L$5:$L$1004,$B$3)+SUMIFS(Expenses!$E$5:$E$1004,Expenses!$B$5:$B$1004,$A50,Expenses!$G$5:$G$1004,$B$3)) | H50: =IF($A50="","",Fleet!$O$49*C50) | I50: =IF($A50="","",F50-G50-H50) | J50: =IF($A50="","",(SUMIFS(Trips!$H$5:$H$1004,Trips!$B$5:$B$1004,$A50,Trips!$L$5:$L$1004,EDATE($B$3,-1))+SUMIFS(Trips!$I$5:$I$1004,Trips!$B$5:$B$1004,$A50,Trips!$L$5:$L$1004,EDATE($B$3,-1))-SUMIFS(Trips!$J$5:$J$1004,Trips!$B$5:$B$1004,$A50,Trips!$L$5:$L$1004,EDATE($B$3,-1))-SUMIFS(Expenses!$E$5:$E$1004,Expenses!$B$5:$B$1004,$A50,Expenses!$G$5:$G$1004,EDATE($B$3,-1))-Fleet!$O$49*IF(AND(Fleet!$A$49<>"",N(Fleet!$E$49)<=EOMONTH(EDATE($B$3,-1),0),OR(Fleet!$F$49="",N(Fleet!$F$49)>=EDATE($B$3,-1))),1,0))) | K50: =IF($A50="","",(SUMIFS(Trips!$H$5:$H$1004,Trips!$B$5:$B$1004,$A50,Trips!$L$5:$L$1004,EDATE($B$3,-2))+SUMIFS(Trips!$I$5:$I$1004,Trips!$B$5:$B$1004,$A50,Trips!$L$5:$L$1004,EDATE($B$3,-2))-SUMIFS(Trips!$J$5:$J$1004,Trips!$B$5:$B$1004,$A50,Trips!$L$5:$L$1004,EDATE($B$3,-2))-SUMIFS(Expenses!$E$5:$E$1004,Expenses!$B$5:$B$1004,$A50,Expenses!$G$5:$G$1004,EDATE($B$3,-2))-Fleet!$O$49*IF(AND(Fleet!$A$49<>"",N(Fleet!$E$49)<=EOMONTH(EDATE($B$3,-2),0),OR(Fleet!$F$49="",N(Fleet!$F$49)>=EDATE($B$3,-2))),1,0))) | L50: =IF($A50="","",SUMIFS(Trips!$M$5:$M$1004,Trips!$B$5:$B$1004,$A50,Trips!$L$5:$L$1004,"<="&$B$3)-SUMIFS(Expenses!$E$5:$E$1004,Expenses!$B$5:$B$1004,$A50,Expenses!$G$5:$G$1004,"<="&$B$3)-Fleet!$O$49*IF(N(Fleet!$E$49)=0,0,MAX(0,(YEAR(IF(Fleet!$F$49="",EOMONTH($B$3,0),MIN(Fleet!$F$49,EOMONTH($B$3,0))))-YEAR(Fleet!$E$49))*12+MONTH(IF(Fleet!$F$49="",EOMONTH($B$3,0),MIN(Fleet!$F$49,EOMONTH($B$3,0))))-MONTH(Fleet!$E$49)+1))) | M50: =IF($A50="","",Fleet!$H$49) | N50: =IF(OR($A50="",N(M50)=0),"",L50/M50) | O50: =IF(OR($A50="",N(C50)=0),"",IF(AND(I50<0,J50<0,K50<0),"REVIEW: 3 losing months",IF(I50<Assumptions!$B$9,"Below net target",IF(E50<Assumptions!$B$8,"Low utilization","On track"))))
A51: =IF(Fleet!A50="","",Fleet!A50) | B51: =IF(Fleet!A50="","",Fleet!B50&" "&Fleet!C50) | C51: =IF($A51="","",IF(AND(Fleet!$A$50<>"",N(Fleet!$E$50)<=EOMONTH($B$3,0),OR(Fleet!$F$50="",N(Fleet!$F$50)>=$B$3)),1,0)) | D51: =IF($A51="","",SUMIFS(Trips!$E$5:$E$1004,Trips!$B$5:$B$1004,$A51,Trips!$L$5:$L$1004,$B$3)) | E51: =IF(OR($A51="",N(C51)=0),"",D51/DAY(EOMONTH($B$3,0))) | F51: =IF($A51="","",SUMIFS(Trips!$H$5:$H$1004,Trips!$B$5:$B$1004,$A51,Trips!$L$5:$L$1004,$B$3)+SUMIFS(Trips!$I$5:$I$1004,Trips!$B$5:$B$1004,$A51,Trips!$L$5:$L$1004,$B$3)) | G51: =IF($A51="","",SUMIFS(Trips!$J$5:$J$1004,Trips!$B$5:$B$1004,$A51,Trips!$L$5:$L$1004,$B$3)+SUMIFS(Expenses!$E$5:$E$1004,Expenses!$B$5:$B$1004,$A51,Expenses!$G$5:$G$1004,$B$3)) | H51: =IF($A51="","",Fleet!$O$50*C51) | I51: =IF($A51="","",F51-G51-H51) | J51: =IF($A51="","",(SUMIFS(Trips!$H$5:$H$1004,Trips!$B$5:$B$1004,$A51,Trips!$L$5:$L$1004,EDATE($B$3,-1))+SUMIFS(Trips!$I$5:$I$1004,Trips!$B$5:$B$1004,$A51,Trips!$L$5:$L$1004,EDATE($B$3,-1))-SUMIFS(Trips!$J$5:$J$1004,Trips!$B$5:$B$1004,$A51,Trips!$L$5:$L$1004,EDATE($B$3,-1))-SUMIFS(Expenses!$E$5:$E$1004,Expenses!$B$5:$B$1004,$A51,Expenses!$G$5:$G$1004,EDATE($B$3,-1))-Fleet!$O$50*IF(AND(Fleet!$A$50<>"",N(Fleet!$E$50)<=EOMONTH(EDATE($B$3,-1),0),OR(Fleet!$F$50="",N(Fleet!$F$50)>=EDATE($B$3,-1))),1,0))) | K51: =IF($A51="","",(SUMIFS(Trips!$H$5:$H$1004,Trips!$B$5:$B$1004,$A51,Trips!$L$5:$L$1004,EDATE($B$3,-2))+SUMIFS(Trips!$I$5:$I$1004,Trips!$B$5:$B$1004,$A51,Trips!$L$5:$L$1004,EDATE($B$3,-2))-SUMIFS(Trips!$J$5:$J$1004,Trips!$B$5:$B$1004,$A51,Trips!$L$5:$L$1004,EDATE($B$3,-2))-SUMIFS(Expenses!$E$5:$E$1004,Expenses!$B$5:$B$1004,$A51,Expenses!$G$5:$G$1004,EDATE($B$3,-2))-Fleet!$O$50*IF(AND(Fleet!$A$50<>"",N(Fleet!$E$50)<=EOMONTH(EDATE($B$3,-2),0),OR(Fleet!$F$50="",N(Fleet!$F$50)>=EDATE($B$3,-2))),1,0))) | L51: =IF($A51="","",SUMIFS(Trips!$M$5:$M$1004,Trips!$B$5:$B$1004,$A51,Trips!$L$5:$L$1004,"<="&$B$3)-SUMIFS(Expenses!$E$5:$E$1004,Expenses!$B$5:$B$1004,$A51,Expenses!$G$5:$G$1004,"<="&$B$3)-Fleet!$O$50*IF(N(Fleet!$E$50)=0,0,MAX(0,(YEAR(IF(Fleet!$F$50="",EOMONTH($B$3,0),MIN(Fleet!$F$50,EOMONTH($B$3,0))))-YEAR(Fleet!$E$50))*12+MONTH(IF(Fleet!$F$50="",EOMONTH($B$3,0),MIN(Fleet!$F$50,EOMONTH($B$3,0))))-MONTH(Fleet!$E$50)+1))) | M51: =IF($A51="","",Fleet!$H$50) | N51: =IF(OR($A51="",N(M51)=0),"",L51/M51) | O51: =IF(OR($A51="",N(C51)=0),"",IF(AND(I51<0,J51<0,K51<0),"REVIEW: 3 losing months",IF(I51<Assumptions!$B$9,"Below net target",IF(E51<Assumptions!$B$8,"Low utilization","On track"))))
A52: =IF(Fleet!A51="","",Fleet!A51) | B52: =IF(Fleet!A51="","",Fleet!B51&" "&Fleet!C51) | C52: =IF($A52="","",IF(AND(Fleet!$A$51<>"",N(Fleet!$E$51)<=EOMONTH($B$3,0),OR(Fleet!$F$51="",N(Fleet!$F$51)>=$B$3)),1,0)) | D52: =IF($A52="","",SUMIFS(Trips!$E$5:$E$1004,Trips!$B$5:$B$1004,$A52,Trips!$L$5:$L$1004,$B$3)) | E52: =IF(OR($A52="",N(C52)=0),"",D52/DAY(EOMONTH($B$3,0))) | F52: =IF($A52="","",SUMIFS(Trips!$H$5:$H$1004,Trips!$B$5:$B$1004,$A52,Trips!$L$5:$L$1004,$B$3)+SUMIFS(Trips!$I$5:$I$1004,Trips!$B$5:$B$1004,$A52,Trips!$L$5:$L$1004,$B$3)) | G52: =IF($A52="","",SUMIFS(Trips!$J$5:$J$1004,Trips!$B$5:$B$1004,$A52,Trips!$L$5:$L$1004,$B$3)+SUMIFS(Expenses!$E$5:$E$1004,Expenses!$B$5:$B$1004,$A52,Expenses!$G$5:$G$1004,$B$3)) | H52: =IF($A52="","",Fleet!$O$51*C52) | I52: =IF($A52="","",F52-G52-H52) | J52: =IF($A52="","",(SUMIFS(Trips!$H$5:$H$1004,Trips!$B$5:$B$1004,$A52,Trips!$L$5:$L$1004,EDATE($B$3,-1))+SUMIFS(Trips!$I$5:$I$1004,Trips!$B$5:$B$1004,$A52,Trips!$L$5:$L$1004,EDATE($B$3,-1))-SUMIFS(Trips!$J$5:$J$1004,Trips!$B$5:$B$1004,$A52,Trips!$L$5:$L$1004,EDATE($B$3,-1))-SUMIFS(Expenses!$E$5:$E$1004,Expenses!$B$5:$B$1004,$A52,Expenses!$G$5:$G$1004,EDATE($B$3,-1))-Fleet!$O$51*IF(AND(Fleet!$A$51<>"",N(Fleet!$E$51)<=EOMONTH(EDATE($B$3,-1),0),OR(Fleet!$F$51="",N(Fleet!$F$51)>=EDATE($B$3,-1))),1,0))) | K52: =IF($A52="","",(SUMIFS(Trips!$H$5:$H$1004,Trips!$B$5:$B$1004,$A52,Trips!$L$5:$L$1004,EDATE($B$3,-2))+SUMIFS(Trips!$I$5:$I$1004,Trips!$B$5:$B$1004,$A52,Trips!$L$5:$L$1004,EDATE($B$3,-2))-SUMIFS(Trips!$J$5:$J$1004,Trips!$B$5:$B$1004,$A52,Trips!$L$5:$L$1004,EDATE($B$3,-2))-SUMIFS(Expenses!$E$5:$E$1004,Expenses!$B$5:$B$1004,$A52,Expenses!$G$5:$G$1004,EDATE($B$3,-2))-Fleet!$O$51*IF(AND(Fleet!$A$51<>"",N(Fleet!$E$51)<=EOMONTH(EDATE($B$3,-2),0),OR(Fleet!$F$51="",N(Fleet!$F$51)>=EDATE($B$3,-2))),1,0))) | L52: =IF($A52="","",SUMIFS(Trips!$M$5:$M$1004,Trips!$B$5:$B$1004,$A52,Trips!$L$5:$L$1004,"<="&$B$3)-SUMIFS(Expenses!$E$5:$E$1004,Expenses!$B$5:$B$1004,$A52,Expenses!$G$5:$G$1004,"<="&$B$3)-Fleet!$O$51*IF(N(Fleet!$E$51)=0,0,MAX(0,(YEAR(IF(Fleet!$F$51="",EOMONTH($B$3,0),MIN(Fleet!$F$51,EOMONTH($B$3,0))))-YEAR(Fleet!$E$51))*12+MONTH(IF(Fleet!$F$51="",EOMONTH($B$3,0),MIN(Fleet!$F$51,EOMONTH($B$3,0))))-MONTH(Fleet!$E$51)+1))) | M52: =IF($A52="","",Fleet!$H$51) | N52: =IF(OR($A52="",N(M52)=0),"",L52/M52) | O52: =IF(OR($A52="",N(C52)=0),"",IF(AND(I52<0,J52<0,K52<0),"REVIEW: 3 losing months",IF(I52<Assumptions!$B$9,"Below net target",IF(E52<Assumptions!$B$8,"Low utilization","On track"))))
A53: =IF(Fleet!A52="","",Fleet!A52) | B53: =IF(Fleet!A52="","",Fleet!B52&" "&Fleet!C52) | C53: =IF($A53="","",IF(AND(Fleet!$A$52<>"",N(Fleet!$E$52)<=EOMONTH($B$3,0),OR(Fleet!$F$52="",N(Fleet!$F$52)>=$B$3)),1,0)) | D53: =IF($A53="","",SUMIFS(Trips!$E$5:$E$1004,Trips!$B$5:$B$1004,$A53,Trips!$L$5:$L$1004,$B$3)) | E53: =IF(OR($A53="",N(C53)=0),"",D53/DAY(EOMONTH($B$3,0))) | F53: =IF($A53="","",SUMIFS(Trips!$H$5:$H$1004,Trips!$B$5:$B$1004,$A53,Trips!$L$5:$L$1004,$B$3)+SUMIFS(Trips!$I$5:$I$1004,Trips!$B$5:$B$1004,$A53,Trips!$L$5:$L$1004,$B$3)) | G53: =IF($A53="","",SUMIFS(Trips!$J$5:$J$1004,Trips!$B$5:$B$1004,$A53,Trips!$L$5:$L$1004,$B$3)+SUMIFS(Expenses!$E$5:$E$1004,Expenses!$B$5:$B$1004,$A53,Expenses!$G$5:$G$1004,$B$3)) | H53: =IF($A53="","",Fleet!$O$52*C53) | I53: =IF($A53="","",F53-G53-H53) | J53: =IF($A53="","",(SUMIFS(Trips!$H$5:$H$1004,Trips!$B$5:$B$1004,$A53,Trips!$L$5:$L$1004,EDATE($B$3,-1))+SUMIFS(Trips!$I$5:$I$1004,Trips!$B$5:$B$1004,$A53,Trips!$L$5:$L$1004,EDATE($B$3,-1))-SUMIFS(Trips!$J$5:$J$1004,Trips!$B$5:$B$1004,$A53,Trips!$L$5:$L$1004,EDATE($B$3,-1))-SUMIFS(Expenses!$E$5:$E$1004,Expenses!$B$5:$B$1004,$A53,Expenses!$G$5:$G$1004,EDATE($B$3,-1))-Fleet!$O$52*IF(AND(Fleet!$A$52<>"",N(Fleet!$E$52)<=EOMONTH(EDATE($B$3,-1),0),OR(Fleet!$F$52="",N(Fleet!$F$52)>=EDATE($B$3,-1))),1,0))) | K53: =IF($A53="","",(SUMIFS(Trips!$H$5:$H$1004,Trips!$B$5:$B$1004,$A53,Trips!$L$5:$L$1004,EDATE($B$3,-2))+SUMIFS(Trips!$I$5:$I$1004,Trips!$B$5:$B$1004,$A53,Trips!$L$5:$L$1004,EDATE($B$3,-2))-SUMIFS(Trips!$J$5:$J$1004,Trips!$B$5:$B$1004,$A53,Trips!$L$5:$L$1004,EDATE($B$3,-2))-SUMIFS(Expenses!$E$5:$E$1004,Expenses!$B$5:$B$1004,$A53,Expenses!$G$5:$G$1004,EDATE($B$3,-2))-Fleet!$O$52*IF(AND(Fleet!$A$52<>"",N(Fleet!$E$52)<=EOMONTH(EDATE($B$3,-2),0),OR(Fleet!$F$52="",N(Fleet!$F$52)>=EDATE($B$3,-2))),1,0))) | L53: =IF($A53="","",SUMIFS(Trips!$M$5:$M$1004,Trips!$B$5:$B$1004,$A53,Trips!$L$5:$L$1004,"<="&$B$3)-SUMIFS(Expenses!$E$5:$E$1004,Expenses!$B$5:$B$1004,$A53,Expenses!$G$5:$G$1004,"<="&$B$3)-Fleet!$O$52*IF(N(Fleet!$E$52)=0,0,MAX(0,(YEAR(IF(Fleet!$F$52="",EOMONTH($B$3,0),MIN(Fleet!$F$52,EOMONTH($B$3,0))))-YEAR(Fleet!$E$52))*12+MONTH(IF(Fleet!$F$52="",EOMONTH($B$3,0),MIN(Fleet!$F$52,EOMONTH($B$3,0))))-MONTH(Fleet!$E$52)+1))) | M53: =IF($A53="","",Fleet!$H$52) | N53: =IF(OR($A53="",N(M53)=0),"",L53/M53) | O53: =IF(OR($A53="",N(C53)=0),"",IF(AND(I53<0,J53<0,K53<0),"REVIEW: 3 losing months",IF(I53<Assumptions!$B$9,"Below net target",IF(E53<Assumptions!$B$8,"Low utilization","On track"))))
A54: =IF(Fleet!A53="","",Fleet!A53) | B54: =IF(Fleet!A53="","",Fleet!B53&" "&Fleet!C53) | C54: =IF($A54="","",IF(AND(Fleet!$A$53<>"",N(Fleet!$E$53)<=EOMONTH($B$3,0),OR(Fleet!$F$53="",N(Fleet!$F$53)>=$B$3)),1,0)) | D54: =IF($A54="","",SUMIFS(Trips!$E$5:$E$1004,Trips!$B$5:$B$1004,$A54,Trips!$L$5:$L$1004,$B$3)) | E54: =IF(OR($A54="",N(C54)=0),"",D54/DAY(EOMONTH($B$3,0))) | F54: =IF($A54="","",SUMIFS(Trips!$H$5:$H$1004,Trips!$B$5:$B$1004,$A54,Trips!$L$5:$L$1004,$B$3)+SUMIFS(Trips!$I$5:$I$1004,Trips!$B$5:$B$1004,$A54,Trips!$L$5:$L$1004,$B$3)) | G54: =IF($A54="","",SUMIFS(Trips!$J$5:$J$1004,Trips!$B$5:$B$1004,$A54,Trips!$L$5:$L$1004,$B$3)+SUMIFS(Expenses!$E$5:$E$1004,Expenses!$B$5:$B$1004,$A54,Expenses!$G$5:$G$1004,$B$3)) | H54: =IF($A54="","",Fleet!$O$53*C54) | I54: =IF($A54="","",F54-G54-H54) | J54: =IF($A54="","",(SUMIFS(Trips!$H$5:$H$1004,Trips!$B$5:$B$1004,$A54,Trips!$L$5:$L$1004,EDATE($B$3,-1))+SUMIFS(Trips!$I$5:$I$1004,Trips!$B$5:$B$1004,$A54,Trips!$L$5:$L$1004,EDATE($B$3,-1))-SUMIFS(Trips!$J$5:$J$1004,Trips!$B$5:$B$1004,$A54,Trips!$L$5:$L$1004,EDATE($B$3,-1))-SUMIFS(Expenses!$E$5:$E$1004,Expenses!$B$5:$B$1004,$A54,Expenses!$G$5:$G$1004,EDATE($B$3,-1))-Fleet!$O$53*IF(AND(Fleet!$A$53<>"",N(Fleet!$E$53)<=EOMONTH(EDATE($B$3,-1),0),OR(Fleet!$F$53="",N(Fleet!$F$53)>=EDATE($B$3,-1))),1,0))) | K54: =IF($A54="","",(SUMIFS(Trips!$H$5:$H$1004,Trips!$B$5:$B$1004,$A54,Trips!$L$5:$L$1004,EDATE($B$3,-2))+SUMIFS(Trips!$I$5:$I$1004,Trips!$B$5:$B$1004,$A54,Trips!$L$5:$L$1004,EDATE($B$3,-2))-SUMIFS(Trips!$J$5:$J$1004,Trips!$B$5:$B$1004,$A54,Trips!$L$5:$L$1004,EDATE($B$3,-2))-SUMIFS(Expenses!$E$5:$E$1004,Expenses!$B$5:$B$1004,$A54,Expenses!$G$5:$G$1004,EDATE($B$3,-2))-Fleet!$O$53*IF(AND(Fleet!$A$53<>"",N(Fleet!$E$53)<=EOMONTH(EDATE($B$3,-2),0),OR(Fleet!$F$53="",N(Fleet!$F$53)>=EDATE($B$3,-2))),1,0))) | L54: =IF($A54="","",SUMIFS(Trips!$M$5:$M$1004,Trips!$B$5:$B$1004,$A54,Trips!$L$5:$L$1004,"<="&$B$3)-SUMIFS(Expenses!$E$5:$E$1004,Expenses!$B$5:$B$1004,$A54,Expenses!$G$5:$G$1004,"<="&$B$3)-Fleet!$O$53*IF(N(Fleet!$E$53)=0,0,MAX(0,(YEAR(IF(Fleet!$F$53="",EOMONTH($B$3,0),MIN(Fleet!$F$53,EOMONTH($B$3,0))))-YEAR(Fleet!$E$53))*12+MONTH(IF(Fleet!$F$53="",EOMONTH($B$3,0),MIN(Fleet!$F$53,EOMONTH($B$3,0))))-MONTH(Fleet!$E$53)+1))) | M54: =IF($A54="","",Fleet!$H$53) | N54: =IF(OR($A54="",N(M54)=0),"",L54/M54) | O54: =IF(OR($A54="",N(C54)=0),"",IF(AND(I54<0,J54<0,K54<0),"REVIEW: 3 losing months",IF(I54<Assumptions!$B$9,"Below net target",IF(E54<Assumptions!$B$8,"Low utilization","On track"))))
A55: =IF(Fleet!A54="","",Fleet!A54) | B55: =IF(Fleet!A54="","",Fleet!B54&" "&Fleet!C54) | C55: =IF($A55="","",IF(AND(Fleet!$A$54<>"",N(Fleet!$E$54)<=EOMONTH($B$3,0),OR(Fleet!$F$54="",N(Fleet!$F$54)>=$B$3)),1,0)) | D55: =IF($A55="","",SUMIFS(Trips!$E$5:$E$1004,Trips!$B$5:$B$1004,$A55,Trips!$L$5:$L$1004,$B$3)) | E55: =IF(OR($A55="",N(C55)=0),"",D55/DAY(EOMONTH($B$3,0))) | F55: =IF($A55="","",SUMIFS(Trips!$H$5:$H$1004,Trips!$B$5:$B$1004,$A55,Trips!$L$5:$L$1004,$B$3)+SUMIFS(Trips!$I$5:$I$1004,Trips!$B$5:$B$1004,$A55,Trips!$L$5:$L$1004,$B$3)) | G55: =IF($A55="","",SUMIFS(Trips!$J$5:$J$1004,Trips!$B$5:$B$1004,$A55,Trips!$L$5:$L$1004,$B$3)+SUMIFS(Expenses!$E$5:$E$1004,Expenses!$B$5:$B$1004,$A55,Expenses!$G$5:$G$1004,$B$3)) | H55: =IF($A55="","",Fleet!$O$54*C55) | I55: =IF($A55="","",F55-G55-H55) | J55: =IF($A55="","",(SUMIFS(Trips!$H$5:$H$1004,Trips!$B$5:$B$1004,$A55,Trips!$L$5:$L$1004,EDATE($B$3,-1))+SUMIFS(Trips!$I$5:$I$1004,Trips!$B$5:$B$1004,$A55,Trips!$L$5:$L$1004,EDATE($B$3,-1))-SUMIFS(Trips!$J$5:$J$1004,Trips!$B$5:$B$1004,$A55,Trips!$L$5:$L$1004,EDATE($B$3,-1))-SUMIFS(Expenses!$E$5:$E$1004,Expenses!$B$5:$B$1004,$A55,Expenses!$G$5:$G$1004,EDATE($B$3,-1))-Fleet!$O$54*IF(AND(Fleet!$A$54<>"",N(Fleet!$E$54)<=EOMONTH(EDATE($B$3,-1),0),OR(Fleet!$F$54="",N(Fleet!$F$54)>=EDATE($B$3,-1))),1,0))) | K55: =IF($A55="","",(SUMIFS(Trips!$H$5:$H$1004,Trips!$B$5:$B$1004,$A55,Trips!$L$5:$L$1004,EDATE($B$3,-2))+SUMIFS(Trips!$I$5:$I$1004,Trips!$B$5:$B$1004,$A55,Trips!$L$5:$L$1004,EDATE($B$3,-2))-SUMIFS(Trips!$J$5:$J$1004,Trips!$B$5:$B$1004,$A55,Trips!$L$5:$L$1004,EDATE($B$3,-2))-SUMIFS(Expenses!$E$5:$E$1004,Expenses!$B$5:$B$1004,$A55,Expenses!$G$5:$G$1004,EDATE($B$3,-2))-Fleet!$O$54*IF(AND(Fleet!$A$54<>"",N(Fleet!$E$54)<=EOMONTH(EDATE($B$3,-2),0),OR(Fleet!$F$54="",N(Fleet!$F$54)>=EDATE($B$3,-2))),1,0))) | L55: =IF($A55="","",SUMIFS(Trips!$M$5:$M$1004,Trips!$B$5:$B$1004,$A55,Trips!$L$5:$L$1004,"<="&$B$3)-SUMIFS(Expenses!$E$5:$E$1004,Expenses!$B$5:$B$1004,$A55,Expenses!$G$5:$G$1004,"<="&$B$3)-Fleet!$O$54*IF(N(Fleet!$E$54)=0,0,MAX(0,(YEAR(IF(Fleet!$F$54="",EOMONTH($B$3,0),MIN(Fleet!$F$54,EOMONTH($B$3,0))))-YEAR(Fleet!$E$54))*12+MONTH(IF(Fleet!$F$54="",EOMONTH($B$3,0),MIN(Fleet!$F$54,EOMONTH($B$3,0))))-MONTH(Fleet!$E$54)+1))) | M55: =IF($A55="","",Fleet!$H$54) | N55: =IF(OR($A55="",N(M55)=0),"",L55/M55) | O55: =IF(OR($A55="",N(C55)=0),"",IF(AND(I55<0,J55<0,K55<0),"REVIEW: 3 losing months",IF(I55<Assumptions!$B$9,"Below net target",IF(E55<Assumptions!$B$8,"Low utilization","On track"))))
A56: =IF(Fleet!A55="","",Fleet!A55) | B56: =IF(Fleet!A55="","",Fleet!B55&" "&Fleet!C55) | C56: =IF($A56="","",IF(AND(Fleet!$A$55<>"",N(Fleet!$E$55)<=EOMONTH($B$3,0),OR(Fleet!$F$55="",N(Fleet!$F$55)>=$B$3)),1,0)) | D56: =IF($A56="","",SUMIFS(Trips!$E$5:$E$1004,Trips!$B$5:$B$1004,$A56,Trips!$L$5:$L$1004,$B$3)) | E56: =IF(OR($A56="",N(C56)=0),"",D56/DAY(EOMONTH($B$3,0))) | F56: =IF($A56="","",SUMIFS(Trips!$H$5:$H$1004,Trips!$B$5:$B$1004,$A56,Trips!$L$5:$L$1004,$B$3)+SUMIFS(Trips!$I$5:$I$1004,Trips!$B$5:$B$1004,$A56,Trips!$L$5:$L$1004,$B$3)) | G56: =IF($A56="","",SUMIFS(Trips!$J$5:$J$1004,Trips!$B$5:$B$1004,$A56,Trips!$L$5:$L$1004,$B$3)+SUMIFS(Expenses!$E$5:$E$1004,Expenses!$B$5:$B$1004,$A56,Expenses!$G$5:$G$1004,$B$3)) | H56: =IF($A56="","",Fleet!$O$55*C56) | I56: =IF($A56="","",F56-G56-H56) | J56: =IF($A56="","",(SUMIFS(Trips!$H$5:$H$1004,Trips!$B$5:$B$1004,$A56,Trips!$L$5:$L$1004,EDATE($B$3,-1))+SUMIFS(Trips!$I$5:$I$1004,Trips!$B$5:$B$1004,$A56,Trips!$L$5:$L$1004,EDATE($B$3,-1))-SUMIFS(Trips!$J$5:$J$1004,Trips!$B$5:$B$1004,$A56,Trips!$L$5:$L$1004,EDATE($B$3,-1))-SUMIFS(Expenses!$E$5:$E$1004,Expenses!$B$5:$B$1004,$A56,Expenses!$G$5:$G$1004,EDATE($B$3,-1))-Fleet!$O$55*IF(AND(Fleet!$A$55<>"",N(Fleet!$E$55)<=EOMONTH(EDATE($B$3,-1),0),OR(Fleet!$F$55="",N(Fleet!$F$55)>=EDATE($B$3,-1))),1,0))) | K56: =IF($A56="","",(SUMIFS(Trips!$H$5:$H$1004,Trips!$B$5:$B$1004,$A56,Trips!$L$5:$L$1004,EDATE($B$3,-2))+SUMIFS(Trips!$I$5:$I$1004,Trips!$B$5:$B$1004,$A56,Trips!$L$5:$L$1004,EDATE($B$3,-2))-SUMIFS(Trips!$J$5:$J$1004,Trips!$B$5:$B$1004,$A56,Trips!$L$5:$L$1004,EDATE($B$3,-2))-SUMIFS(Expenses!$E$5:$E$1004,Expenses!$B$5:$B$1004,$A56,Expenses!$G$5:$G$1004,EDATE($B$3,-2))-Fleet!$O$55*IF(AND(Fleet!$A$55<>"",N(Fleet!$E$55)<=EOMONTH(EDATE($B$3,-2),0),OR(Fleet!$F$55="",N(Fleet!$F$55)>=EDATE($B$3,-2))),1,0))) | L56: =IF($A56="","",SUMIFS(Trips!$M$5:$M$1004,Trips!$B$5:$B$1004,$A56,Trips!$L$5:$L$1004,"<="&$B$3)-SUMIFS(Expenses!$E$5:$E$1004,Expenses!$B$5:$B$1004,$A56,Expenses!$G$5:$G$1004,"<="&$B$3)-Fleet!$O$55*IF(N(Fleet!$E$55)=0,0,MAX(0,(YEAR(IF(Fleet!$F$55="",EOMONTH($B$3,0),MIN(Fleet!$F$55,EOMONTH($B$3,0))))-YEAR(Fleet!$E$55))*12+MONTH(IF(Fleet!$F$55="",EOMONTH($B$3,0),MIN(Fleet!$F$55,EOMONTH($B$3,0))))-MONTH(Fleet!$E$55)+1))) | M56: =IF($A56="","",Fleet!$H$55) | N56: =IF(OR($A56="",N(M56)=0),"",L56/M56) | O56: =IF(OR($A56="",N(C56)=0),"",IF(AND(I56<0,J56<0,K56<0),"REVIEW: 3 losing months",IF(I56<Assumptions!$B$9,"Below net target",IF(E56<Assumptions!$B$8,"Low utilization","On track"))))
A57: =IF(Fleet!A56="","",Fleet!A56) | B57: =IF(Fleet!A56="","",Fleet!B56&" "&Fleet!C56) | C57: =IF($A57="","",IF(AND(Fleet!$A$56<>"",N(Fleet!$E$56)<=EOMONTH($B$3,0),OR(Fleet!$F$56="",N(Fleet!$F$56)>=$B$3)),1,0)) | D57: =IF($A57="","",SUMIFS(Trips!$E$5:$E$1004,Trips!$B$5:$B$1004,$A57,Trips!$L$5:$L$1004,$B$3)) | E57: =IF(OR($A57="",N(C57)=0),"",D57/DAY(EOMONTH($B$3,0))) | F57: =IF($A57="","",SUMIFS(Trips!$H$5:$H$1004,Trips!$B$5:$B$1004,$A57,Trips!$L$5:$L$1004,$B$3)+SUMIFS(Trips!$I$5:$I$1004,Trips!$B$5:$B$1004,$A57,Trips!$L$5:$L$1004,$B$3)) | G57: =IF($A57="","",SUMIFS(Trips!$J$5:$J$1004,Trips!$B$5:$B$1004,$A57,Trips!$L$5:$L$1004,$B$3)+SUMIFS(Expenses!$E$5:$E$1004,Expenses!$B$5:$B$1004,$A57,Expenses!$G$5:$G$1004,$B$3)) | H57: =IF($A57="","",Fleet!$O$56*C57) | I57: =IF($A57="","",F57-G57-H57) | J57: =IF($A57="","",(SUMIFS(Trips!$H$5:$H$1004,Trips!$B$5:$B$1004,$A57,Trips!$L$5:$L$1004,EDATE($B$3,-1))+SUMIFS(Trips!$I$5:$I$1004,Trips!$B$5:$B$1004,$A57,Trips!$L$5:$L$1004,EDATE($B$3,-1))-SUMIFS(Trips!$J$5:$J$1004,Trips!$B$5:$B$1004,$A57,Trips!$L$5:$L$1004,EDATE($B$3,-1))-SUMIFS(Expenses!$E$5:$E$1004,Expenses!$B$5:$B$1004,$A57,Expenses!$G$5:$G$1004,EDATE($B$3,-1))-Fleet!$O$56*IF(AND(Fleet!$A$56<>"",N(Fleet!$E$56)<=EOMONTH(EDATE($B$3,-1),0),OR(Fleet!$F$56="",N(Fleet!$F$56)>=EDATE($B$3,-1))),1,0))) | K57: =IF($A57="","",(SUMIFS(Trips!$H$5:$H$1004,Trips!$B$5:$B$1004,$A57,Trips!$L$5:$L$1004,EDATE($B$3,-2))+SUMIFS(Trips!$I$5:$I$1004,Trips!$B$5:$B$1004,$A57,Trips!$L$5:$L$1004,EDATE($B$3,-2))-SUMIFS(Trips!$J$5:$J$1004,Trips!$B$5:$B$1004,$A57,Trips!$L$5:$L$1004,EDATE($B$3,-2))-SUMIFS(Expenses!$E$5:$E$1004,Expenses!$B$5:$B$1004,$A57,Expenses!$G$5:$G$1004,EDATE($B$3,-2))-Fleet!$O$56*IF(AND(Fleet!$A$56<>"",N(Fleet!$E$56)<=EOMONTH(EDATE($B$3,-2),0),OR(Fleet!$F$56="",N(Fleet!$F$56)>=EDATE($B$3,-2))),1,0))) | L57: =IF($A57="","",SUMIFS(Trips!$M$5:$M$1004,Trips!$B$5:$B$1004,$A57,Trips!$L$5:$L$1004,"<="&$B$3)-SUMIFS(Expenses!$E$5:$E$1004,Expenses!$B$5:$B$1004,$A57,Expenses!$G$5:$G$1004,"<="&$B$3)-Fleet!$O$56*IF(N(Fleet!$E$56)=0,0,MAX(0,(YEAR(IF(Fleet!$F$56="",EOMONTH($B$3,0),MIN(Fleet!$F$56,EOMONTH($B$3,0))))-YEAR(Fleet!$E$56))*12+MONTH(IF(Fleet!$F$56="",EOMONTH($B$3,0),MIN(Fleet!$F$56,EOMONTH($B$3,0))))-MONTH(Fleet!$E$56)+1))) | M57: =IF($A57="","",Fleet!$H$56) | N57: =IF(OR($A57="",N(M57)=0),"",L57/M57) | O57: =IF(OR($A57="",N(C57)=0),"",IF(AND(I57<0,J57<0,K57<0),"REVIEW: 3 losing months",IF(I57<Assumptions!$B$9,"Below net target",IF(E57<Assumptions!$B$8,"Low utilization","On track"))))
A58: =IF(Fleet!A57="","",Fleet!A57) | B58: =IF(Fleet!A57="","",Fleet!B57&" "&Fleet!C57) | C58: =IF($A58="","",IF(AND(Fleet!$A$57<>"",N(Fleet!$E$57)<=EOMONTH($B$3,0),OR(Fleet!$F$57="",N(Fleet!$F$57)>=$B$3)),1,0)) | D58: =IF($A58="","",SUMIFS(Trips!$E$5:$E$1004,Trips!$B$5:$B$1004,$A58,Trips!$L$5:$L$1004,$B$3)) | E58: =IF(OR($A58="",N(C58)=0),"",D58/DAY(EOMONTH($B$3,0))) | F58: =IF($A58="","",SUMIFS(Trips!$H$5:$H$1004,Trips!$B$5:$B$1004,$A58,Trips!$L$5:$L$1004,$B$3)+SUMIFS(Trips!$I$5:$I$1004,Trips!$B$5:$B$1004,$A58,Trips!$L$5:$L$1004,$B$3)) | G58: =IF($A58="","",SUMIFS(Trips!$J$5:$J$1004,Trips!$B$5:$B$1004,$A58,Trips!$L$5:$L$1004,$B$3)+SUMIFS(Expenses!$E$5:$E$1004,Expenses!$B$5:$B$1004,$A58,Expenses!$G$5:$G$1004,$B$3)) | H58: =IF($A58="","",Fleet!$O$57*C58) | I58: =IF($A58="","",F58-G58-H58) | J58: =IF($A58="","",(SUMIFS(Trips!$H$5:$H$1004,Trips!$B$5:$B$1004,$A58,Trips!$L$5:$L$1004,EDATE($B$3,-1))+SUMIFS(Trips!$I$5:$I$1004,Trips!$B$5:$B$1004,$A58,Trips!$L$5:$L$1004,EDATE($B$3,-1))-SUMIFS(Trips!$J$5:$J$1004,Trips!$B$5:$B$1004,$A58,Trips!$L$5:$L$1004,EDATE($B$3,-1))-SUMIFS(Expenses!$E$5:$E$1004,Expenses!$B$5:$B$1004,$A58,Expenses!$G$5:$G$1004,EDATE($B$3,-1))-Fleet!$O$57*IF(AND(Fleet!$A$57<>"",N(Fleet!$E$57)<=EOMONTH(EDATE($B$3,-1),0),OR(Fleet!$F$57="",N(Fleet!$F$57)>=EDATE($B$3,-1))),1,0))) | K58: =IF($A58="","",(SUMIFS(Trips!$H$5:$H$1004,Trips!$B$5:$B$1004,$A58,Trips!$L$5:$L$1004,EDATE($B$3,-2))+SUMIFS(Trips!$I$5:$I$1004,Trips!$B$5:$B$1004,$A58,Trips!$L$5:$L$1004,EDATE($B$3,-2))-SUMIFS(Trips!$J$5:$J$1004,Trips!$B$5:$B$1004,$A58,Trips!$L$5:$L$1004,EDATE($B$3,-2))-SUMIFS(Expenses!$E$5:$E$1004,Expenses!$B$5:$B$1004,$A58,Expenses!$G$5:$G$1004,EDATE($B$3,-2))-Fleet!$O$57*IF(AND(Fleet!$A$57<>"",N(Fleet!$E$57)<=EOMONTH(EDATE($B$3,-2),0),OR(Fleet!$F$57="",N(Fleet!$F$57)>=EDATE($B$3,-2))),1,0))) | L58: =IF($A58="","",SUMIFS(Trips!$M$5:$M$1004,Trips!$B$5:$B$1004,$A58,Trips!$L$5:$L$1004,"<="&$B$3)-SUMIFS(Expenses!$E$5:$E$1004,Expenses!$B$5:$B$1004,$A58,Expenses!$G$5:$G$1004,"<="&$B$3)-Fleet!$O$57*IF(N(Fleet!$E$57)=0,0,MAX(0,(YEAR(IF(Fleet!$F$57="",EOMONTH($B$3,0),MIN(Fleet!$F$57,EOMONTH($B$3,0))))-YEAR(Fleet!$E$57))*12+MONTH(IF(Fleet!$F$57="",EOMONTH($B$3,0),MIN(Fleet!$F$57,EOMONTH($B$3,0))))-MONTH(Fleet!$E$57)+1))) | M58: =IF($A58="","",Fleet!$H$57) | N58: =IF(OR($A58="",N(M58)=0),"",L58/M58) | O58: =IF(OR($A58="",N(C58)=0),"",IF(AND(I58<0,J58<0,K58<0),"REVIEW: 3 losing months",IF(I58<Assumptions!$B$9,"Below net target",IF(E58<Assumptions!$B$8,"Low utilization","On track"))))
A59: =IF(Fleet!A58="","",Fleet!A58) | B59: =IF(Fleet!A58="","",Fleet!B58&" "&Fleet!C58) | C59: =IF($A59="","",IF(AND(Fleet!$A$58<>"",N(Fleet!$E$58)<=EOMONTH($B$3,0),OR(Fleet!$F$58="",N(Fleet!$F$58)>=$B$3)),1,0)) | D59: =IF($A59="","",SUMIFS(Trips!$E$5:$E$1004,Trips!$B$5:$B$1004,$A59,Trips!$L$5:$L$1004,$B$3)) | E59: =IF(OR($A59="",N(C59)=0),"",D59/DAY(EOMONTH($B$3,0))) | F59: =IF($A59="","",SUMIFS(Trips!$H$5:$H$1004,Trips!$B$5:$B$1004,$A59,Trips!$L$5:$L$1004,$B$3)+SUMIFS(Trips!$I$5:$I$1004,Trips!$B$5:$B$1004,$A59,Trips!$L$5:$L$1004,$B$3)) | G59: =IF($A59="","",SUMIFS(Trips!$J$5:$J$1004,Trips!$B$5:$B$1004,$A59,Trips!$L$5:$L$1004,$B$3)+SUMIFS(Expenses!$E$5:$E$1004,Expenses!$B$5:$B$1004,$A59,Expenses!$G$5:$G$1004,$B$3)) | H59: =IF($A59="","",Fleet!$O$58*C59) | I59: =IF($A59="","",F59-G59-H59) | J59: =IF($A59="","",(SUMIFS(Trips!$H$5:$H$1004,Trips!$B$5:$B$1004,$A59,Trips!$L$5:$L$1004,EDATE($B$3,-1))+SUMIFS(Trips!$I$5:$I$1004,Trips!$B$5:$B$1004,$A59,Trips!$L$5:$L$1004,EDATE($B$3,-1))-SUMIFS(Trips!$J$5:$J$1004,Trips!$B$5:$B$1004,$A59,Trips!$L$5:$L$1004,EDATE($B$3,-1))-SUMIFS(Expenses!$E$5:$E$1004,Expenses!$B$5:$B$1004,$A59,Expenses!$G$5:$G$1004,EDATE($B$3,-1))-Fleet!$O$58*IF(AND(Fleet!$A$58<>"",N(Fleet!$E$58)<=EOMONTH(EDATE($B$3,-1),0),OR(Fleet!$F$58="",N(Fleet!$F$58)>=EDATE($B$3,-1))),1,0))) | K59: =IF($A59="","",(SUMIFS(Trips!$H$5:$H$1004,Trips!$B$5:$B$1004,$A59,Trips!$L$5:$L$1004,EDATE($B$3,-2))+SUMIFS(Trips!$I$5:$I$1004,Trips!$B$5:$B$1004,$A59,Trips!$L$5:$L$1004,EDATE($B$3,-2))-SUMIFS(Trips!$J$5:$J$1004,Trips!$B$5:$B$1004,$A59,Trips!$L$5:$L$1004,EDATE($B$3,-2))-SUMIFS(Expenses!$E$5:$E$1004,Expenses!$B$5:$B$1004,$A59,Expenses!$G$5:$G$1004,EDATE($B$3,-2))-Fleet!$O$58*IF(AND(Fleet!$A$58<>"",N(Fleet!$E$58)<=EOMONTH(EDATE($B$3,-2),0),OR(Fleet!$F$58="",N(Fleet!$F$58)>=EDATE($B$3,-2))),1,0))) | L59: =IF($A59="","",SUMIFS(Trips!$M$5:$M$1004,Trips!$B$5:$B$1004,$A59,Trips!$L$5:$L$1004,"<="&$B$3)-SUMIFS(Expenses!$E$5:$E$1004,Expenses!$B$5:$B$1004,$A59,Expenses!$G$5:$G$1004,"<="&$B$3)-Fleet!$O$58*IF(N(Fleet!$E$58)=0,0,MAX(0,(YEAR(IF(Fleet!$F$58="",EOMONTH($B$3,0),MIN(Fleet!$F$58,EOMONTH($B$3,0))))-YEAR(Fleet!$E$58))*12+MONTH(IF(Fleet!$F$58="",EOMONTH($B$3,0),MIN(Fleet!$F$58,EOMONTH($B$3,0))))-MONTH(Fleet!$E$58)+1))) | M59: =IF($A59="","",Fleet!$H$58) | N59: =IF(OR($A59="",N(M59)=0),"",L59/M59) | O59: =IF(OR($A59="",N(C59)=0),"",IF(AND(I59<0,J59<0,K59<0),"REVIEW: 3 losing months",IF(I59<Assumptions!$B$9,"Below net target",IF(E59<Assumptions!$B$8,"Low utilization","On track"))))
A60: =IF(Fleet!A59="","",Fleet!A59) | B60: =IF(Fleet!A59="","",Fleet!B59&" "&Fleet!C59) | C60: =IF($A60="","",IF(AND(Fleet!$A$59<>"",N(Fleet!$E$59)<=EOMONTH($B$3,0),OR(Fleet!$F$59="",N(Fleet!$F$59)>=$B$3)),1,0)) | D60: =IF($A60="","",SUMIFS(Trips!$E$5:$E$1004,Trips!$B$5:$B$1004,$A60,Trips!$L$5:$L$1004,$B$3)) | E60: =IF(OR($A60="",N(C60)=0),"",D60/DAY(EOMONTH($B$3,0))) | F60: =IF($A60="","",SUMIFS(Trips!$H$5:$H$1004,Trips!$B$5:$B$1004,$A60,Trips!$L$5:$L$1004,$B$3)+SUMIFS(Trips!$I$5:$I$1004,Trips!$B$5:$B$1004,$A60,Trips!$L$5:$L$1004,$B$3)) | G60: =IF($A60="","",SUMIFS(Trips!$J$5:$J$1004,Trips!$B$5:$B$1004,$A60,Trips!$L$5:$L$1004,$B$3)+SUMIFS(Expenses!$E$5:$E$1004,Expenses!$B$5:$B$1004,$A60,Expenses!$G$5:$G$1004,$B$3)) | H60: =IF($A60="","",Fleet!$O$59*C60) | I60: =IF($A60="","",F60-G60-H60) | J60: =IF($A60="","",(SUMIFS(Trips!$H$5:$H$1004,Trips!$B$5:$B$1004,$A60,Trips!$L$5:$L$1004,EDATE($B$3,-1))+SUMIFS(Trips!$I$5:$I$1004,Trips!$B$5:$B$1004,$A60,Trips!$L$5:$L$1004,EDATE($B$3,-1))-SUMIFS(Trips!$J$5:$J$1004,Trips!$B$5:$B$1004,$A60,Trips!$L$5:$L$1004,EDATE($B$3,-1))-SUMIFS(Expenses!$E$5:$E$1004,Expenses!$B$5:$B$1004,$A60,Expenses!$G$5:$G$1004,EDATE($B$3,-1))-Fleet!$O$59*IF(AND(Fleet!$A$59<>"",N(Fleet!$E$59)<=EOMONTH(EDATE($B$3,-1),0),OR(Fleet!$F$59="",N(Fleet!$F$59)>=EDATE($B$3,-1))),1,0))) | K60: =IF($A60="","",(SUMIFS(Trips!$H$5:$H$1004,Trips!$B$5:$B$1004,$A60,Trips!$L$5:$L$1004,EDATE($B$3,-2))+SUMIFS(Trips!$I$5:$I$1004,Trips!$B$5:$B$1004,$A60,Trips!$L$5:$L$1004,EDATE($B$3,-2))-SUMIFS(Trips!$J$5:$J$1004,Trips!$B$5:$B$1004,$A60,Trips!$L$5:$L$1004,EDATE($B$3,-2))-SUMIFS(Expenses!$E$5:$E$1004,Expenses!$B$5:$B$1004,$A60,Expenses!$G$5:$G$1004,EDATE($B$3,-2))-Fleet!$O$59*IF(AND(Fleet!$A$59<>"",N(Fleet!$E$59)<=EOMONTH(EDATE($B$3,-2),0),OR(Fleet!$F$59="",N(Fleet!$F$59)>=EDATE($B$3,-2))),1,0))) | L60: =IF($A60="","",SUMIFS(Trips!$M$5:$M$1004,Trips!$B$5:$B$1004,$A60,Trips!$L$5:$L$1004,"<="&$B$3)-SUMIFS(Expenses!$E$5:$E$1004,Expenses!$B$5:$B$1004,$A60,Expenses!$G$5:$G$1004,"<="&$B$3)-Fleet!$O$59*IF(N(Fleet!$E$59)=0,0,MAX(0,(YEAR(IF(Fleet!$F$59="",EOMONTH($B$3,0),MIN(Fleet!$F$59,EOMONTH($B$3,0))))-YEAR(Fleet!$E$59))*12+MONTH(IF(Fleet!$F$59="",EOMONTH($B$3,0),MIN(Fleet!$F$59,EOMONTH($B$3,0))))-MONTH(Fleet!$E$59)+1))) | M60: =IF($A60="","",Fleet!$H$59) | N60: =IF(OR($A60="",N(M60)=0),"",L60/M60) | O60: =IF(OR($A60="",N(C60)=0),"",IF(AND(I60<0,J60<0,K60<0),"REVIEW: 3 losing months",IF(I60<Assumptions!$B$9,"Below net target",IF(E60<Assumptions!$B$8,"Low utilization","On track"))))
A61: =IF(Fleet!A60="","",Fleet!A60) | B61: =IF(Fleet!A60="","",Fleet!B60&" "&Fleet!C60) | C61: =IF($A61="","",IF(AND(Fleet!$A$60<>"",N(Fleet!$E$60)<=EOMONTH($B$3,0),OR(Fleet!$F$60="",N(Fleet!$F$60)>=$B$3)),1,0)) | D61: =IF($A61="","",SUMIFS(Trips!$E$5:$E$1004,Trips!$B$5:$B$1004,$A61,Trips!$L$5:$L$1004,$B$3)) | E61: =IF(OR($A61="",N(C61)=0),"",D61/DAY(EOMONTH($B$3,0))) | F61: =IF($A61="","",SUMIFS(Trips!$H$5:$H$1004,Trips!$B$5:$B$1004,$A61,Trips!$L$5:$L$1004,$B$3)+SUMIFS(Trips!$I$5:$I$1004,Trips!$B$5:$B$1004,$A61,Trips!$L$5:$L$1004,$B$3)) | G61: =IF($A61="","",SUMIFS(Trips!$J$5:$J$1004,Trips!$B$5:$B$1004,$A61,Trips!$L$5:$L$1004,$B$3)+SUMIFS(Expenses!$E$5:$E$1004,Expenses!$B$5:$B$1004,$A61,Expenses!$G$5:$G$1004,$B$3)) | H61: =IF($A61="","",Fleet!$O$60*C61) | I61: =IF($A61="","",F61-G61-H61) | J61: =IF($A61="","",(SUMIFS(Trips!$H$5:$H$1004,Trips!$B$5:$B$1004,$A61,Trips!$L$5:$L$1004,EDATE($B$3,-1))+SUMIFS(Trips!$I$5:$I$1004,Trips!$B$5:$B$1004,$A61,Trips!$L$5:$L$1004,EDATE($B$3,-1))-SUMIFS(Trips!$J$5:$J$1004,Trips!$B$5:$B$1004,$A61,Trips!$L$5:$L$1004,EDATE($B$3,-1))-SUMIFS(Expenses!$E$5:$E$1004,Expenses!$B$5:$B$1004,$A61,Expenses!$G$5:$G$1004,EDATE($B$3,-1))-Fleet!$O$60*IF(AND(Fleet!$A$60<>"",N(Fleet!$E$60)<=EOMONTH(EDATE($B$3,-1),0),OR(Fleet!$F$60="",N(Fleet!$F$60)>=EDATE($B$3,-1))),1,0))) | K61: =IF($A61="","",(SUMIFS(Trips!$H$5:$H$1004,Trips!$B$5:$B$1004,$A61,Trips!$L$5:$L$1004,EDATE($B$3,-2))+SUMIFS(Trips!$I$5:$I$1004,Trips!$B$5:$B$1004,$A61,Trips!$L$5:$L$1004,EDATE($B$3,-2))-SUMIFS(Trips!$J$5:$J$1004,Trips!$B$5:$B$1004,$A61,Trips!$L$5:$L$1004,EDATE($B$3,-2))-SUMIFS(Expenses!$E$5:$E$1004,Expenses!$B$5:$B$1004,$A61,Expenses!$G$5:$G$1004,EDATE($B$3,-2))-Fleet!$O$60*IF(AND(Fleet!$A$60<>"",N(Fleet!$E$60)<=EOMONTH(EDATE($B$3,-2),0),OR(Fleet!$F$60="",N(Fleet!$F$60)>=EDATE($B$3,-2))),1,0))) | L61: =IF($A61="","",SUMIFS(Trips!$M$5:$M$1004,Trips!$B$5:$B$1004,$A61,Trips!$L$5:$L$1004,"<="&$B$3)-SUMIFS(Expenses!$E$5:$E$1004,Expenses!$B$5:$B$1004,$A61,Expenses!$G$5:$G$1004,"<="&$B$3)-Fleet!$O$60*IF(N(Fleet!$E$60)=0,0,MAX(0,(YEAR(IF(Fleet!$F$60="",EOMONTH($B$3,0),MIN(Fleet!$F$60,EOMONTH($B$3,0))))-YEAR(Fleet!$E$60))*12+MONTH(IF(Fleet!$F$60="",EOMONTH($B$3,0),MIN(Fleet!$F$60,EOMONTH($B$3,0))))-MONTH(Fleet!$E$60)+1))) | M61: =IF($A61="","",Fleet!$H$60) | N61: =IF(OR($A61="",N(M61)=0),"",L61/M61) | O61: =IF(OR($A61="",N(C61)=0),"",IF(AND(I61<0,J61<0,K61<0),"REVIEW: 3 losing months",IF(I61<Assumptions!$B$9,"Below net target",IF(E61<Assumptions!$B$8,"Low utilization","On track"))))
A62: =IF(Fleet!A61="","",Fleet!A61) | B62: =IF(Fleet!A61="","",Fleet!B61&" "&Fleet!C61) | C62: =IF($A62="","",IF(AND(Fleet!$A$61<>"",N(Fleet!$E$61)<=EOMONTH($B$3,0),OR(Fleet!$F$61="",N(Fleet!$F$61)>=$B$3)),1,0)) | D62: =IF($A62="","",SUMIFS(Trips!$E$5:$E$1004,Trips!$B$5:$B$1004,$A62,Trips!$L$5:$L$1004,$B$3)) | E62: =IF(OR($A62="",N(C62)=0),"",D62/DAY(EOMONTH($B$3,0))) | F62: =IF($A62="","",SUMIFS(Trips!$H$5:$H$1004,Trips!$B$5:$B$1004,$A62,Trips!$L$5:$L$1004,$B$3)+SUMIFS(Trips!$I$5:$I$1004,Trips!$B$5:$B$1004,$A62,Trips!$L$5:$L$1004,$B$3)) | G62: =IF($A62="","",SUMIFS(Trips!$J$5:$J$1004,Trips!$B$5:$B$1004,$A62,Trips!$L$5:$L$1004,$B$3)+SUMIFS(Expenses!$E$5:$E$1004,Expenses!$B$5:$B$1004,$A62,Expenses!$G$5:$G$1004,$B$3)) | H62: =IF($A62="","",Fleet!$O$61*C62) | I62: =IF($A62="","",F62-G62-H62) | J62: =IF($A62="","",(SUMIFS(Trips!$H$5:$H$1004,Trips!$B$5:$B$1004,$A62,Trips!$L$5:$L$1004,EDATE($B$3,-1))+SUMIFS(Trips!$I$5:$I$1004,Trips!$B$5:$B$1004,$A62,Trips!$L$5:$L$1004,EDATE($B$3,-1))-SUMIFS(Trips!$J$5:$J$1004,Trips!$B$5:$B$1004,$A62,Trips!$L$5:$L$1004,EDATE($B$3,-1))-SUMIFS(Expenses!$E$5:$E$1004,Expenses!$B$5:$B$1004,$A62,Expenses!$G$5:$G$1004,EDATE($B$3,-1))-Fleet!$O$61*IF(AND(Fleet!$A$61<>"",N(Fleet!$E$61)<=EOMONTH(EDATE($B$3,-1),0),OR(Fleet!$F$61="",N(Fleet!$F$61)>=EDATE($B$3,-1))),1,0))) | K62: =IF($A62="","",(SUMIFS(Trips!$H$5:$H$1004,Trips!$B$5:$B$1004,$A62,Trips!$L$5:$L$1004,EDATE($B$3,-2))+SUMIFS(Trips!$I$5:$I$1004,Trips!$B$5:$B$1004,$A62,Trips!$L$5:$L$1004,EDATE($B$3,-2))-SUMIFS(Trips!$J$5:$J$1004,Trips!$B$5:$B$1004,$A62,Trips!$L$5:$L$1004,EDATE($B$3,-2))-SUMIFS(Expenses!$E$5:$E$1004,Expenses!$B$5:$B$1004,$A62,Expenses!$G$5:$G$1004,EDATE($B$3,-2))-Fleet!$O$61*IF(AND(Fleet!$A$61<>"",N(Fleet!$E$61)<=EOMONTH(EDATE($B$3,-2),0),OR(Fleet!$F$61="",N(Fleet!$F$61)>=EDATE($B$3,-2))),1,0))) | L62: =IF($A62="","",SUMIFS(Trips!$M$5:$M$1004,Trips!$B$5:$B$1004,$A62,Trips!$L$5:$L$1004,"<="&$B$3)-SUMIFS(Expenses!$E$5:$E$1004,Expenses!$B$5:$B$1004,$A62,Expenses!$G$5:$G$1004,"<="&$B$3)-Fleet!$O$61*IF(N(Fleet!$E$61)=0,0,MAX(0,(YEAR(IF(Fleet!$F$61="",EOMONTH($B$3,0),MIN(Fleet!$F$61,EOMONTH($B$3,0))))-YEAR(Fleet!$E$61))*12+MONTH(IF(Fleet!$F$61="",EOMONTH($B$3,0),MIN(Fleet!$F$61,EOMONTH($B$3,0))))-MONTH(Fleet!$E$61)+1))) | M62: =IF($A62="","",Fleet!$H$61) | N62: =IF(OR($A62="",N(M62)=0),"",L62/M62) | O62: =IF(OR($A62="",N(C62)=0),"",IF(AND(I62<0,J62<0,K62<0),"REVIEW: 3 losing months",IF(I62<Assumptions!$B$9,"Below net target",IF(E62<Assumptions!$B$8,"Low utilization","On track"))))
A63: =IF(Fleet!A62="","",Fleet!A62) | B63: =IF(Fleet!A62="","",Fleet!B62&" "&Fleet!C62) | C63: =IF($A63="","",IF(AND(Fleet!$A$62<>"",N(Fleet!$E$62)<=EOMONTH($B$3,0),OR(Fleet!$F$62="",N(Fleet!$F$62)>=$B$3)),1,0)) | D63: =IF($A63="","",SUMIFS(Trips!$E$5:$E$1004,Trips!$B$5:$B$1004,$A63,Trips!$L$5:$L$1004,$B$3)) | E63: =IF(OR($A63="",N(C63)=0),"",D63/DAY(EOMONTH($B$3,0))) | F63: =IF($A63="","",SUMIFS(Trips!$H$5:$H$1004,Trips!$B$5:$B$1004,$A63,Trips!$L$5:$L$1004,$B$3)+SUMIFS(Trips!$I$5:$I$1004,Trips!$B$5:$B$1004,$A63,Trips!$L$5:$L$1004,$B$3)) | G63: =IF($A63="","",SUMIFS(Trips!$J$5:$J$1004,Trips!$B$5:$B$1004,$A63,Trips!$L$5:$L$1004,$B$3)+SUMIFS(Expenses!$E$5:$E$1004,Expenses!$B$5:$B$1004,$A63,Expenses!$G$5:$G$1004,$B$3)) | H63: =IF($A63="","",Fleet!$O$62*C63) | I63: =IF($A63="","",F63-G63-H63) | J63: =IF($A63="","",(SUMIFS(Trips!$H$5:$H$1004,Trips!$B$5:$B$1004,$A63,Trips!$L$5:$L$1004,EDATE($B$3,-1))+SUMIFS(Trips!$I$5:$I$1004,Trips!$B$5:$B$1004,$A63,Trips!$L$5:$L$1004,EDATE($B$3,-1))-SUMIFS(Trips!$J$5:$J$1004,Trips!$B$5:$B$1004,$A63,Trips!$L$5:$L$1004,EDATE($B$3,-1))-SUMIFS(Expenses!$E$5:$E$1004,Expenses!$B$5:$B$1004,$A63,Expenses!$G$5:$G$1004,EDATE($B$3,-1))-Fleet!$O$62*IF(AND(Fleet!$A$62<>"",N(Fleet!$E$62)<=EOMONTH(EDATE($B$3,-1),0),OR(Fleet!$F$62="",N(Fleet!$F$62)>=EDATE($B$3,-1))),1,0))) | K63: =IF($A63="","",(SUMIFS(Trips!$H$5:$H$1004,Trips!$B$5:$B$1004,$A63,Trips!$L$5:$L$1004,EDATE($B$3,-2))+SUMIFS(Trips!$I$5:$I$1004,Trips!$B$5:$B$1004,$A63,Trips!$L$5:$L$1004,EDATE($B$3,-2))-SUMIFS(Trips!$J$5:$J$1004,Trips!$B$5:$B$1004,$A63,Trips!$L$5:$L$1004,EDATE($B$3,-2))-SUMIFS(Expenses!$E$5:$E$1004,Expenses!$B$5:$B$1004,$A63,Expenses!$G$5:$G$1004,EDATE($B$3,-2))-Fleet!$O$62*IF(AND(Fleet!$A$62<>"",N(Fleet!$E$62)<=EOMONTH(EDATE($B$3,-2),0),OR(Fleet!$F$62="",N(Fleet!$F$62)>=EDATE($B$3,-2))),1,0))) | L63: =IF($A63="","",SUMIFS(Trips!$M$5:$M$1004,Trips!$B$5:$B$1004,$A63,Trips!$L$5:$L$1004,"<="&$B$3)-SUMIFS(Expenses!$E$5:$E$1004,Expenses!$B$5:$B$1004,$A63,Expenses!$G$5:$G$1004,"<="&$B$3)-Fleet!$O$62*IF(N(Fleet!$E$62)=0,0,MAX(0,(YEAR(IF(Fleet!$F$62="",EOMONTH($B$3,0),MIN(Fleet!$F$62,EOMONTH($B$3,0))))-YEAR(Fleet!$E$62))*12+MONTH(IF(Fleet!$F$62="",EOMONTH($B$3,0),MIN(Fleet!$F$62,EOMONTH($B$3,0))))-MONTH(Fleet!$E$62)+1))) | M63: =IF($A63="","",Fleet!$H$62) | N63: =IF(OR($A63="",N(M63)=0),"",L63/M63) | O63: =IF(OR($A63="",N(C63)=0),"",IF(AND(I63<0,J63<0,K63<0),"REVIEW: 3 losing months",IF(I63<Assumptions!$B$9,"Below net target",IF(E63<Assumptions!$B$8,"Low utilization","On track"))))
A64: =IF(Fleet!A63="","",Fleet!A63) | B64: =IF(Fleet!A63="","",Fleet!B63&" "&Fleet!C63) | C64: =IF($A64="","",IF(AND(Fleet!$A$63<>"",N(Fleet!$E$63)<=EOMONTH($B$3,0),OR(Fleet!$F$63="",N(Fleet!$F$63)>=$B$3)),1,0)) | D64: =IF($A64="","",SUMIFS(Trips!$E$5:$E$1004,Trips!$B$5:$B$1004,$A64,Trips!$L$5:$L$1004,$B$3)) | E64: =IF(OR($A64="",N(C64)=0),"",D64/DAY(EOMONTH($B$3,0))) | F64: =IF($A64="","",SUMIFS(Trips!$H$5:$H$1004,Trips!$B$5:$B$1004,$A64,Trips!$L$5:$L$1004,$B$3)+SUMIFS(Trips!$I$5:$I$1004,Trips!$B$5:$B$1004,$A64,Trips!$L$5:$L$1004,$B$3)) | G64: =IF($A64="","",SUMIFS(Trips!$J$5:$J$1004,Trips!$B$5:$B$1004,$A64,Trips!$L$5:$L$1004,$B$3)+SUMIFS(Expenses!$E$5:$E$1004,Expenses!$B$5:$B$1004,$A64,Expenses!$G$5:$G$1004,$B$3)) | H64: =IF($A64="","",Fleet!$O$63*C64) | I64: =IF($A64="","",F64-G64-H64) | J64: =IF($A64="","",(SUMIFS(Trips!$H$5:$H$1004,Trips!$B$5:$B$1004,$A64,Trips!$L$5:$L$1004,EDATE($B$3,-1))+SUMIFS(Trips!$I$5:$I$1004,Trips!$B$5:$B$1004,$A64,Trips!$L$5:$L$1004,EDATE($B$3,-1))-SUMIFS(Trips!$J$5:$J$1004,Trips!$B$5:$B$1004,$A64,Trips!$L$5:$L$1004,EDATE($B$3,-1))-SUMIFS(Expenses!$E$5:$E$1004,Expenses!$B$5:$B$1004,$A64,Expenses!$G$5:$G$1004,EDATE($B$3,-1))-Fleet!$O$63*IF(AND(Fleet!$A$63<>"",N(Fleet!$E$63)<=EOMONTH(EDATE($B$3,-1),0),OR(Fleet!$F$63="",N(Fleet!$F$63)>=EDATE($B$3,-1))),1,0))) | K64: =IF($A64="","",(SUMIFS(Trips!$H$5:$H$1004,Trips!$B$5:$B$1004,$A64,Trips!$L$5:$L$1004,EDATE($B$3,-2))+SUMIFS(Trips!$I$5:$I$1004,Trips!$B$5:$B$1004,$A64,Trips!$L$5:$L$1004,EDATE($B$3,-2))-SUMIFS(Trips!$J$5:$J$1004,Trips!$B$5:$B$1004,$A64,Trips!$L$5:$L$1004,EDATE($B$3,-2))-SUMIFS(Expenses!$E$5:$E$1004,Expenses!$B$5:$B$1004,$A64,Expenses!$G$5:$G$1004,EDATE($B$3,-2))-Fleet!$O$63*IF(AND(Fleet!$A$63<>"",N(Fleet!$E$63)<=EOMONTH(EDATE($B$3,-2),0),OR(Fleet!$F$63="",N(Fleet!$F$63)>=EDATE($B$3,-2))),1,0))) | L64: =IF($A64="","",SUMIFS(Trips!$M$5:$M$1004,Trips!$B$5:$B$1004,$A64,Trips!$L$5:$L$1004,"<="&$B$3)-SUMIFS(Expenses!$E$5:$E$1004,Expenses!$B$5:$B$1004,$A64,Expenses!$G$5:$G$1004,"<="&$B$3)-Fleet!$O$63*IF(N(Fleet!$E$63)=0,0,MAX(0,(YEAR(IF(Fleet!$F$63="",EOMONTH($B$3,0),MIN(Fleet!$F$63,EOMONTH($B$3,0))))-YEAR(Fleet!$E$63))*12+MONTH(IF(Fleet!$F$63="",EOMONTH($B$3,0),MIN(Fleet!$F$63,EOMONTH($B$3,0))))-MONTH(Fleet!$E$63)+1))) | M64: =IF($A64="","",Fleet!$H$63) | N64: =IF(OR($A64="",N(M64)=0),"",L64/M64) | O64: =IF(OR($A64="",N(C64)=0),"",IF(AND(I64<0,J64<0,K64<0),"REVIEW: 3 losing months",IF(I64<Assumptions!$B$9,"Below net target",IF(E64<Assumptions!$B$8,"Low utilization","On track"))))
A65: =IF(Fleet!A64="","",Fleet!A64) | B65: =IF(Fleet!A64="","",Fleet!B64&" "&Fleet!C64) | C65: =IF($A65="","",IF(AND(Fleet!$A$64<>"",N(Fleet!$E$64)<=EOMONTH($B$3,0),OR(Fleet!$F$64="",N(Fleet!$F$64)>=$B$3)),1,0)) | D65: =IF($A65="","",SUMIFS(Trips!$E$5:$E$1004,Trips!$B$5:$B$1004,$A65,Trips!$L$5:$L$1004,$B$3)) | E65: =IF(OR($A65="",N(C65)=0),"",D65/DAY(EOMONTH($B$3,0))) | F65: =IF($A65="","",SUMIFS(Trips!$H$5:$H$1004,Trips!$B$5:$B$1004,$A65,Trips!$L$5:$L$1004,$B$3)+SUMIFS(Trips!$I$5:$I$1004,Trips!$B$5:$B$1004,$A65,Trips!$L$5:$L$1004,$B$3)) | G65: =IF($A65="","",SUMIFS(Trips!$J$5:$J$1004,Trips!$B$5:$B$1004,$A65,Trips!$L$5:$L$1004,$B$3)+SUMIFS(Expenses!$E$5:$E$1004,Expenses!$B$5:$B$1004,$A65,Expenses!$G$5:$G$1004,$B$3)) | H65: =IF($A65="","",Fleet!$O$64*C65) | I65: =IF($A65="","",F65-G65-H65) | J65: =IF($A65="","",(SUMIFS(Trips!$H$5:$H$1004,Trips!$B$5:$B$1004,$A65,Trips!$L$5:$L$1004,EDATE($B$3,-1))+SUMIFS(Trips!$I$5:$I$1004,Trips!$B$5:$B$1004,$A65,Trips!$L$5:$L$1004,EDATE($B$3,-1))-SUMIFS(Trips!$J$5:$J$1004,Trips!$B$5:$B$1004,$A65,Trips!$L$5:$L$1004,EDATE($B$3,-1))-SUMIFS(Expenses!$E$5:$E$1004,Expenses!$B$5:$B$1004,$A65,Expenses!$G$5:$G$1004,EDATE($B$3,-1))-Fleet!$O$64*IF(AND(Fleet!$A$64<>"",N(Fleet!$E$64)<=EOMONTH(EDATE($B$3,-1),0),OR(Fleet!$F$64="",N(Fleet!$F$64)>=EDATE($B$3,-1))),1,0))) | K65: =IF($A65="","",(SUMIFS(Trips!$H$5:$H$1004,Trips!$B$5:$B$1004,$A65,Trips!$L$5:$L$1004,EDATE($B$3,-2))+SUMIFS(Trips!$I$5:$I$1004,Trips!$B$5:$B$1004,$A65,Trips!$L$5:$L$1004,EDATE($B$3,-2))-SUMIFS(Trips!$J$5:$J$1004,Trips!$B$5:$B$1004,$A65,Trips!$L$5:$L$1004,EDATE($B$3,-2))-SUMIFS(Expenses!$E$5:$E$1004,Expenses!$B$5:$B$1004,$A65,Expenses!$G$5:$G$1004,EDATE($B$3,-2))-Fleet!$O$64*IF(AND(Fleet!$A$64<>"",N(Fleet!$E$64)<=EOMONTH(EDATE($B$3,-2),0),OR(Fleet!$F$64="",N(Fleet!$F$64)>=EDATE($B$3,-2))),1,0))) | L65: =IF($A65="","",SUMIFS(Trips!$M$5:$M$1004,Trips!$B$5:$B$1004,$A65,Trips!$L$5:$L$1004,"<="&$B$3)-SUMIFS(Expenses!$E$5:$E$1004,Expenses!$B$5:$B$1004,$A65,Expenses!$G$5:$G$1004,"<="&$B$3)-Fleet!$O$64*IF(N(Fleet!$E$64)=0,0,MAX(0,(YEAR(IF(Fleet!$F$64="",EOMONTH($B$3,0),MIN(Fleet!$F$64,EOMONTH($B$3,0))))-YEAR(Fleet!$E$64))*12+MONTH(IF(Fleet!$F$64="",EOMONTH($B$3,0),MIN(Fleet!$F$64,EOMONTH($B$3,0))))-MONTH(Fleet!$E$64)+1))) | M65: =IF($A65="","",Fleet!$H$64) | N65: =IF(OR($A65="",N(M65)=0),"",L65/M65) | O65: =IF(OR($A65="",N(C65)=0),"",IF(AND(I65<0,J65<0,K65<0),"REVIEW: 3 losing months",IF(I65<Assumptions!$B$9,"Below net target",IF(E65<Assumptions!$B$8,"Low utilization","On track"))))
A66: =IF(Fleet!A65="","",Fleet!A65) | B66: =IF(Fleet!A65="","",Fleet!B65&" "&Fleet!C65) | C66: =IF($A66="","",IF(AND(Fleet!$A$65<>"",N(Fleet!$E$65)<=EOMONTH($B$3,0),OR(Fleet!$F$65="",N(Fleet!$F$65)>=$B$3)),1,0)) | D66: =IF($A66="","",SUMIFS(Trips!$E$5:$E$1004,Trips!$B$5:$B$1004,$A66,Trips!$L$5:$L$1004,$B$3)) | E66: =IF(OR($A66="",N(C66)=0),"",D66/DAY(EOMONTH($B$3,0))) | F66: =IF($A66="","",SUMIFS(Trips!$H$5:$H$1004,Trips!$B$5:$B$1004,$A66,Trips!$L$5:$L$1004,$B$3)+SUMIFS(Trips!$I$5:$I$1004,Trips!$B$5:$B$1004,$A66,Trips!$L$5:$L$1004,$B$3)) | G66: =IF($A66="","",SUMIFS(Trips!$J$5:$J$1004,Trips!$B$5:$B$1004,$A66,Trips!$L$5:$L$1004,$B$3)+SUMIFS(Expenses!$E$5:$E$1004,Expenses!$B$5:$B$1004,$A66,Expenses!$G$5:$G$1004,$B$3)) | H66: =IF($A66="","",Fleet!$O$65*C66) | I66: =IF($A66="","",F66-G66-H66) | J66: =IF($A66="","",(SUMIFS(Trips!$H$5:$H$1004,Trips!$B$5:$B$1004,$A66,Trips!$L$5:$L$1004,EDATE($B$3,-1))+SUMIFS(Trips!$I$5:$I$1004,Trips!$B$5:$B$1004,$A66,Trips!$L$5:$L$1004,EDATE($B$3,-1))-SUMIFS(Trips!$J$5:$J$1004,Trips!$B$5:$B$1004,$A66,Trips!$L$5:$L$1004,EDATE($B$3,-1))-SUMIFS(Expenses!$E$5:$E$1004,Expenses!$B$5:$B$1004,$A66,Expenses!$G$5:$G$1004,EDATE($B$3,-1))-Fleet!$O$65*IF(AND(Fleet!$A$65<>"",N(Fleet!$E$65)<=EOMONTH(EDATE($B$3,-1),0),OR(Fleet!$F$65="",N(Fleet!$F$65)>=EDATE($B$3,-1))),1,0))) | K66: =IF($A66="","",(SUMIFS(Trips!$H$5:$H$1004,Trips!$B$5:$B$1004,$A66,Trips!$L$5:$L$1004,EDATE($B$3,-2))+SUMIFS(Trips!$I$5:$I$1004,Trips!$B$5:$B$1004,$A66,Trips!$L$5:$L$1004,EDATE($B$3,-2))-SUMIFS(Trips!$J$5:$J$1004,Trips!$B$5:$B$1004,$A66,Trips!$L$5:$L$1004,EDATE($B$3,-2))-SUMIFS(Expenses!$E$5:$E$1004,Expenses!$B$5:$B$1004,$A66,Expenses!$G$5:$G$1004,EDATE($B$3,-2))-Fleet!$O$65*IF(AND(Fleet!$A$65<>"",N(Fleet!$E$65)<=EOMONTH(EDATE($B$3,-2),0),OR(Fleet!$F$65="",N(Fleet!$F$65)>=EDATE($B$3,-2))),1,0))) | L66: =IF($A66="","",SUMIFS(Trips!$M$5:$M$1004,Trips!$B$5:$B$1004,$A66,Trips!$L$5:$L$1004,"<="&$B$3)-SUMIFS(Expenses!$E$5:$E$1004,Expenses!$B$5:$B$1004,$A66,Expenses!$G$5:$G$1004,"<="&$B$3)-Fleet!$O$65*IF(N(Fleet!$E$65)=0,0,MAX(0,(YEAR(IF(Fleet!$F$65="",EOMONTH($B$3,0),MIN(Fleet!$F$65,EOMONTH($B$3,0))))-YEAR(Fleet!$E$65))*12+MONTH(IF(Fleet!$F$65="",EOMONTH($B$3,0),MIN(Fleet!$F$65,EOMONTH($B$3,0))))-MONTH(Fleet!$E$65)+1))) | M66: =IF($A66="","",Fleet!$H$65) | N66: =IF(OR($A66="",N(M66)=0),"",L66/M66) | O66: =IF(OR($A66="",N(C66)=0),"",IF(AND(I66<0,J66<0,K66<0),"REVIEW: 3 losing months",IF(I66<Assumptions!$B$9,"Below net target",IF(E66<Assumptions!$B$8,"Low utilization","On track"))))
A67: =IF(Fleet!A66="","",Fleet!A66) | B67: =IF(Fleet!A66="","",Fleet!B66&" "&Fleet!C66) | C67: =IF($A67="","",IF(AND(Fleet!$A$66<>"",N(Fleet!$E$66)<=EOMONTH($B$3,0),OR(Fleet!$F$66="",N(Fleet!$F$66)>=$B$3)),1,0)) | D67: =IF($A67="","",SUMIFS(Trips!$E$5:$E$1004,Trips!$B$5:$B$1004,$A67,Trips!$L$5:$L$1004,$B$3)) | E67: =IF(OR($A67="",N(C67)=0),"",D67/DAY(EOMONTH($B$3,0))) | F67: =IF($A67="","",SUMIFS(Trips!$H$5:$H$1004,Trips!$B$5:$B$1004,$A67,Trips!$L$5:$L$1004,$B$3)+SUMIFS(Trips!$I$5:$I$1004,Trips!$B$5:$B$1004,$A67,Trips!$L$5:$L$1004,$B$3)) | G67: =IF($A67="","",SUMIFS(Trips!$J$5:$J$1004,Trips!$B$5:$B$1004,$A67,Trips!$L$5:$L$1004,$B$3)+SUMIFS(Expenses!$E$5:$E$1004,Expenses!$B$5:$B$1004,$A67,Expenses!$G$5:$G$1004,$B$3)) | H67: =IF($A67="","",Fleet!$O$66*C67) | I67: =IF($A67="","",F67-G67-H67) | J67: =IF($A67="","",(SUMIFS(Trips!$H$5:$H$1004,Trips!$B$5:$B$1004,$A67,Trips!$L$5:$L$1004,EDATE($B$3,-1))+SUMIFS(Trips!$I$5:$I$1004,Trips!$B$5:$B$1004,$A67,Trips!$L$5:$L$1004,EDATE($B$3,-1))-SUMIFS(Trips!$J$5:$J$1004,Trips!$B$5:$B$1004,$A67,Trips!$L$5:$L$1004,EDATE($B$3,-1))-SUMIFS(Expenses!$E$5:$E$1004,Expenses!$B$5:$B$1004,$A67,Expenses!$G$5:$G$1004,EDATE($B$3,-1))-Fleet!$O$66*IF(AND(Fleet!$A$66<>"",N(Fleet!$E$66)<=EOMONTH(EDATE($B$3,-1),0),OR(Fleet!$F$66="",N(Fleet!$F$66)>=EDATE($B$3,-1))),1,0))) | K67: =IF($A67="","",(SUMIFS(Trips!$H$5:$H$1004,Trips!$B$5:$B$1004,$A67,Trips!$L$5:$L$1004,EDATE($B$3,-2))+SUMIFS(Trips!$I$5:$I$1004,Trips!$B$5:$B$1004,$A67,Trips!$L$5:$L$1004,EDATE($B$3,-2))-SUMIFS(Trips!$J$5:$J$1004,Trips!$B$5:$B$1004,$A67,Trips!$L$5:$L$1004,EDATE($B$3,-2))-SUMIFS(Expenses!$E$5:$E$1004,Expenses!$B$5:$B$1004,$A67,Expenses!$G$5:$G$1004,EDATE($B$3,-2))-Fleet!$O$66*IF(AND(Fleet!$A$66<>"",N(Fleet!$E$66)<=EOMONTH(EDATE($B$3,-2),0),OR(Fleet!$F$66="",N(Fleet!$F$66)>=EDATE($B$3,-2))),1,0))) | L67: =IF($A67="","",SUMIFS(Trips!$M$5:$M$1004,Trips!$B$5:$B$1004,$A67,Trips!$L$5:$L$1004,"<="&$B$3)-SUMIFS(Expenses!$E$5:$E$1004,Expenses!$B$5:$B$1004,$A67,Expenses!$G$5:$G$1004,"<="&$B$3)-Fleet!$O$66*IF(N(Fleet!$E$66)=0,0,MAX(0,(YEAR(IF(Fleet!$F$66="",EOMONTH($B$3,0),MIN(Fleet!$F$66,EOMONTH($B$3,0))))-YEAR(Fleet!$E$66))*12+MONTH(IF(Fleet!$F$66="",EOMONTH($B$3,0),MIN(Fleet!$F$66,EOMONTH($B$3,0))))-MONTH(Fleet!$E$66)+1))) | M67: =IF($A67="","",Fleet!$H$66) | N67: =IF(OR($A67="",N(M67)=0),"",L67/M67) | O67: =IF(OR($A67="",N(C67)=0),"",IF(AND(I67<0,J67<0,K67<0),"REVIEW: 3 losing months",IF(I67<Assumptions!$B$9,"Below net target",IF(E67<Assumptions!$B$8,"Low utilization","On track"))))
A68: =IF(Fleet!A67="","",Fleet!A67) | B68: =IF(Fleet!A67="","",Fleet!B67&" "&Fleet!C67) | C68: =IF($A68="","",IF(AND(Fleet!$A$67<>"",N(Fleet!$E$67)<=EOMONTH($B$3,0),OR(Fleet!$F$67="",N(Fleet!$F$67)>=$B$3)),1,0)) | D68: =IF($A68="","",SUMIFS(Trips!$E$5:$E$1004,Trips!$B$5:$B$1004,$A68,Trips!$L$5:$L$1004,$B$3)) | E68: =IF(OR($A68="",N(C68)=0),"",D68/DAY(EOMONTH($B$3,0))) | F68: =IF($A68="","",SUMIFS(Trips!$H$5:$H$1004,Trips!$B$5:$B$1004,$A68,Trips!$L$5:$L$1004,$B$3)+SUMIFS(Trips!$I$5:$I$1004,Trips!$B$5:$B$1004,$A68,Trips!$L$5:$L$1004,$B$3)) | G68: =IF($A68="","",SUMIFS(Trips!$J$5:$J$1004,Trips!$B$5:$B$1004,$A68,Trips!$L$5:$L$1004,$B$3)+SUMIFS(Expenses!$E$5:$E$1004,Expenses!$B$5:$B$1004,$A68,Expenses!$G$5:$G$1004,$B$3)) | H68: =IF($A68="","",Fleet!$O$67*C68) | I68: =IF($A68="","",F68-G68-H68) | J68: =IF($A68="","",(SUMIFS(Trips!$H$5:$H$1004,Trips!$B$5:$B$1004,$A68,Trips!$L$5:$L$1004,EDATE($B$3,-1))+SUMIFS(Trips!$I$5:$I$1004,Trips!$B$5:$B$1004,$A68,Trips!$L$5:$L$1004,EDATE($B$3,-1))-SUMIFS(Trips!$J$5:$J$1004,Trips!$B$5:$B$1004,$A68,Trips!$L$5:$L$1004,EDATE($B$3,-1))-SUMIFS(Expenses!$E$5:$E$1004,Expenses!$B$5:$B$1004,$A68,Expenses!$G$5:$G$1004,EDATE($B$3,-1))-Fleet!$O$67*IF(AND(Fleet!$A$67<>"",N(Fleet!$E$67)<=EOMONTH(EDATE($B$3,-1),0),OR(Fleet!$F$67="",N(Fleet!$F$67)>=EDATE($B$3,-1))),1,0))) | K68: =IF($A68="","",(SUMIFS(Trips!$H$5:$H$1004,Trips!$B$5:$B$1004,$A68,Trips!$L$5:$L$1004,EDATE($B$3,-2))+SUMIFS(Trips!$I$5:$I$1004,Trips!$B$5:$B$1004,$A68,Trips!$L$5:$L$1004,EDATE($B$3,-2))-SUMIFS(Trips!$J$5:$J$1004,Trips!$B$5:$B$1004,$A68,Trips!$L$5:$L$1004,EDATE($B$3,-2))-SUMIFS(Expenses!$E$5:$E$1004,Expenses!$B$5:$B$1004,$A68,Expenses!$G$5:$G$1004,EDATE($B$3,-2))-Fleet!$O$67*IF(AND(Fleet!$A$67<>"",N(Fleet!$E$67)<=EOMONTH(EDATE($B$3,-2),0),OR(Fleet!$F$67="",N(Fleet!$F$67)>=EDATE($B$3,-2))),1,0))) | L68: =IF($A68="","",SUMIFS(Trips!$M$5:$M$1004,Trips!$B$5:$B$1004,$A68,Trips!$L$5:$L$1004,"<="&$B$3)-SUMIFS(Expenses!$E$5:$E$1004,Expenses!$B$5:$B$1004,$A68,Expenses!$G$5:$G$1004,"<="&$B$3)-Fleet!$O$67*IF(N(Fleet!$E$67)=0,0,MAX(0,(YEAR(IF(Fleet!$F$67="",EOMONTH($B$3,0),MIN(Fleet!$F$67,EOMONTH($B$3,0))))-YEAR(Fleet!$E$67))*12+MONTH(IF(Fleet!$F$67="",EOMONTH($B$3,0),MIN(Fleet!$F$67,EOMONTH($B$3,0))))-MONTH(Fleet!$E$67)+1))) | M68: =IF($A68="","",Fleet!$H$67) | N68: =IF(OR($A68="",N(M68)=0),"",L68/M68) | O68: =IF(OR($A68="",N(C68)=0),"",IF(AND(I68<0,J68<0,K68<0),"REVIEW: 3 losing months",IF(I68<Assumptions!$B$9,"Below net target",IF(E68<Assumptions!$B$8,"Low utilization","On track"))))
A69: =IF(Fleet!A68="","",Fleet!A68) | B69: =IF(Fleet!A68="","",Fleet!B68&" "&Fleet!C68) | C69: =IF($A69="","",IF(AND(Fleet!$A$68<>"",N(Fleet!$E$68)<=EOMONTH($B$3,0),OR(Fleet!$F$68="",N(Fleet!$F$68)>=$B$3)),1,0)) | D69: =IF($A69="","",SUMIFS(Trips!$E$5:$E$1004,Trips!$B$5:$B$1004,$A69,Trips!$L$5:$L$1004,$B$3)) | E69: =IF(OR($A69="",N(C69)=0),"",D69/DAY(EOMONTH($B$3,0))) | F69: =IF($A69="","",SUMIFS(Trips!$H$5:$H$1004,Trips!$B$5:$B$1004,$A69,Trips!$L$5:$L$1004,$B$3)+SUMIFS(Trips!$I$5:$I$1004,Trips!$B$5:$B$1004,$A69,Trips!$L$5:$L$1004,$B$3)) | G69: =IF($A69="","",SUMIFS(Trips!$J$5:$J$1004,Trips!$B$5:$B$1004,$A69,Trips!$L$5:$L$1004,$B$3)+SUMIFS(Expenses!$E$5:$E$1004,Expenses!$B$5:$B$1004,$A69,Expenses!$G$5:$G$1004,$B$3)) | H69: =IF($A69="","",Fleet!$O$68*C69) | I69: =IF($A69="","",F69-G69-H69) | J69: =IF($A69="","",(SUMIFS(Trips!$H$5:$H$1004,Trips!$B$5:$B$1004,$A69,Trips!$L$5:$L$1004,EDATE($B$3,-1))+SUMIFS(Trips!$I$5:$I$1004,Trips!$B$5:$B$1004,$A69,Trips!$L$5:$L$1004,EDATE($B$3,-1))-SUMIFS(Trips!$J$5:$J$1004,Trips!$B$5:$B$1004,$A69,Trips!$L$5:$L$1004,EDATE($B$3,-1))-SUMIFS(Expenses!$E$5:$E$1004,Expenses!$B$5:$B$1004,$A69,Expenses!$G$5:$G$1004,EDATE($B$3,-1))-Fleet!$O$68*IF(AND(Fleet!$A$68<>"",N(Fleet!$E$68)<=EOMONTH(EDATE($B$3,-1),0),OR(Fleet!$F$68="",N(Fleet!$F$68)>=EDATE($B$3,-1))),1,0))) | K69: =IF($A69="","",(SUMIFS(Trips!$H$5:$H$1004,Trips!$B$5:$B$1004,$A69,Trips!$L$5:$L$1004,EDATE($B$3,-2))+SUMIFS(Trips!$I$5:$I$1004,Trips!$B$5:$B$1004,$A69,Trips!$L$5:$L$1004,EDATE($B$3,-2))-SUMIFS(Trips!$J$5:$J$1004,Trips!$B$5:$B$1004,$A69,Trips!$L$5:$L$1004,EDATE($B$3,-2))-SUMIFS(Expenses!$E$5:$E$1004,Expenses!$B$5:$B$1004,$A69,Expenses!$G$5:$G$1004,EDATE($B$3,-2))-Fleet!$O$68*IF(AND(Fleet!$A$68<>"",N(Fleet!$E$68)<=EOMONTH(EDATE($B$3,-2),0),OR(Fleet!$F$68="",N(Fleet!$F$68)>=EDATE($B$3,-2))),1,0))) | L69: =IF($A69="","",SUMIFS(Trips!$M$5:$M$1004,Trips!$B$5:$B$1004,$A69,Trips!$L$5:$L$1004,"<="&$B$3)-SUMIFS(Expenses!$E$5:$E$1004,Expenses!$B$5:$B$1004,$A69,Expenses!$G$5:$G$1004,"<="&$B$3)-Fleet!$O$68*IF(N(Fleet!$E$68)=0,0,MAX(0,(YEAR(IF(Fleet!$F$68="",EOMONTH($B$3,0),MIN(Fleet!$F$68,EOMONTH($B$3,0))))-YEAR(Fleet!$E$68))*12+MONTH(IF(Fleet!$F$68="",EOMONTH($B$3,0),MIN(Fleet!$F$68,EOMONTH($B$3,0))))-MONTH(Fleet!$E$68)+1))) | M69: =IF($A69="","",Fleet!$H$68) | N69: =IF(OR($A69="",N(M69)=0),"",L69/M69) | O69: =IF(OR($A69="",N(C69)=0),"",IF(AND(I69<0,J69<0,K69<0),"REVIEW: 3 losing months",IF(I69<Assumptions!$B$9,"Below net target",IF(E69<Assumptions!$B$8,"Low utilization","On track"))))
A70: =IF(Fleet!A69="","",Fleet!A69) | B70: =IF(Fleet!A69="","",Fleet!B69&" "&Fleet!C69) | C70: =IF($A70="","",IF(AND(Fleet!$A$69<>"",N(Fleet!$E$69)<=EOMONTH($B$3,0),OR(Fleet!$F$69="",N(Fleet!$F$69)>=$B$3)),1,0)) | D70: =IF($A70="","",SUMIFS(Trips!$E$5:$E$1004,Trips!$B$5:$B$1004,$A70,Trips!$L$5:$L$1004,$B$3)) | E70: =IF(OR($A70="",N(C70)=0),"",D70/DAY(EOMONTH($B$3,0))) | F70: =IF($A70="","",SUMIFS(Trips!$H$5:$H$1004,Trips!$B$5:$B$1004,$A70,Trips!$L$5:$L$1004,$B$3)+SUMIFS(Trips!$I$5:$I$1004,Trips!$B$5:$B$1004,$A70,Trips!$L$5:$L$1004,$B$3)) | G70: =IF($A70="","",SUMIFS(Trips!$J$5:$J$1004,Trips!$B$5:$B$1004,$A70,Trips!$L$5:$L$1004,$B$3)+SUMIFS(Expenses!$E$5:$E$1004,Expenses!$B$5:$B$1004,$A70,Expenses!$G$5:$G$1004,$B$3)) | H70: =IF($A70="","",Fleet!$O$69*C70) | I70: =IF($A70="","",F70-G70-H70) | J70: =IF($A70="","",(SUMIFS(Trips!$H$5:$H$1004,Trips!$B$5:$B$1004,$A70,Trips!$L$5:$L$1004,EDATE($B$3,-1))+SUMIFS(Trips!$I$5:$I$1004,Trips!$B$5:$B$1004,$A70,Trips!$L$5:$L$1004,EDATE($B$3,-1))-SUMIFS(Trips!$J$5:$J$1004,Trips!$B$5:$B$1004,$A70,Trips!$L$5:$L$1004,EDATE($B$3,-1))-SUMIFS(Expenses!$E$5:$E$1004,Expenses!$B$5:$B$1004,$A70,Expenses!$G$5:$G$1004,EDATE($B$3,-1))-Fleet!$O$69*IF(AND(Fleet!$A$69<>"",N(Fleet!$E$69)<=EOMONTH(EDATE($B$3,-1),0),OR(Fleet!$F$69="",N(Fleet!$F$69)>=EDATE($B$3,-1))),1,0))) | K70: =IF($A70="","",(SUMIFS(Trips!$H$5:$H$1004,Trips!$B$5:$B$1004,$A70,Trips!$L$5:$L$1004,EDATE($B$3,-2))+SUMIFS(Trips!$I$5:$I$1004,Trips!$B$5:$B$1004,$A70,Trips!$L$5:$L$1004,EDATE($B$3,-2))-SUMIFS(Trips!$J$5:$J$1004,Trips!$B$5:$B$1004,$A70,Trips!$L$5:$L$1004,EDATE($B$3,-2))-SUMIFS(Expenses!$E$5:$E$1004,Expenses!$B$5:$B$1004,$A70,Expenses!$G$5:$G$1004,EDATE($B$3,-2))-Fleet!$O$69*IF(AND(Fleet!$A$69<>"",N(Fleet!$E$69)<=EOMONTH(EDATE($B$3,-2),0),OR(Fleet!$F$69="",N(Fleet!$F$69)>=EDATE($B$3,-2))),1,0))) | L70: =IF($A70="","",SUMIFS(Trips!$M$5:$M$1004,Trips!$B$5:$B$1004,$A70,Trips!$L$5:$L$1004,"<="&$B$3)-SUMIFS(Expenses!$E$5:$E$1004,Expenses!$B$5:$B$1004,$A70,Expenses!$G$5:$G$1004,"<="&$B$3)-Fleet!$O$69*IF(N(Fleet!$E$69)=0,0,MAX(0,(YEAR(IF(Fleet!$F$69="",EOMONTH($B$3,0),MIN(Fleet!$F$69,EOMONTH($B$3,0))))-YEAR(Fleet!$E$69))*12+MONTH(IF(Fleet!$F$69="",EOMONTH($B$3,0),MIN(Fleet!$F$69,EOMONTH($B$3,0))))-MONTH(Fleet!$E$69)+1))) | M70: =IF($A70="","",Fleet!$H$69) | N70: =IF(OR($A70="",N(M70)=0),"",L70/M70) | O70: =IF(OR($A70="",N(C70)=0),"",IF(AND(I70<0,J70<0,K70<0),"REVIEW: 3 losing months",IF(I70<Assumptions!$B$9,"Below net target",IF(E70<Assumptions!$B$8,"Low utilization","On track"))))
A71: =IF(Fleet!A70="","",Fleet!A70) | B71: =IF(Fleet!A70="","",Fleet!B70&" "&Fleet!C70) | C71: =IF($A71="","",IF(AND(Fleet!$A$70<>"",N(Fleet!$E$70)<=EOMONTH($B$3,0),OR(Fleet!$F$70="",N(Fleet!$F$70)>=$B$3)),1,0)) | D71: =IF($A71="","",SUMIFS(Trips!$E$5:$E$1004,Trips!$B$5:$B$1004,$A71,Trips!$L$5:$L$1004,$B$3)) | E71: =IF(OR($A71="",N(C71)=0),"",D71/DAY(EOMONTH($B$3,0))) | F71: =IF($A71="","",SUMIFS(Trips!$H$5:$H$1004,Trips!$B$5:$B$1004,$A71,Trips!$L$5:$L$1004,$B$3)+SUMIFS(Trips!$I$5:$I$1004,Trips!$B$5:$B$1004,$A71,Trips!$L$5:$L$1004,$B$3)) | G71: =IF($A71="","",SUMIFS(Trips!$J$5:$J$1004,Trips!$B$5:$B$1004,$A71,Trips!$L$5:$L$1004,$B$3)+SUMIFS(Expenses!$E$5:$E$1004,Expenses!$B$5:$B$1004,$A71,Expenses!$G$5:$G$1004,$B$3)) | H71: =IF($A71="","",Fleet!$O$70*C71) | I71: =IF($A71="","",F71-G71-H71) | J71: =IF($A71="","",(SUMIFS(Trips!$H$5:$H$1004,Trips!$B$5:$B$1004,$A71,Trips!$L$5:$L$1004,EDATE($B$3,-1))+SUMIFS(Trips!$I$5:$I$1004,Trips!$B$5:$B$1004,$A71,Trips!$L$5:$L$1004,EDATE($B$3,-1))-SUMIFS(Trips!$J$5:$J$1004,Trips!$B$5:$B$1004,$A71,Trips!$L$5:$L$1004,EDATE($B$3,-1))-SUMIFS(Expenses!$E$5:$E$1004,Expenses!$B$5:$B$1004,$A71,Expenses!$G$5:$G$1004,EDATE($B$3,-1))-Fleet!$O$70*IF(AND(Fleet!$A$70<>"",N(Fleet!$E$70)<=EOMONTH(EDATE($B$3,-1),0),OR(Fleet!$F$70="",N(Fleet!$F$70)>=EDATE($B$3,-1))),1,0))) | K71: =IF($A71="","",(SUMIFS(Trips!$H$5:$H$1004,Trips!$B$5:$B$1004,$A71,Trips!$L$5:$L$1004,EDATE($B$3,-2))+SUMIFS(Trips!$I$5:$I$1004,Trips!$B$5:$B$1004,$A71,Trips!$L$5:$L$1004,EDATE($B$3,-2))-SUMIFS(Trips!$J$5:$J$1004,Trips!$B$5:$B$1004,$A71,Trips!$L$5:$L$1004,EDATE($B$3,-2))-SUMIFS(Expenses!$E$5:$E$1004,Expenses!$B$5:$B$1004,$A71,Expenses!$G$5:$G$1004,EDATE($B$3,-2))-Fleet!$O$70*IF(AND(Fleet!$A$70<>"",N(Fleet!$E$70)<=EOMONTH(EDATE($B$3,-2),0),OR(Fleet!$F$70="",N(Fleet!$F$70)>=EDATE($B$3,-2))),1,0))) | L71: =IF($A71="","",SUMIFS(Trips!$M$5:$M$1004,Trips!$B$5:$B$1004,$A71,Trips!$L$5:$L$1004,"<="&$B$3)-SUMIFS(Expenses!$E$5:$E$1004,Expenses!$B$5:$B$1004,$A71,Expenses!$G$5:$G$1004,"<="&$B$3)-Fleet!$O$70*IF(N(Fleet!$E$70)=0,0,MAX(0,(YEAR(IF(Fleet!$F$70="",EOMONTH($B$3,0),MIN(Fleet!$F$70,EOMONTH($B$3,0))))-YEAR(Fleet!$E$70))*12+MONTH(IF(Fleet!$F$70="",EOMONTH($B$3,0),MIN(Fleet!$F$70,EOMONTH($B$3,0))))-MONTH(Fleet!$E$70)+1))) | M71: =IF($A71="","",Fleet!$H$70) | N71: =IF(OR($A71="",N(M71)=0),"",L71/M71) | O71: =IF(OR($A71="",N(C71)=0),"",IF(AND(I71<0,J71<0,K71<0),"REVIEW: 3 losing months",IF(I71<Assumptions!$B$9,"Below net target",IF(E71<Assumptions!$B$8,"Low utilization","On track"))))
A72: =IF(Fleet!A71="","",Fleet!A71) | B72: =IF(Fleet!A71="","",Fleet!B71&" "&Fleet!C71) | C72: =IF($A72="","",IF(AND(Fleet!$A$71<>"",N(Fleet!$E$71)<=EOMONTH($B$3,0),OR(Fleet!$F$71="",N(Fleet!$F$71)>=$B$3)),1,0)) | D72: =IF($A72="","",SUMIFS(Trips!$E$5:$E$1004,Trips!$B$5:$B$1004,$A72,Trips!$L$5:$L$1004,$B$3)) | E72: =IF(OR($A72="",N(C72)=0),"",D72/DAY(EOMONTH($B$3,0))) | F72: =IF($A72="","",SUMIFS(Trips!$H$5:$H$1004,Trips!$B$5:$B$1004,$A72,Trips!$L$5:$L$1004,$B$3)+SUMIFS(Trips!$I$5:$I$1004,Trips!$B$5:$B$1004,$A72,Trips!$L$5:$L$1004,$B$3)) | G72: =IF($A72="","",SUMIFS(Trips!$J$5:$J$1004,Trips!$B$5:$B$1004,$A72,Trips!$L$5:$L$1004,$B$3)+SUMIFS(Expenses!$E$5:$E$1004,Expenses!$B$5:$B$1004,$A72,Expenses!$G$5:$G$1004,$B$3)) | H72: =IF($A72="","",Fleet!$O$71*C72) | I72: =IF($A72="","",F72-G72-H72) | J72: =IF($A72="","",(SUMIFS(Trips!$H$5:$H$1004,Trips!$B$5:$B$1004,$A72,Trips!$L$5:$L$1004,EDATE($B$3,-1))+SUMIFS(Trips!$I$5:$I$1004,Trips!$B$5:$B$1004,$A72,Trips!$L$5:$L$1004,EDATE($B$3,-1))-SUMIFS(Trips!$J$5:$J$1004,Trips!$B$5:$B$1004,$A72,Trips!$L$5:$L$1004,EDATE($B$3,-1))-SUMIFS(Expenses!$E$5:$E$1004,Expenses!$B$5:$B$1004,$A72,Expenses!$G$5:$G$1004,EDATE($B$3,-1))-Fleet!$O$71*IF(AND(Fleet!$A$71<>"",N(Fleet!$E$71)<=EOMONTH(EDATE($B$3,-1),0),OR(Fleet!$F$71="",N(Fleet!$F$71)>=EDATE($B$3,-1))),1,0))) | K72: =IF($A72="","",(SUMIFS(Trips!$H$5:$H$1004,Trips!$B$5:$B$1004,$A72,Trips!$L$5:$L$1004,EDATE($B$3,-2))+SUMIFS(Trips!$I$5:$I$1004,Trips!$B$5:$B$1004,$A72,Trips!$L$5:$L$1004,EDATE($B$3,-2))-SUMIFS(Trips!$J$5:$J$1004,Trips!$B$5:$B$1004,$A72,Trips!$L$5:$L$1004,EDATE($B$3,-2))-SUMIFS(Expenses!$E$5:$E$1004,Expenses!$B$5:$B$1004,$A72,Expenses!$G$5:$G$1004,EDATE($B$3,-2))-Fleet!$O$71*IF(AND(Fleet!$A$71<>"",N(Fleet!$E$71)<=EOMONTH(EDATE($B$3,-2),0),OR(Fleet!$F$71="",N(Fleet!$F$71)>=EDATE($B$3,-2))),1,0))) | L72: =IF($A72="","",SUMIFS(Trips!$M$5:$M$1004,Trips!$B$5:$B$1004,$A72,Trips!$L$5:$L$1004,"<="&$B$3)-SUMIFS(Expenses!$E$5:$E$1004,Expenses!$B$5:$B$1004,$A72,Expenses!$G$5:$G$1004,"<="&$B$3)-Fleet!$O$71*IF(N(Fleet!$E$71)=0,0,MAX(0,(YEAR(IF(Fleet!$F$71="",EOMONTH($B$3,0),MIN(Fleet!$F$71,EOMONTH($B$3,0))))-YEAR(Fleet!$E$71))*12+MONTH(IF(Fleet!$F$71="",EOMONTH($B$3,0),MIN(Fleet!$F$71,EOMONTH($B$3,0))))-MONTH(Fleet!$E$71)+1))) | M72: =IF($A72="","",Fleet!$H$71) | N72: =IF(OR($A72="",N(M72)=0),"",L72/M72) | O72: =IF(OR($A72="",N(C72)=0),"",IF(AND(I72<0,J72<0,K72<0),"REVIEW: 3 losing months",IF(I72<Assumptions!$B$9,"Below net target",IF(E72<Assumptions!$B$8,"Low utilization","On track"))))
